Workbook

Sheet Meter1 TOU Detail
A1: Meter 1 TOU Detail Historical Load & TOU Detail
A2: Service account 8001881589 | Tariff TOU-GS-2-E | Meter 1
A4: Billing Period | B4: Start Date | C4: End Date | D4: Days | E4: Total Load (kWh) | F4: Bill Total ($) | G4: Summer On-Peak kWh | H4: Summer On-Peak Energy $ | I4: Summer Mid-Peak kWh | J4: Summer Mid-Peak Energy $ | K4: Summer Off-Peak kWh | L4: Summer Off-Peak Energy $ | M4: Winter Mid-Peak kWh | N4: Winter Mid-Peak Energy $ | O4: Winter Off-Peak kWh | P4: Winter Off-Peak Energy $ | Q4: Winter Super-Off-Peak kWh | R4: Winter Super-Off-Peak Energy $ | S4: Max Demand (kW) | T4: Base Demand Charge ($) | U4: Summer On-Peak Demand (kW) | V4: Summer On-Peak Demand $ | W4: Winter Mid-Peak Demand (kW) | X4: Winter Mid-Peak Demand $ | Y4: TOU Energy Charges ($) | Z4: Demand Charges ($) | AA4: Other / Residual Charges ($) | AB4: Source | AC4: Data Quality
A5: Oct 2023 | B5: 09/20/2023 | C5: 10/19/2023 | D5: 29 | E5: 7569 | F5: 2199.45 | G5: 358 | H5: 306.92 | I5: 109 | J5: 36.16 | K5: 2265 | L5: 459.02 | M5: 722 | N5: 153.91 | O5: 1767 | P5: 248.3 | Q5: 2348 | R5: 110.59 | S5: 32 | T5: 506.81 | U5: 20 | V5: 60.84 | W5: 24 | X5: 46.33 | Y5: =SUM(H5,J5,L5,N5,P5,R5) -> 1314.9 | Z5: =SUM(T5,V5,X5) -> 613.98 | AA5: =F5-Y5-Z5 -> 270.57 | AB5: https://utilityapi.com/api/v2/files/pdf_bill/1689169/8001881589_2023-09-20_to_2023-10-19.pdf | AC5: Complete
A6: Nov 2023 | B6: 10/19/2023 | C6: 11/20/2023 | D6: 32 | E6: 9408 | F6: 2092.71 | M6: 1361 | N6: 290.11 | O6: 3998 | P6: 561.8 | Q6: 4049 | R6: 190.71 | S6: 39 | T6: 562.14 | W6: 24 | X6: 74.64 | Y6: =SUM(H6,J6,L6,N6,P6,R6) -> 1042.62 | Z6: =SUM(T6,V6,X6) -> 636.78 | AA6: =F6-Y6-Z6 -> 413.31 | AB6: https://utilityapi.com/api/v2/files/pdf_bill/1689169/8001881589_2023-10-19_to_2023-11-20.pdf | AC6: Complete
A7: Dec 2023 | B7: 11/20/2023 | C7: 12/20/2023 | D7: 30 | E7: 11409 | F7: 2449.71 | M7: 1694 | N7: 361.09 | O7: 5123 | P7: 719.89 | Q7: 4592 | R7: 216.28 | S7: 43 | T7: 618.36 | W7: 26 | X7: 80.86 | Y7: =SUM(H7,J7,L7,N7,P7,R7) -> 1297.26 | Z7: =SUM(T7,V7,X7) -> 699.22 | AA7: =F7-Y7-Z7 -> 453.23 | AB7: https://utilityapi.com/api/v2/files/pdf_bill/1689169/8001881589_2023-11-20_to_2023-12-20.pdf | AC7: Complete
A8: Jan 2024 | B8: 12/20/2023 | C8: 01/22/2024 | D8: 33 | E8: 12241 | F8: 2575.94 | M8: 1904 | N8: 396.21 | O8: 5368 | P8: 736.98 | Q8: 4969 | R8: 257.42 | S8: 44 | T8: 628.02 | W8: 24 | X8: 69.9 | Y8: =SUM(H8,J8,L8,N8,P8,R8) -> 1390.61 | Z8: =SUM(T8,V8,X8) -> 697.92 | AA8: =F8-Y8-Z8 -> 487.41 | AB8: https://utilityapi.com/api/v2/files/pdf_bill/1689169/8001881589_2023-12-20_to_2024-01-22.pdf | AC8: Complete
A9: Feb 2024 | B9: 01/22/2024 | C9: 02/21/2024 | D9: 30 | E9: 10734 | F9: 2376.93 | M9: 1517 | N9: 311.44 | O9: 4591 | P9: 622.45 | Q9: 4626 | R9: 251.28 | S9: 46 | T9: 663.94 | W9: 27 | X9: 75.6 | Y9: =SUM(H9,J9,L9,N9,P9,R9) -> 1185.17 | Z9: =SUM(T9,V9,X9) -> 739.54 | AA9: =F9-Y9-Z9 -> 452.22 | AB9: https://utilityapi.com/api/v2/files/pdf_bill/1689169/8001881589_2024-01-22_to_2024-02-21.pdf | AC9: Complete
A10: Mar 2024 | B10: 02/21/2024 | C10: 03/21/2024 | D10: 29 | E10: 7646 | F10: 1802.68 | M10: 1052 | N10: 216.76 | O10: 3377 | P10: 459.26 | Q10: 3217 | R10: 176.58 | S10: 36 | T10: 510.71 | W10: 16 | X10: 44.8 | Y10: =SUM(H10,J10,L10,N10,P10,R10) -> 852.6 | Z10: =SUM(T10,V10,X10) -> 555.51 | AA10: =F10-Y10-Z10 -> 394.57 | AB10: https://utilityapi.com/api/v2/files/pdf_bill/1689169/8001881589_2024-02-21_to_2024-03-21.pdf | AC10: Complete
A11: Apr 2024 | B11: 03/21/2024 | C11: 04/22/2024 | D11: 32 | E11: 6348 | F11: 1532.43 | M11: 902 | N11: 186.19 | O11: 2653 | P11: 361.36 | Q11: 2793 | R11: 154.01 | S11: 28 | T11: 420.28 | W11: 20 | X11: 56 | Y11: =SUM(H11,J11,L11,N11,P11,R11) -> 701.56 | Z11: =SUM(T11,V11,X11) -> 476.28 | AA11: =F11-Y11-Z11 -> 354.59 | AB11: https://utilityapi.com/api/v2/files/pdf_bill/1689169/8001881589_2024-03-21_to_2024-04-22.pdf | AC11: Complete | AD11: May TOU scale factor
A12: May 2024 | B12: 04/22/2024 | C12: 05/21/2024 | D12: 29 | E12: 6057 | F12: 1515.83 | G12: =G13*$AD$12 -> 403.83324 | H12: =H13*$AD$12 -> 343.21338 | I12: =I13*$AD$12 -> 128.62836 | J12: =J13*$AD$12 -> 45.159524 | K12: =K13*$AD$12 -> 2359.6824 | L12: =L13*$AD$12 -> 502.80229 | M12: =M11*$AD$12 -> 449.70072 | N12: =N11*$AD$12 -> 92.826803 | O12: =O11*$AD$12 -> 1322.6785 | P12: =P11*$AD$12 -> 180.15948 | Q12: =Q11*$AD$12 -> 1392.4768 | R12: =R11*$AD$12 -> 76.783157 | S12: =AVERAGE(S11,S13) -> 34.5 | T12: =AVERAGE(T11,T13) -> 553.21 | U12: =U13 -> 29 | V12: =V13 -> 123.97 | W12: =W11 -> 20 | X12: =X11 -> 56 | Y12: =SUM(H12,J12,L12,N12,P12,R12) -> 1240.9446 | Z12: =SUM(T12,V12,X12) -> 733.18 | AA12: =F12-Y12-Z12 -> -458.29464 | AC12: Estimated May TOU: Jun summer components + Apr winter components | AD12: =E12/SUM(G13,I13,K13,M11,O11,Q11) -> 0.49855955
A13: Jun 2024 | B13: 05/21/2024 | C13: 06/20/2024 | D13: 30 | E13: 8802 | F13: 3167.93 | G13: 810 | H13: 688.41 | I13: 258 | J13: 90.58 | K13: 4733 | L13: 1008.51 | M13: 555 | N13: 114.56 | O13: 1023 | P13: 139.34 | Q13: 1423 | R13: 78.46 | S13: 41 | T13: 686.14 | U13: 29 | V13: 123.97 | W13: 26 | X13: 26.69 | Y13: =SUM(H13,J13,L13,N13,P13,R13) -> 2119.86 | Z13: =SUM(T13,V13,X13) -> 836.8 | AA13: =F13-Y13-Z13 -> 211.27 | AB13: https://utilityapi.com/api/v2/files/pdf_bill/1689169/8001881589_2024-05-21_to_2024-06-20.pdf | AC13: Complete
A14: Jul 2024 | B14: 06/20/2024 | C14: 07/23/2024 | D14: 33 | E14: 12723 | F14: 4972.77 | G14: 1450 | H14: 1232.34 | I14: 531 | J14: 186.42 | K14: 10742 | L14: 2288.91 | S14: 51 | T14: 944.34 | U14: 41 | V14: 276.75 | Y14: =SUM(H14,J14,L14,N14,P14,R14) -> 3707.67 | Z14: =SUM(T14,V14,X14) -> 1221.09 | AA14: =F14-Y14-Z14 -> 44.01 | AB14: https://utilityapi.com/api/v2/files/pdf_bill/1689169/8001881589_2024-06-20_to_2024-07-23.pdf | AC14: Complete
A15: Aug 2024 | B15: 07/23/2024 | C15: 08/21/2024 | D15: 29 | E15: 13067 | F15: 5128.28 | G15: 1607 | H15: 1365.77 | I15: 479 | J15: 168.17 | K15: 10981 | L15: 2339.83 | S15: 50 | T15: 931.25 | U15: 41 | V15: 276.75 | Y15: =SUM(H15,J15,L15,N15,P15,R15) -> 3873.77 | Z15: =SUM(T15,V15,X15) -> 1208 | AA15: =F15-Y15-Z15 -> 46.51 | AB15: https://utilityapi.com/api/v2/files/pdf_bill/1689169/8001881589_2024-07-23_to_2024-08-21.pdf | AC15: Complete
A16: Sep 2024 | B16: 08/21/2024 | C16: 09/20/2024 | D16: 30 | E16: 11054 | F16: 4280.39 | G16: 1177 | H16: 1000.32 | I16: 454 | J16: 159.39 | K16: 9423 | L16: 2007.85 | S16: 47 | T16: 804.23 | U16: 28 | V16: 189 | Y16: =SUM(H16,J16,L16,N16,P16,R16) -> 3167.56 | Z16: =SUM(T16,V16,X16) -> 993.23 | AA16: =F16-Y16-Z16 -> 119.6 | AB16: https://utilityapi.com/api/v2/files/pdf_bill/1689169/8001881589_2024-08-21_to_2024-09-20.pdf | AC16: Complete
A17: 12-Period Total | E17: =SUM(E5:E16) -> 117058 | F17: =SUM(F5:F16) -> 34095.05 | G17: =SUM(G5:G16) -> 5805.8332 | H17: =SUM(H5:H16) -> 4936.9734 | I17: =SUM(I5:I16) -> 1959.6284 | J17: =SUM(J5:J16) -> 685.87952 | K17: =SUM(K5:K16) -> 40503.682 | L17: =SUM(L5:L16) -> 8606.9223 | ... R17: =SUM(R5:R16) -> 1512.1132 | Y17: =SUM(Y5:Y16) -> 21894.525 | Z17: =SUM(Z5:Z16) -> 9411.53 | AA17: =SUM(AA5:AA16) -> 2788.9954

Sheet Meter2 TOU Detail
A1: Meter 2 TOU Detail Historical Load & TOU Detail
A2: Service account 8013693720 | Tariff TOU-8-D | Meter 2
A4: Billing Period | B4: Start Date | C4: End Date | D4: Days | E4: Total Load (kWh) | F4: Bill Total ($) | G4: Summer On-Peak kWh | H4: Summer On-Peak Energy $ | I4: Summer Mid-Peak kWh | J4: Summer Mid-Peak Energy $ | K4: Summer Off-Peak kWh | L4: Summer Off-Peak Energy $ | M4: Winter Mid-Peak kWh | N4: Winter Mid-Peak Energy $ | O4: Winter Off-Peak kWh | P4: Winter Off-Peak Energy $ | Q4: Winter Super-Off-Peak kWh | R4: Winter Super-Off-Peak Energy $ | S4: Max Demand (kW) | T4: Base Demand Charge ($) | U4: Summer On-Peak Demand (kW) | V4: Summer On-Peak Demand $ | W4: Winter Mid-Peak Demand (kW) | X4: Winter Mid-Peak Demand $ | Y4: TOU Energy Charges ($) | Z4: Demand Charges ($) | AA4: Other / Residual Charges ($) | AB4: Source | AC4: Data Quality
A5: Oct 2023 | B5: 09/20/2023 | C5: 10/19/2023 | D5: 29 | E5: 42448 | F5: 18373.78 | G5: 86 | H5: 14.95 | I5: 37 | J5: 5.93 | K5: 16852 | L5: 2002.19 | M5: 389 | N5: 51.56 | O5: 2382 | P5: 314.49 | Q5: 22702 | R5: 690.37 | S5: 552 | T5: 12811.13 | U5: 12 | V5: 115.89 | W5: 142 | X5: 689.24 | Y5: =SUM(H5,J5,L5,N5,P5,R5) -> 3079.49 | Z5: =SUM(T5,V5,X5) -> 13616.26 | AA5: =F5-Y5-Z5 -> 1678.03 | AB5: https://utilityapi.com/api/v2/files/pdf_bill/1689171/8013693720_2023-09-20_to_2023-10-19.pdf | AC5: Complete
A6: Nov 2023 | B6: 10/19/2023 | C6: 11/20/2023 | D6: 32 | E6: 51688 | F6: 19755.43 | M6: 293 | N6: 38.83 | O6: 3945 | P6: 520.86 | Q6: 47450 | R6: 1442.95 | S6: 622 | T6: 14032.88 | W6: 47 | X6: 367.54 | Y6: =SUM(H6,J6,L6,N6,P6,R6) -> 2002.64 | Z6: =SUM(T6,V6,X6) -> 14400.42 | AA6: =F6-Y6-Z6 -> 3352.37 | AB6: https://utilityapi.com/api/v2/files/pdf_bill/1689171/8013693720_2023-10-19_to_2023-11-20.pdf | AC6: Complete
A7: Dec 2023 | B7: 11/20/2023 | C7: 12/20/2023 | D7: 30 | E7: 41843 | F7: 17151.12 | M7: 330 | N7: 43.74 | O7: 3938 | P7: 519.93 | Q7: 37575 | R7: 1142.66 | S7: 513 | T7: 12169.91 | W7: 115 | X7: 899.3 | Y7: =SUM(H7,J7,L7,N7,P7,R7) -> 1706.33 | Z7: =SUM(T7,V7,X7) -> 13069.21 | AA7: =F7-Y7-Z7 -> 2375.58 | AB7: https://utilityapi.com/api/v2/files/pdf_bill/1689171/8013693720_2023-11-20_to_2023-12-20.pdf | AC7: Complete
A8: Jan 2024 | B8: 12/20/2023 | C8: 01/22/2024 | D8: 33 | E8: 42603 | F8: 20168.76 | M8: 233 | N8: 30.29 | O8: 3868 | P8: 499.88 | Q8: 38502 | R8: 1308.51 | S8: 655 | T8: 15251.57 | W8: 43 | X8: 315.19 | Y8: =SUM(H8,J8,L8,N8,P8,R8) -> 1838.68 | Z8: =SUM(T8,V8,X8) -> 15566.76 | AA8: =F8-Y8-Z8 -> 2763.32 | AB8: https://utilityapi.com/api/v2/files/pdf_bill/1689171/8013693720_2023-12-20_to_2024-01-22.pdf | AC8: Complete
A9: Feb 2024 | B9: 01/22/2024 | C9: 02/21/2024 | D9: 30 | E9: 38192 | F9: 19764.91 | M9: 285 | N9: 36.69 | O9: 3399 | P9: 435.04 | Q9: 34508 | R9: 1249.19 | S9: 640 | T9: 15223.5 | W9: 46 | X9: 324.3 | Y9: =SUM(H9,J9,L9,N9,P9,R9) -> 1720.92 | Z9: =SUM(T9,V9,X9) -> 15547.8 | AA9: =F9-Y9-Z9 -> 2496.19 | AB9: https://utilityapi.com/api/v2/files/pdf_bill/1689171/8013693720_2024-01-22_to_2024-02-21.pdf | AC9: Complete
A10: Mar 2024 | B10: 02/21/2024 | C10: 03/21/2024 | D10: 29 | E10: 44803 | F10: 18580.72 | M10: 385 | N10: 49.77 | O10: 4449 | P10: 571.18 | Q10: 39969 | R10: 1460 | S10: 500 | T10: 12987.94 | W10: 170 | X10: 1199.67 | Y10: =SUM(H10,J10,L10,N10,P10,R10) -> 2080.95 | Z10: =SUM(T10,V10,X10) -> 14187.61 | AA10: =F10-Y10-Z10 -> 2312.16 | AB10: https://utilityapi.com/api/v2/files/pdf_bill/1689171/8013693720_2024-02-21_to_2024-03-21.pdf | AC10: Complete
A11: Apr 2024 | B11: 03/21/2024 | C11: 04/22/2024 | D11: 32 | E11: 34404 | F11: 15527.63 | M11: 415 | N11: 53.69 | O11: 3441 | P11: 442.48 | Q11: 30548 | R11: 1119.89 | S11: 442 | T11: 11164.64 | W11: 97 | X11: 684.82 | Y11: =SUM(H11,J11,L11,N11,P11,R11) -> 1616.06 | Z11: =SUM(T11,V11,X11) -> 11849.46 | AA11: =F11-Y11-Z11 -> 2062.11 | AB11: https://utilityapi.com/api/v2/files/pdf_bill/1689171/8013693720_2024-03-21_to_2024-04-22.pdf | AC11: Complete
A12: May 2024 | B12: 04/22/2024 | C12: 05/21/2024 | D12: 29 | E12: 45163 | F12: 16968.39 | M12: 298 | N12: 38.56 | O12: 4070 | P12: 523.36 | Q12: 40795 | R12: 1495.54 | S12: 466 | T12: 11641.9 | W12: 84 | X12: 593.04 | Y12: =SUM(H12,J12,L12,N12,P12,R12) -> 2057.46 | Z12: =SUM(T12,V12,X12) -> 12234.94 | AA12: =F12-Y12-Z12 -> 2675.99 | AB12: https://utilityapi.com/api/v2/files/pdf_bill/1689171/8013693720_2024-04-22_to_2024-05-21.pdf | AC12: Complete
A13: Jun 2024 | B13: 05/21/2024 | C13: 06/20/2024 | D13: 30 | E13: 41942 | F13: 17606.49 | G13: 198 | H13: 31.61 | I13: 58 | J13: 8.57 | K13: 24786 | L13: 2792.89 | M13: 122 | N13: 15.78 | O13: 1568 | P13: 201.63 | Q13: 15210 | R13: 557.6 | S13: 471 | T13: 11775.4 | U13: 36 | V13: 490.2 | W13: 19 | X13: 49.18 | Y13: =SUM(H13,J13,L13,N13,P13,R13) -> 3608.08 | Z13: =SUM(T13,V13,X13) -> 12314.78 | AA13: =F13-Y13-Z13 -> 1683.63 | AB13: https://utilityapi.com/api/v2/files/pdf_bill/1689171/8013693720_2024-05-21_to_2024-06-20.pdf | AC13: Complete
A14: Jul 2024 | B14: 06/20/2024 | C14: 07/23/2024 | D14: 33 | E14: 68386 | F14: 28541.31 | G14: 625 | H14: 99.79 | I14: 192 | J14: 28.39 | K14: 67569 | L14: 7613.67 | S14: 725 | T14: 18496 | U14: 53 | V14: 1139.5 | Y14: =SUM(H14,J14,L14,N14,P14,R14) -> 7741.85 | Z14: =SUM(T14,V14,X14) -> 19635.5 | AA14: =F14-Y14-Z14 -> 1163.96 | AB14: https://utilityapi.com/api/v2/files/pdf_bill/1689171/8013693720_2024-06-20_to_2024-07-23.pdf | AC14: Complete
A15: Aug 2024 | B15: 07/23/2024 | C15: 08/21/2024 | D15: 29 | E15: 67656 | F15: 29001.91 | G15: 3285 | H15: 524.48 | I15: 152 | J15: 22.47 | K15: 64219 | L15: 7236.2 | S15: 705 | T15: 18490.2 | U15: 75 | V15: 1612.5 | Y15: =SUM(H15,J15,L15,N15,P15,R15) -> 7783.15 | Z15: =SUM(T15,V15,X15) -> 20102.7 | AA15: =F15-Y15-Z15 -> 1116.06 | AB15: https://utilityapi.com/api/v2/files/pdf_bill/1689171/8013693720_2024-07-23_to_2024-08-21.pdf | AC15: Complete
A16: Sep 2024 | B16: 08/21/2024 | C16: 09/20/2024 | D16: 30 | E16: 73315 | F16: 31196.61 | G16: 2605 | H16: 415.92 | I16: 175 | J16: 25.87 | K16: 70535 | L16: 7947.88 | S16: 730 | T16: 19583.2 | U16: 98 | V16: 2107 | Y16: =SUM(H16,J16,L16,N16,P16,R16) -> 8389.67 | Z16: =SUM(T16,V16,X16) -> 21690.2 | AA16: =F16-Y16-Z16 -> 1116.74 | AB16: https://utilityapi.com/api/v2/files/pdf_bill/1689171/8013693720_2024-08-21_to_2024-09-20.pdf | AC16: Complete
A17: 12-Period Total | E17: =SUM(E5:E16) -> 592443 | F17: =SUM(F5:F16) -> 252637.06 | G17: =SUM(G5:G16) -> 6799 | H17: =SUM(H5:H16) -> 1086.75 | I17: =SUM(I5:I16) -> 614 | J17: =SUM(J5:J16) -> 91.23 | K17: =SUM(K5:K16) -> 243961 | L17: =SUM(L5:L16) -> 27592.83 | ... R17: =SUM(R5:R16) -> 10466.71 | Y17: =SUM(Y5:Y16) -> 43625.28 | Z17: =SUM(Z5:Z16) -> 184215.64 | AA17: =SUM(AA5:AA16) -> 24796.14

Sheet Combined TOU Profile
A1: Barstow Historical Load & TOU Profile
A2: Two-account baseline: Meter 1 + Meter 2. Annual electricity consumption = 709,501 kWh.
A4: Billing Period | B4: Start Date | C4: End Date | D4: Meter 1 Load (kWh) | E4: Meter 2 Load (kWh) | F4: Combined Load (kWh) | G4: On-Peak kWh | H4: Mid-Peak kWh | I4: Off-Peak kWh | J4: Super-Off-Peak kWh | K4: Meter 1 Max Demand kW | L4: Meter 2 Max Demand kW | M4: Site Max-Demand Indicator kW | N4: Meter 1 TOU Peak Demand kW | O4: Meter 2 TOU Peak Demand kW | P4: Energy Charges ($) | Q4: Demand Charges ($) | R4: Bill Total ($) | S4: Other / Residual Charges ($) | T4: TOU kWh Reconciliation | U4: Data Quality | V4: Notes
A5: Oct 2023 | B5: 09/20/2023 | C5: 10/19/2023 | D5: 7569 | E5: 42448 | F5: =D5+E5 -> 50017 | G5: ='Meter1 TOU Detail'!G5+'Meter2 TOU Detail'!G5 -> 444 | H5: =SUM('Meter1 TOU Detail'!I5,'Meter1 TOU Detail'!M5,'Meter2 TOU Detail'!I5,'Meter2 TOU Detail'!M5) -> 1257 | I5: =SUM('Meter1 TOU Detail'!K5,'Meter1 TOU Detail'!O5,'Meter2 TOU Detail'!K5,'Meter2 TOU Detail'!O5) -> 23266 | J5: ='Meter1 TOU Detail'!Q5+'Meter2 TOU Detail'!Q5 -> 25050 | K5: ='Meter1 TOU Detail'!S5 -> 32 | L5: ='Meter2 TOU Detail'!S5 -> 552 | M5: =MAX(K5:L5) -> 552 | N5: =MAX('Meter1 TOU Detail'!U5,'Meter1 TOU Detail'!W5) -> 24 | O5: =MAX('Meter2 TOU Detail'!U5,'Meter2 TOU Detail'!W5) -> 142 | P5: ='Meter1 TOU Detail'!Y5+'Meter2 TOU Detail'!Y5 -> 4394.39 | Q5: ='Meter1 TOU Detail'!Z5+'Meter2 TOU Detail'!Z5 -> 14230.24 | R5: ='Meter1 TOU Detail'!F5+'Meter2 TOU Detail'!F5 -> 20573.23 | S5: =R5-P5-Q5 -> 1948.6 | T5: =SUM(G5:J5)-F5 -> 0 | U5: Complete | V5: Site max-demand indicator is MAX(account peaks), not a coincident summed site peak.
A6: Nov 2023 | B6: 10/19/2023 | C6: 11/20/2023 | D6: 9408 | E6: 51688 | F6: =D6+E6 -> 61096 | G6: ='Meter1 TOU Detail'!G6+'Meter2 TOU Detail'!G6 -> 0 | H6: =SUM('Meter1 TOU Detail'!I6,'Meter1 TOU Detail'!M6,'Meter2 TOU Detail'!I6,'Meter2 TOU Detail'!M6) -> 1654 | I6: =SUM('Meter1 TOU Detail'!K6,'Meter1 TOU Detail'!O6,'Meter2 TOU Detail'!K6,'Meter2 TOU Detail'!O6) -> 7943 | J6: ='Meter1 TOU Detail'!Q6+'Meter2 TOU Detail'!Q6 -> 51499 | K6: ='Meter1 TOU Detail'!S6 -> 39 | L6: ='Meter2 TOU Detail'!S6 -> 622 | M6: =MAX(K6:L6) -> 622 | N6: =MAX('Meter1 TOU Detail'!U6,'Meter1 TOU Detail'!W6) -> 24 | O6: =MAX('Meter2 TOU Detail'!U6,'Meter2 TOU Detail'!W6) -> 47 | P6: ='Meter1 TOU Detail'!Y6+'Meter2 TOU Detail'!Y6 -> 3045.26 | Q6: ='Meter1 TOU Detail'!Z6+'Meter2 TOU Detail'!Z6 -> 15037.2 | R6: ='Meter1 TOU Detail'!F6+'Meter2 TOU Detail'!F6 -> 21848.14 | S6: =R6-P6-Q6 -> 3765.68 | T6: =SUM(G6:J6)-F6 -> 0 | U6: Complete | V6: Site max-demand indicator is MAX(account peaks), not a coincident summed site peak.
A7: Dec 2023 | B7: 11/20/2023 | C7: 12/20/2023 | D7: 11409 | E7: 41843 | F7: =D7+E7 -> 53252 | G7: ='Meter1 TOU Detail'!G7+'Meter2 TOU Detail'!G7 -> 0 | H7: =SUM('Meter1 TOU Detail'!I7,'Meter1 TOU Detail'!M7,'Meter2 TOU Detail'!I7,'Meter2 TOU Detail'!M7) -> 2024 | I7: =SUM('Meter1 TOU Detail'!K7,'Meter1 TOU Detail'!O7,'Meter2 TOU Detail'!K7,'Meter2 TOU Detail'!O7) -> 9061 | J7: ='Meter1 TOU Detail'!Q7+'Meter2 TOU Detail'!Q7 -> 42167 | K7: ='Meter1 TOU Detail'!S7 -> 43 | L7: ='Meter2 TOU Detail'!S7 -> 513 | M7: =MAX(K7:L7) -> 513 | N7: =MAX('Meter1 TOU Detail'!U7,'Meter1 TOU Detail'!W7) -> 26 | O7: =MAX('Meter2 TOU Detail'!U7,'Meter2 TOU Detail'!W7) -> 115 | P7: ='Meter1 TOU Detail'!Y7+'Meter2 TOU Detail'!Y7 -> 3003.59 | Q7: ='Meter1 TOU Detail'!Z7+'Meter2 TOU Detail'!Z7 -> 13768.43 | R7: ='Meter1 TOU Detail'!F7+'Meter2 TOU Detail'!F7 -> 19600.83 | S7: =R7-P7-Q7 -> 2828.81 | T7: =SUM(G7:J7)-F7 -> 0 | U7: Complete | V7: Site max-demand indicator is MAX(account peaks), not a coincident summed site peak.
A8: Jan 2024 | B8: 12/20/2023 | C8: 01/22/2024 | D8: 12241 | E8: 42603 | F8: =D8+E8 -> 54844 | G8: ='Meter1 TOU Detail'!G8+'Meter2 TOU Detail'!G8 -> 0 | H8: =SUM('Meter1 TOU Detail'!I8,'Meter1 TOU Detail'!M8,'Meter2 TOU Detail'!I8,'Meter2 TOU Detail'!M8) -> 2137 | I8: =SUM('Meter1 TOU Detail'!K8,'Meter1 TOU Detail'!O8,'Meter2 TOU Detail'!K8,'Meter2 TOU Detail'!O8) -> 9236 | J8: ='Meter1 TOU Detail'!Q8+'Meter2 TOU Detail'!Q8 -> 43471 | K8: ='Meter1 TOU Detail'!S8 -> 44 | L8: ='Meter2 TOU Detail'!S8 -> 655 | M8: =MAX(K8:L8) -> 655 | N8: =MAX('Meter1 TOU Detail'!U8,'Meter1 TOU Detail'!W8) -> 24 | O8: =MAX('Meter2 TOU Detail'!U8,'Meter2 TOU Detail'!W8) -> 43 | P8: ='Meter1 TOU Detail'!Y8+'Meter2 TOU Detail'!Y8 -> 3229.29 | Q8: ='Meter1 TOU Detail'!Z8+'Meter2 TOU Detail'!Z8 -> 16264.68 | R8: ='Meter1 TOU Detail'!F8+'Meter2 TOU Detail'!F8 -> 22744.7 | S8: =R8-P8-Q8 -> 3250.73 | T8: =SUM(G8:J8)-F8 -> 0 | U8: Complete | V8: Site max-demand indicator is MAX(account peaks), not a coincident summed site peak.
A9: Feb 2024 | B9: 01/22/2024 | C9: 02/21/2024 | D9: 10734 | E9: 38192 | F9: =D9+E9 -> 48926 | G9: ='Meter1 TOU Detail'!G9+'Meter2 TOU Detail'!G9 -> 0 | H9: =SUM('Meter1 TOU Detail'!I9,'Meter1 TOU Detail'!M9,'Meter2 TOU Detail'!I9,'Meter2 TOU Detail'!M9) -> 1802 | I9: =SUM('Meter1 TOU Detail'!K9,'Meter1 TOU Detail'!O9,'Meter2 TOU Detail'!K9,'Meter2 TOU Detail'!O9) -> 7990 | J9: ='Meter1 TOU Detail'!Q9+'Meter2 TOU Detail'!Q9 -> 39134 | K9: ='Meter1 TOU Detail'!S9 -> 46 | L9: ='Meter2 TOU Detail'!S9 -> 640 | M9: =MAX(K9:L9) -> 640 | N9: =MAX('Meter1 TOU Detail'!U9,'Meter1 TOU Detail'!W9) -> 27 | O9: =MAX('Meter2 TOU Detail'!U9,'Meter2 TOU Detail'!W9) -> 46 | P9: ='Meter1 TOU Detail'!Y9+'Meter2 TOU Detail'!Y9 -> 2906.09 | Q9: ='Meter1 TOU Detail'!Z9+'Meter2 TOU Detail'!Z9 -> 16287.34 | R9: ='Meter1 TOU Detail'!F9+'Meter2 TOU Detail'!F9 -> 22141.84 | S9: =R9-P9-Q9 -> 2948.41 | T9: =SUM(G9:J9)-F9 -> 0 | U9: Complete | V9: Site max-demand indicator is MAX(account peaks), not a coincident summed site peak.
A10: Mar 2024 | B10: 02/21/2024 | C10: 03/21/2024 | D10: 7646 | E10: 44803 | F10: =D10+E10 -> 52449 | G10: ='Meter1 TOU Detail'!G10+'Meter2 TOU Detail'!G10 -> 0 | H10: =SUM('Meter1 TOU Detail'!I10,'Meter1 TOU Detail'!M10,'Meter2 TOU Detail'!I10,'Meter2 TOU Detail'!M10) -> 1437 | I10: =SUM('Meter1 TOU Detail'!K10,'Meter1 TOU Detail'!O10,'Meter2 TOU Detail'!K10,'Meter2 TOU Detail'!O10) -> 7826 | J10: ='Meter1 TOU Detail'!Q10+'Meter2 TOU Detail'!Q10 -> 43186 | K10: ='Meter1 TOU Detail'!S10 -> 36 | L10: ='Meter2 TOU Detail'!S10 -> 500 | M10: =MAX(K10:L10) -> 500 | N10: =MAX('Meter1 TOU Detail'!U10,'Meter1 TOU Detail'!W10) -> 16 | O10: =MAX('Meter2 TOU Detail'!U10,'Meter2 TOU Detail'!W10) -> 170 | P10: ='Meter1 TOU Detail'!Y10+'Meter2 TOU Detail'!Y10 -> 2933.55 | Q10: ='Meter1 TOU Detail'!Z10+'Meter2 TOU Detail'!Z10 -> 14743.12 | R10: ='Meter1 TOU Detail'!F10+'Meter2 TOU Detail'!F10 -> 20383.4 | S10: =R10-P10-Q10 -> 2706.73 | T10: =SUM(G10:J10)-F10 -> 0 | U10: Complete | V10: Site max-demand indicator is MAX(account peaks), not a coincident summed site peak.
A11: Apr 2024 | B11: 03/21/2024 | C11: 04/22/2024 | D11: 6348 | E11: 34404 | F11: =D11+E11 -> 40752 | G11: ='Meter1 TOU Detail'!G11+'Meter2 TOU Detail'!G11 -> 0 | H11: =SUM('Meter1 TOU Detail'!I11,'Meter1 TOU Detail'!M11,'Meter2 TOU Detail'!I11,'Meter2 TOU Detail'!M11) -> 1317 | I11: =SUM('Meter1 TOU Detail'!K11,'Meter1 TOU Detail'!O11,'Meter2 TOU Detail'!K11,'Meter2 TOU Detail'!O11) -> 6094 | J11: ='Meter1 TOU Detail'!Q11+'Meter2 TOU Detail'!Q11 -> 33341 | K11: ='Meter1 TOU Detail'!S11 -> 28 | L11: ='Meter2 TOU Detail'!S11 -> 442 | M11: =MAX(K11:L11) -> 442 | N11: =MAX('Meter1 TOU Detail'!U11,'Meter1 TOU Detail'!W11) -> 20 | O11: =MAX('Meter2 TOU Detail'!U11,'Meter2 TOU Detail'!W11) -> 97 | P11: ='Meter1 TOU Detail'!Y11+'Meter2 TOU Detail'!Y11 -> 2317.62 | Q11: ='Meter1 TOU Detail'!Z11+'Meter2 TOU Detail'!Z11 -> 12325.74 | R11: ='Meter1 TOU Detail'!F11+'Meter2 TOU Detail'!F11 -> 17060.06 | S11: =R11-P11-Q11 -> 2416.7 | T11: =SUM(G11:J11)-F11 -> 0 | U11: Complete | V11: Site max-demand indicator is MAX(account peaks), not a coincident summed site peak.
A12: May 2024 | B12: 04/22/2024 | C12: 05/21/2024 | D12: 6057 | E12: 45163 | F12: =D12+E12 -> 51220 | G12: ='Meter1 TOU Detail'!G12+'Meter2 TOU Detail'!G12 -> 403.83324 | H12: =SUM('Meter1 TOU Detail'!I12,'Meter1 TOU Detail'!M12,'Meter2 TOU Detail'!I12,'Meter2 TOU Detail'!M12) -> 876.32908 | I12: =SUM('Meter1 TOU Detail'!K12,'Meter1 TOU Detail'!O12,'Meter2 TOU Detail'!K12,'Meter2 TOU Detail'!O12) -> 7752.3609 | J12: ='Meter1 TOU Detail'!Q12+'Meter2 TOU Detail'!Q12 -> 42187.477 | K12: ='Meter1 TOU Detail'!S12 -> 34.5 | L12: ='Meter2 TOU Detail'!S12 -> 466 | M12: =MAX(K12:L12) -> 466 | N12: =MAX('Meter1 TOU Detail'!U12,'Meter1 TOU Detail'!W12) -> 29 | O12: =MAX('Meter2 TOU Detail'!U12,'Meter2 TOU Detail'!W12) -> 84 | P12: ='Meter1 TOU Detail'!Y12+'Meter2 TOU Detail'!Y12 -> 3298.4046 | Q12: ='Meter1 TOU Detail'!Z12+'Meter2 TOU Detail'!Z12 -> 12968.12 | R12: ='Meter1 TOU Detail'!F12+'Meter2 TOU Detail'!F12 -> 18484.22 | S12: =R12-P12-Q12 -> 2217.6954 | T12: =SUM(G12:J12)-F12 -> 0 | U12: Estimated — Meter1 May TOU from adjacent periods | V12: Meter 1 May TOU estimated using adjacent Apr/Jun periods and scaled to known 6,057-kWh total; 2957 remains actual source data. Site max-demand indicator is MAX(account peaks), not coincident summed demand.
A13: Jun 2024 | B13: 05/21/2024 | C13: 06/20/2024 | D13: 8802 | E13: 41942 | F13: =D13+E13 -> 50744 | G13: ='Meter1 TOU Detail'!G13+'Meter2 TOU Detail'!G13 -> 1008 | H13: =SUM('Meter1 TOU Detail'!I13,'Meter1 TOU Detail'!M13,'Meter2 TOU Detail'!I13,'Meter2 TOU Detail'!M13) -> 993 | I13: =SUM('Meter1 TOU Detail'!K13,'Meter1 TOU Detail'!O13,'Meter2 TOU Detail'!K13,'Meter2 TOU Detail'!O13) -> 32110 | J13: ='Meter1 TOU Detail'!Q13+'Meter2 TOU Detail'!Q13 -> 16633 | K13: ='Meter1 TOU Detail'!S13 -> 41 | L13: ='Meter2 TOU Detail'!S13 -> 471 | M13: =MAX(K13:L13) -> 471 | N13: =MAX('Meter1 TOU Detail'!U13,'Meter1 TOU Detail'!W13) -> 29 | O13: =MAX('Meter2 TOU Detail'!U13,'Meter2 TOU Detail'!W13) -> 36 | P13: ='Meter1 TOU Detail'!Y13+'Meter2 TOU Detail'!Y13 -> 5727.94 | Q13: ='Meter1 TOU Detail'!Z13+'Meter2 TOU Detail'!Z13 -> 13151.58 | R13: ='Meter1 TOU Detail'!F13+'Meter2 TOU Detail'!F13 -> 20774.42 | S13: =R13-P13-Q13 -> 1894.9 | T13: =SUM(G13:J13)-F13 -> 0 | U13: Complete | V13: Site max-demand indicator is MAX(account peaks), not a coincident summed site peak.
A14: Jul 2024 | B14: 06/20/2024 | C14: 07/23/2024 | D14: 12723 | E14: 68386 | F14: =D14+E14 -> 81109 | G14: ='Meter1 TOU Detail'!G14+'Meter2 TOU Detail'!G14 -> 2075 | H14: =SUM('Meter1 TOU Detail'!I14,'Meter1 TOU Detail'!M14,'Meter2 TOU Detail'!I14,'Meter2 TOU Detail'!M14) -> 723 | I14: =SUM('Meter1 TOU Detail'!K14,'Meter1 TOU Detail'!O14,'Meter2 TOU Detail'!K14,'Meter2 TOU Detail'!O14) -> 78311 | J14: ='Meter1 TOU Detail'!Q14+'Meter2 TOU Detail'!Q14 -> 0 | K14: ='Meter1 TOU Detail'!S14 -> 51 | L14: ='Meter2 TOU Detail'!S14 -> 725 | M14: =MAX(K14:L14) -> 725 | N14: =MAX('Meter1 TOU Detail'!U14,'Meter1 TOU Detail'!W14) -> 41 | O14: =MAX('Meter2 TOU Detail'!U14,'Meter2 TOU Detail'!W14) -> 53 | P14: ='Meter1 TOU Detail'!Y14+'Meter2 TOU Detail'!Y14 -> 11449.52 | Q14: ='Meter1 TOU Detail'!Z14+'Meter2 TOU Detail'!Z14 -> 20856.59 | R14: ='Meter1 TOU Detail'!F14+'Meter2 TOU Detail'!F14 -> 33514.08 | S14: =R14-P14-Q14 -> 1207.97 | T14: =SUM(G14:J14)-F14 -> 0 | U14: Complete | V14: Site max-demand indicator is MAX(account peaks), not a coincident summed site peak.
A15: Aug 2024 | B15: 07/23/2024 | C15: 08/21/2024 | D15: 13067 | E15: 67656 | F15: =D15+E15 -> 80723 | G15: ='Meter1 TOU Detail'!G15+'Meter2 TOU Detail'!G15 -> 4892 | H15: =SUM('Meter1 TOU Detail'!I15,'Meter1 TOU Detail'!M15,'Meter2 TOU Detail'!I15,'Meter2 TOU Detail'!M15) -> 631 | I15: =SUM('Meter1 TOU Detail'!K15,'Meter1 TOU Detail'!O15,'Meter2 TOU Detail'!K15,'Meter2 TOU Detail'!O15) -> 75200 | J15: ='Meter1 TOU Detail'!Q15+'Meter2 TOU Detail'!Q15 -> 0 | K15: ='Meter1 TOU Detail'!S15 -> 50 | L15: ='Meter2 TOU Detail'!S15 -> 705 | M15: =MAX(K15:L15) -> 705 | N15: =MAX('Meter1 TOU Detail'!U15,'Meter1 TOU Detail'!W15) -> 41 | O15: =MAX('Meter2 TOU Detail'!U15,'Meter2 TOU Detail'!W15) -> 75 | P15: ='Meter1 TOU Detail'!Y15+'Meter2 TOU Detail'!Y15 -> 11656.92 | Q15: ='Meter1 TOU Detail'!Z15+'Meter2 TOU Detail'!Z15 -> 21310.7 | R15: ='Meter1 TOU Detail'!F15+'Meter2 TOU Detail'!F15 -> 34130.19 | S15: =R15-P15-Q15 -> 1162.57 | T15: =SUM(G15:J15)-F15 -> 0 | U15: Complete | V15: Site max-demand indicator is MAX(account peaks), not a coincident summed site peak.
A16: Sep 2024 | B16: 08/21/2024 | C16: 09/20/2024 | D16: 11054 | E16: 73315 | F16: =D16+E16 -> 84369 | G16: ='Meter1 TOU Detail'!G16+'Meter2 TOU Detail'!G16 -> 3782 | H16: =SUM('Meter1 TOU Detail'!I16,'Meter1 TOU Detail'!M16,'Meter2 TOU Detail'!I16,'Meter2 TOU Detail'!M16) -> 629 | I16: =SUM('Meter1 TOU Detail'!K16,'Meter1 TOU Detail'!O16,'Meter2 TOU Detail'!K16,'Meter2 TOU Detail'!O16) -> 79958 | J16: ='Meter1 TOU Detail'!Q16+'Meter2 TOU Detail'!Q16 -> 0 | K16: ='Meter1 TOU Detail'!S16 -> 47 | L16: ='Meter2 TOU Detail'!S16 -> 730 | M16: =MAX(K16:L16) -> 730 | N16: =MAX('Meter1 TOU Detail'!U16,'Meter1 TOU Detail'!W16) -> 28 | O16: =MAX('Meter2 TOU Detail'!U16,'Meter2 TOU Detail'!W16) -> 98 | P16: ='Meter1 TOU Detail'!Y16+'Meter2 TOU Detail'!Y16 -> 11557.23 | Q16: ='Meter1 TOU Detail'!Z16+'Meter2 TOU Detail'!Z16 -> 22683.43 | R16: ='Meter1 TOU Detail'!F16+'Meter2 TOU Detail'!F16 -> 35477 | S16: =R16-P16-Q16 -> 1236.34 | T16: =SUM(G16:J16)-F16 -> 0 | U16: Complete | V16: Site max-demand indicator is MAX(account peaks), not a coincident summed site peak.
A17: 12-Period Total / Summary | D17: =SUM(D5:D16) -> 117058 | E17: =SUM(E5:E16) -> 592443 | F17: =SUM(F5:F16) -> 709501 | G17: =SUM(G5:G16) -> 12604.833 | H17: =SUM(H5:H16) -> 15480.329 | I17: =SUM(I5:I16) -> 344747.36 | J17: =SUM(J5:J16) -> 336668.48 | K17: =MAX(K5:K16) -> 51 | L17: =MAX(L5:L16) -> 730 | M17: =MAX(M5:M16) -> 730 | N17: =MAX(N5:N16) -> 41 | O17: =MAX(O5:O16) -> 170 | P17: =SUM(P5:P16) -> 65519.805 | Q17: =SUM(Q5:Q16) -> 193627.17 | R17: =SUM(R5:R16) -> 286732.11 | S17: =SUM(S5:S16) -> 27585.135 | U17: Annual load verified

Sheet Documentation
A1: Barstow Historical Load & TOU Profile — Documentation
A3: Item | B3: Definition / Method
A4: Baseline window | B4: 12 billing cycles ending Oct 2023 through Sep 2024.
A5: Verified annual electricity consumption | B5: 709,501 kWh = 117,058 kWh (Meter 1) + 592,443 kWh (Meter 2). This is electricity load, not PV generation.
A6: On-Peak kWh | B6: Summer On-Peak usage from the source utility records.
A7: Mid-Peak kWh | B7: Summer Mid-Peak + Winter Mid-Peak usage.
A8: Off-Peak kWh | B8: Summer Off-Peak + Winter Off-Peak usage.
A9: Super-Off-Peak kWh | B9: Winter Super-Off-Peak usage.
A10: TOU peak demand | B10: Summer On-Peak Demand kW in summer; Winter Mid-Peak Demand kW in winter/mixed periods.
A11: Site max-demand indicator | B11: MAX of the two account-level monthly maximum demands.
A12: Energy charges | B12: Sum of the available seasonal TOU energy-charge fields in each bill record.
A13: May 2024 estimation | B13: Meter 1 May 2024 total load (6,057 kWh) and bill total are observed. Missing TOU detail is estimated from the immediately adjacent Apr and Jun 2024 periods. Seasonal components are taken from the nearest applicable adjacent period and proportionally scaled so estimated TOU kWh reconcile exactly to the observed 6,057-kWh May total. Max demand/base demand charge use the Apr–Jun average.
A14: Residual charges | B14: Bill total minus extracted TOU energy charges minus extracted demand charges; may include customer, taxes, reactive/other charges not separately represented in the source columns.

Sheet Model Assumptions
A1: Barstow PV & ESS Sizing Model — Assumptions
A3: Category | B3: Input | C3: Value | D3: Unit | E3: Status | F3: Basis / Note
A4: Load | B4: Verified annual load | C4: 709501 | D4: kWh/year | E4: Verified | F4: 12-period historical baseline
A5: PV | B5: Panel nameplate | C5: 0.485 | D5: kW DC/panel | E5: Specified | F5: 485 W panel
A6: PV | B6: Reference PV capacity | C6: 485 | D6: kW DC | E6: Historical modeled | F6: ETB PV configuration
A7: PV | B7: Reference annual PV generation | C7: 847503 | D7: kWh/year | E7: Historical modeled | F7: ETB modeled generation
A8: PV | B8: Reference panel count | C8: 1000 | D8: panels | E8: Specified | F8: 485 kW / 0.485 kW per panel
A9: PV | B9: Minimum annual coverage | C9: 1 | D9: x | E9: Constraint | F9: Annual PV generation must be >= verified annual load
A10: ESS | B10: Battery sizing-unit energy | C10: 215.04 | D10: kWh/unit | E10: Product-source basis | F10: 215.04 kWh battery cluster sizing unit
A11: ESS | B11: Design discharge rate | C11: 0.5 | D11: C | E11: Product-source basis | F11: 0.5C listed for 215.04 kWh battery cluster
A12: ESS | B12: Implied sizing-unit power | C12: =C10*C11 -> 107.52 | D12: kW/unit | E12: Product-source basis | F12: Energy × C-rate
A13: ESS | B13: Usable energy fraction | C13: 0.9 | D13: x | E13: Modeling assumption | F13: Conservative usable-energy assumption.
A14: ESS | B14: Discharge efficiency | C14: 0.95 | D14: x | E14: Modeling assumption | F14: Assumed discharge efficiency.
A15: ESS | B15: Legacy demand-shave reference (retired from proposal calc) | C15: 0.2 | D15: x | E15: Assumption | F15: Screening target, not measured dispatch result
A16: Finance | B16: Export value | C16: 0.05 | D16: $/kWh | E16: Verified | F16: value for PV surplus
A17: Finance | B17: PV installed cost | C17: 2.01 | D17: $/W DC | E17: Historical internal value | F17: cost snapshot
A18: Finance | B18: ESS installed cost | C18: 600 | D18: $/kWh | E18: Historical internal value | F18: component-level ESS cost snapshot
A19: Finance | B19: Analysis horizon | C19: 30 | D19: years | E19: Assumption | F19: Screening financial horizon
A20: Finance | B20: Discount rate | C20: 0.05 | D20: x | E20: Historical assumption | F20: proposal financial assumption
A21: Finance | B21: Electricity escalation | C21: 0.03 | D21: x/year | E21: Historical assumption | F21: proposal financial assumption
A22: Finance | B22: PV degradation | C22: 0.008 | D22: x/year | E22: Historical assumption | F22: proposal financial assumption
B25: Proposal demand-shave target (Meter 2 account, kW) | C25: 100
B27: Federal ITC proposal-case rate | C27: 0.3 | D27: x | E27: Current policy | F27: 48E/PWA/eligibility verified
B28: Federal depreciation effective tax-benefit rate | C28: 0.255 | D28: x | E28: Current policy | F28: 30% tax rate × 85% post-ITC depreciable basis
B29: California depreciation effective tax-benefit rate | C29: 0.08 | D29: x | E29: Current policy | F29: official website verified
B30: AC PCS rating per 215.04-kWh unit | C30: 100 | D30: kW AC/unit | E30: Modeling assumption | F30: Comparable-product benchmark
B31: Total AC PCS rating — 2 units | C31: 200 | D31: kW AC | E31: Derived assumption | F31: 2 × 100 kW assumed AC PCS.

Sheet PV Production
A1: PV Panel Sizing & Monthly Production
A2: Monthly PV shape is calculated from the 485-kW panel. Candidate-system production is scaled linearly by DC capacity. Load uses billing-cycle ending month, so month-to-month comparison is a screening approximation rather than interval simulation.
A4: Month | B4: Historical Load (kWh) | C4: Reference PV Gen @485kW (kWh) | D4: Reference Yield (kWh/kW) | E4: Min Panels Candidate | F4: Candidate PV DC (kW) | G4: Candidate PV Gen (kWh) | H4: Monthly Surplus/(Deficit) (kWh) | I4: PV-to-Load | J4: Self-Consumed PV Proxy (kWh) | K4: Export/Surplus Proxy (kWh)
A5: Jan 2024 | B5: ='Combined TOU Profile'!F8 -> 54844 | C5: 51780 | D5: =C5/'Model Assumptions'!$C$6 -> 106.76289 | E5: =ROUNDUP('Model Assumptions'!$C$4/('Model Assumptions'!$C$7/'Model Assumptions'!$C$8),0) -> 838 | F5: =E5*'Model Assumptions'!$C$5 -> 406.43 | G5: =C5*F5/'Model Assumptions'!$C$6 -> 43391.64 | H5: =G5-B5 -> -11452.36 | I5: =G5/B5 -> 0.79118299 | J5: =MIN(G5,B5) -> 43391.64 | K5: =MAX(G5-B5,0) -> 0
A6: Feb 2024 | B6: ='Combined TOU Profile'!F9 -> 48926 | C6: 55888 | D6: =C6/'Model Assumptions'!$C$6 -> 115.23299 | E6: =ROUNDUP('Model Assumptions'!$C$4/('Model Assumptions'!$C$7/'Model Assumptions'!$C$8),0) -> 838 | F6: =E6*'Model Assumptions'!$C$5 -> 406.43 | G6: =C6*F6/'Model Assumptions'!$C$6 -> 46834.144 | H6: =G6-B6 -> -2091.856 | I6: =G6/B6 -> 0.95724449 | J6: =MIN(G6,B6) -> 46834.144 | K6: =MAX(G6-B6,0) -> 0
A7: Mar 2024 | B7: ='Combined TOU Profile'!F10 -> 52449 | C7: 73686 | D7: =C7/'Model Assumptions'!$C$6 -> 151.9299 | E7: =ROUNDUP('Model Assumptions'!$C$4/('Model Assumptions'!$C$7/'Model Assumptions'!$C$8),0) -> 838 | F7: =E7*'Model Assumptions'!$C$5 -> 406.43 | G7: =C7*F7/'Model Assumptions'!$C$6 -> 61748.868 | H7: =G7-B7 -> 9299.868 | I7: =G7/B7 -> 1.1773126 | J7: =MIN(G7,B7) -> 52449 | K7: =MAX(G7-B7,0) -> 9299.868
A8: Apr 2024 | B8: ='Combined TOU Profile'!F11 -> 40752 | C8: 82939 | D8: =C8/'Model Assumptions'!$C$6 -> 171.00825 | E8: =ROUNDUP('Model Assumptions'!$C$4/('Model Assumptions'!$C$7/'Model Assumptions'!$C$8),0) -> 838 | F8: =E8*'Model Assumptions'!$C$5 -> 406.43 | G8: =C8*F8/'Model Assumptions'!$C$6 -> 69502.882 | H8: =G8-B8 -> 28750.882 | I8: =G8/B8 -> 1.7055085 | J8: =MIN(G8,B8) -> 40752 | K8: =MAX(G8-B8,0) -> 28750.882
A9: May 2024 | B9: ='Combined TOU Profile'!F12 -> 51220 | C9: 91798 | D9: =C9/'Model Assumptions'!$C$6 -> 189.27423 | E9: =ROUNDUP('Model Assumptions'!$C$4/('Model Assumptions'!$C$7/'Model Assumptions'!$C$8),0) -> 838 | F9: =E9*'Model Assumptions'!$C$5 -> 406.43 | G9: =C9*F9/'Model Assumptions'!$C$6 -> 76926.724 | H9: =G9-B9 -> 25706.724 | I9: =G9/B9 -> 1.5018884 | J9: =MIN(G9,B9) -> 51220 | K9: =MAX(G9-B9,0) -> 25706.724
A10: Jun 2024 | B10: ='Combined TOU Profile'!F13 -> 50744 | C10: 91057 | D10: =C10/'Model Assumptions'!$C$6 -> 187.74639 | E10: =ROUNDUP('Model Assumptions'!$C$4/('Model Assumptions'!$C$7/'Model Assumptions'!$C$8),0) -> 838 | F10: =E10*'Model Assumptions'!$C$5 -> 406.43 | G10: =C10*F10/'Model Assumptions'!$C$6 -> 76305.766 | H10: =G10-B10 -> 25561.766 | I10: =G10/B10 -> 1.5037397 | J10: =MIN(G10,B10) -> 50744 | K10: =MAX(G10-B10,0) -> 25561.766
A11: Jul 2024 | B11: ='Combined TOU Profile'!F14 -> 81109 | C11: 84094 | D11: =C11/'Model Assumptions'!$C$6 -> 173.38969 | E11: =ROUNDUP('Model Assumptions'!$C$4/('Model Assumptions'!$C$7/'Model Assumptions'!$C$8),0) -> 838 | F11: =E11*'Model Assumptions'!$C$5 -> 406.43 | G11: =C11*F11/'Model Assumptions'!$C$6 -> 70470.772 | H11: =G11-B11 -> -10638.228 | I11: =G11/B11 -> 0.86884035 | J11: =MIN(G11,B11) -> 70470.772 | K11: =MAX(G11-B11,0) -> 0
A12: Aug 2024 | B12: ='Combined TOU Profile'!F15 -> 80723 | C12: 83095 | D12: =C12/'Model Assumptions'!$C$6 -> 171.3299 | E12: =ROUNDUP('Model Assumptions'!$C$4/('Model Assumptions'!$C$7/'Model Assumptions'!$C$8),0) -> 838 | F12: =E12*'Model Assumptions'!$C$5 -> 406.43 | G12: =C12*F12/'Model Assumptions'!$C$6 -> 69633.61 | H12: =G12-B12 -> -11089.39 | I12: =G12/B12 -> 0.86262416 | J12: =MIN(G12,B12) -> 69633.61 | K12: =MAX(G12-B12,0) -> 0
A13: Sep 2024 | B13: ='Combined TOU Profile'!F16 -> 84369 | C13: 72370 | D13: =C13/'Model Assumptions'!$C$6 -> 149.21649 | E13: =ROUNDUP('Model Assumptions'!$C$4/('Model Assumptions'!$C$7/'Model Assumptions'!$C$8),0) -> 838 | F13: =E13*'Model Assumptions'!$C$5 -> 406.43 | G13: =C13*F13/'Model Assumptions'!$C$6 -> 60646.06 | H13: =G13-B13 -> -23722.94 | I13: =G13/B13 -> 0.71881923 | J13: =MIN(G13,B13) -> 60646.06 | K13: =MAX(G13-B13,0) -> 0
A14: Oct 2023 | B14: ='Combined TOU Profile'!F5 -> 50017 | C14: 65606 | D14: =C14/'Model Assumptions'!$C$6 -> 135.2701 | E14: =ROUNDUP('Model Assumptions'!$C$4/('Model Assumptions'!$C$7/'Model Assumptions'!$C$8),0) -> 838 | F14: =E14*'Model Assumptions'!$C$5 -> 406.43 | G14: =C14*F14/'Model Assumptions'!$C$6 -> 54977.828 | H14: =G14-B14 -> 4960.828 | I14: =G14/B14 -> 1.0991828 | J14: =MIN(G14,B14) -> 50017 | K14: =MAX(G14-B14,0) -> 4960.828
A15: Nov 2023 | B15: ='Combined TOU Profile'!F6 -> 61096 | C15: 51050 | D15: =C15/'Model Assumptions'!$C$6 -> 105.25773 | E15: =ROUNDUP('Model Assumptions'!$C$4/('Model Assumptions'!$C$7/'Model Assumptions'!$C$8),0) -> 838 | F15: =E15*'Model Assumptions'!$C$5 -> 406.43 | G15: =C15*F15/'Model Assumptions'!$C$6 -> 42779.9 | H15: =G15-B15 -> -18316.1 | I15: =G15/B15 -> 0.70020787 | J15: =MIN(G15,B15) -> 42779.9 | K15: =MAX(G15-B15,0) -> 0
A16: Dec 2023 | B16: ='Combined TOU Profile'!F7 -> 53252 | C16: 44140 | D16: =C16/'Model Assumptions'!$C$6 -> 91.010309 | E16: =ROUNDUP('Model Assumptions'!$C$4/('Model Assumptions'!$C$7/'Model Assumptions'!$C$8),0) -> 838 | F16: =E16*'Model Assumptions'!$C$5 -> 406.43 | G16: =C16*F16/'Model Assumptions'!$C$6 -> 36989.32 | H16: =G16-B16 -> -16262.68 | I16: =G16/B16 -> 0.69460903 | J16: =MIN(G16,B16) -> 36989.32 | K16: =MAX(G16-B16,0) -> 0
A17: Annual | B17: =SUM(B5:B16) -> 709501 | C17: =SUM(C5:C16) -> 847503 | D17: =C17/'Model Assumptions'!$C$6 -> 1747.4289 | E17: =E5 -> 838 | F17: =F5 -> 406.43 | G17: =SUM(G5:G16) -> 710207.51 | H17: =SUM(H5:H16) -> 706.514 | I17: =G17/B17 -> 1.0009958 | J17: =SUM(J5:J16) -> 615927.45 | K17: =SUM(K5:K16) -> 94280.068

Sheet ESS Sizing
A1: SPT6800 ESS Sizing — TOU Energy + Peak Demand
A2: Energy sizing uses average daily On+Mid-Peak energy; power sizing uses the fixed 100-kW proposal demand-shave target. The 215.04-kWh / 0.5C sizing basis comes from the SPT product material.
A4: Period | B4: Days | C4: On-Peak kWh | D4: Mid-Peak kWh | E4: Peak-Window Energy (kWh) | F4: Avg Daily Peak-Window Energy (kWh/day) | G4: Site Max-Demand Indicator (kW) | H4: Target Peak Shave (kW) | I4: Usable Delivered Energy / Unit (kWh) | J4: Power / Unit (kW) | K4: Units by Energy | L4: Units by Power | M4: Required Units | N4: Data Status
A5: ='Combined TOU Profile'!A5 -> Oct 2023 | B5: 29 | C5: ='Combined TOU Profile'!G5 -> 444 | D5: ='Combined TOU Profile'!H5 -> 1257 | E5: =SUM(C5:D5) -> 1701 | F5: =E5/B5 -> 58.655172 | G5: ='Combined TOU Profile'!M5 -> 552 | H5: ='Model Assumptions'!$C$30 -> 100 | I5: ='Model Assumptions'!$C$10*'Model Assumptions'!$C$13*'Model Assumptions'!$C$14 -> 183.8592 | J5: ='Model Assumptions'!$C$12 -> 107.52 | K5: =ROUNDUP(F5/I5,0) -> 1 | L5: =ROUNDUP(H5/J5,0) -> 1 | M5: =MAX(K5,L5) -> 1 | N5: ='Combined TOU Profile'!U5 -> Complete
A6: ='Combined TOU Profile'!A6 -> Nov 2023 | B6: 32 | C6: ='Combined TOU Profile'!G6 -> 0 | D6: ='Combined TOU Profile'!H6 -> 1654 | E6: =SUM(C6:D6) -> 1654 | F6: =E6/B6 -> 51.6875 | G6: ='Combined TOU Profile'!M6 -> 622 | H6: ='Model Assumptions'!$C$30 -> 100 | I6: ='Model Assumptions'!$C$10*'Model Assumptions'!$C$13*'Model Assumptions'!$C$14 -> 183.8592 | J6: ='Model Assumptions'!$C$12 -> 107.52 | K6: =ROUNDUP(F6/I6,0) -> 1 | L6: =ROUNDUP(H6/J6,0) -> 1 | M6: =MAX(K6,L6) -> 1 | N6: ='Combined TOU Profile'!U6 -> Complete
A7: ='Combined TOU Profile'!A7 -> Dec 2023 | B7: 30 | C7: ='Combined TOU Profile'!G7 -> 0 | D7: ='Combined TOU Profile'!H7 -> 2024 | E7: =SUM(C7:D7) -> 2024 | F7: =E7/B7 -> 67.466667 | G7: ='Combined TOU Profile'!M7 -> 513 | H7: ='Model Assumptions'!$C$30 -> 100 | I7: ='Model Assumptions'!$C$10*'Model Assumptions'!$C$13*'Model Assumptions'!$C$14 -> 183.8592 | J7: ='Model Assumptions'!$C$12 -> 107.52 | K7: =ROUNDUP(F7/I7,0) -> 1 | L7: =ROUNDUP(H7/J7,0) -> 1 | M7: =MAX(K7,L7) -> 1 | N7: ='Combined TOU Profile'!U7 -> Complete
A8: ='Combined TOU Profile'!A8 -> Jan 2024 | B8: 33 | C8: ='Combined TOU Profile'!G8 -> 0 | D8: ='Combined TOU Profile'!H8 -> 2137 | E8: =SUM(C8:D8) -> 2137 | F8: =E8/B8 -> 64.757576 | G8: ='Combined TOU Profile'!M8 -> 655 | H8: ='Model Assumptions'!$C$30 -> 100 | I8: ='Model Assumptions'!$C$10*'Model Assumptions'!$C$13*'Model Assumptions'!$C$14 -> 183.8592 | J8: ='Model Assumptions'!$C$12 -> 107.52 | K8: =ROUNDUP(F8/I8,0) -> 1 | L8: =ROUNDUP(H8/J8,0) -> 1 | M8: =MAX(K8,L8) -> 1 | N8: ='Combined TOU Profile'!U8 -> Complete
A9: ='Combined TOU Profile'!A9 -> Feb 2024 | B9: 30 | C9: ='Combined TOU Profile'!G9 -> 0 | D9: ='Combined TOU Profile'!H9 -> 1802 | E9: =SUM(C9:D9) -> 1802 | F9: =E9/B9 -> 60.066667 | G9: ='Combined TOU Profile'!M9 -> 640 | H9: ='Model Assumptions'!$C$30 -> 100 | I9: ='Model Assumptions'!$C$10*'Model Assumptions'!$C$13*'Model Assumptions'!$C$14 -> 183.8592 | J9: ='Model Assumptions'!$C$12 -> 107.52 | K9: =ROUNDUP(F9/I9,0) -> 1 | L9: =ROUNDUP(H9/J9,0) -> 1 | M9: =MAX(K9,L9) -> 1 | N9: ='Combined TOU Profile'!U9 -> Complete
A10: ='Combined TOU Profile'!A10 -> Mar 2024 | B10: 29 | C10: ='Combined TOU Profile'!G10 -> 0 | D10: ='Combined TOU Profile'!H10 -> 1437 | E10: =SUM(C10:D10) -> 1437 | F10: =E10/B10 -> 49.551724 | G10: ='Combined TOU Profile'!M10 -> 500 | H10: ='Model Assumptions'!$C$30 -> 100 | I10: ='Model Assumptions'!$C$10*'Model Assumptions'!$C$13*'Model Assumptions'!$C$14 -> 183.8592 | J10: ='Model Assumptions'!$C$12 -> 107.52 | K10: =ROUNDUP(F10/I10,0) -> 1 | L10: =ROUNDUP(H10/J10,0) -> 1 | M10: =MAX(K10,L10) -> 1 | N10: ='Combined TOU Profile'!U10 -> Complete
A11: ='Combined TOU Profile'!A11 -> Apr 2024 | B11: 32 | C11: ='Combined TOU Profile'!G11 -> 0 | D11: ='Combined TOU Profile'!H11 -> 1317 | E11: =SUM(C11:D11) -> 1317 | F11: =E11/B11 -> 41.15625 | G11: ='Combined TOU Profile'!M11 -> 442 | H11: ='Model Assumptions'!$C$30 -> 100 | I11: ='Model Assumptions'!$C$10*'Model Assumptions'!$C$13*'Model Assumptions'!$C$14 -> 183.8592 | J11: ='Model Assumptions'!$C$12 -> 107.52 | K11: =ROUNDUP(F11/I11,0) -> 1 | L11: =ROUNDUP(H11/J11,0) -> 1 | M11: =MAX(K11,L11) -> 1 | N11: ='Combined TOU Profile'!U11 -> Complete
A12: ='Combined TOU Profile'!A12 -> May 2024 | B12: 29 | C12: ='Combined TOU Profile'!G12 -> 403.83324 | D12: ='Combined TOU Profile'!H12 -> 876.32908 | E12: =SUM(C12:D12) -> 1280.1623 | F12: =E12/B12 -> 44.143528 | G12: ='Combined TOU Profile'!M12 -> 466 | H12: ='Model Assumptions'!$C$30 -> 100 | I12: ='Model Assumptions'!$C$10*'Model Assumptions'!$C$13*'Model Assumptions'!$C$14 -> 183.8592 | J12: ='Model Assumptions'!$C$12 -> 107.52 | K12: =ROUNDUP(F12/I12,0) -> 1 | L12: =ROUNDUP(H12/J12,0) -> 1 | M12: =MAX(K12,L12) -> 1 | N12: ='Combined TOU Profile'!U12 -> Estimated — Meter1 May TOU from adjacent periods
A13: ='Combined TOU Profile'!A13 -> Jun 2024 | B13: 30 | C13: ='Combined TOU Profile'!G13 -> 1008 | D13: ='Combined TOU Profile'!H13 -> 993 | E13: =SUM(C13:D13) -> 2001 | F13: =E13/B13 -> 66.7 | G13: ='Combined TOU Profile'!M13 -> 471 | H13: ='Model Assumptions'!$C$30 -> 100 | I13: ='Model Assumptions'!$C$10*'Model Assumptions'!$C$13*'Model Assumptions'!$C$14 -> 183.8592 | J13: ='Model Assumptions'!$C$12 -> 107.52 | K13: =ROUNDUP(F13/I13,0) -> 1 | L13: =ROUNDUP(H13/J13,0) -> 1 | M13: =MAX(K13,L13) -> 1 | N13: ='Combined TOU Profile'!U13 -> Complete
A14: ='Combined TOU Profile'!A14 -> Jul 2024 | B14: 33 | C14: ='Combined TOU Profile'!G14 -> 2075 | D14: ='Combined TOU Profile'!H14 -> 723 | E14: =SUM(C14:D14) -> 2798 | F14: =E14/B14 -> 84.787879 | G14: ='Combined TOU Profile'!M14 -> 725 | H14: ='Model Assumptions'!$C$30 -> 100 | I14: ='Model Assumptions'!$C$10*'Model Assumptions'!$C$13*'Model Assumptions'!$C$14 -> 183.8592 | J14: ='Model Assumptions'!$C$12 -> 107.52 | K14: =ROUNDUP(F14/I14,0) -> 1 | L14: =ROUNDUP(H14/J14,0) -> 1 | M14: =MAX(K14,L14) -> 1 | N14: ='Combined TOU Profile'!U14 -> Complete
A15: ='Combined TOU Profile'!A15 -> Aug 2024 | B15: 29 | C15: ='Combined TOU Profile'!G15 -> 4892 | D15: ='Combined TOU Profile'!H15 -> 631 | E15: =SUM(C15:D15) -> 5523 | F15: =E15/B15 -> 190.44828 | G15: ='Combined TOU Profile'!M15 -> 705 | H15: ='Model Assumptions'!$C$30 -> 100 | I15: ='Model Assumptions'!$C$10*'Model Assumptions'!$C$13*'Model Assumptions'!$C$14 -> 183.8592 | J15: ='Model Assumptions'!$C$12 -> 107.52 | K15: =ROUNDUP(F15/I15,0) -> 2 | L15: =ROUNDUP(H15/J15,0) -> 1 | M15: =MAX(K15,L15) -> 2 | N15: ='Combined TOU Profile'!U15 -> Complete
A16: ='Combined TOU Profile'!A16 -> Sep 2024 | B16: 30 | C16: ='Combined TOU Profile'!G16 -> 3782 | D16: ='Combined TOU Profile'!H16 -> 629 | E16: =SUM(C16:D16) -> 4411 | F16: =E16/B16 -> 147.03333 | G16: ='Combined TOU Profile'!M16 -> 730 | H16: ='Model Assumptions'!$C$30 -> 100 | I16: ='Model Assumptions'!$C$10*'Model Assumptions'!$C$13*'Model Assumptions'!$C$14 -> 183.8592 | J16: ='Model Assumptions'!$C$12 -> 107.52 | K16: =ROUNDUP(F16/I16,0) -> 1 | L16: =ROUNDUP(H16/J16,0) -> 1 | M16: =MAX(K16,L16) -> 1 | N16: ='Combined TOU Profile'!U16 -> Complete
A17: Design Requirement | F17: =MAX(F5:F16) -> 190.44828 | G17: =MAX(G5:G16) -> 730 | H17: =MAX(H5:H16) -> 100 | I17: =I5 -> 183.8592 | J17: =J5 -> 107.52 | K17: =MAX(K5:K16) -> 2 | L17: =MAX(L5:L16) -> 1 | M17: =MAX(M5:M16) -> 2

Sheet Scenarios
A1: PV + ESS Configuration Scenarios
A3: Scenario | B3: PV Panels | C3: PV DC (kW) | D3: Annual PV Gen (kWh) | E3: Annual Coverage | F3: ESS Units | G3: ESS Nominal Energy (kWh) | H3: ESS Screening Power (kW) | I3: Energy Sizing Pass | J3: Power Sizing Pass | K3: PV Cost ($) | L3: ESS Cost ($) | M3: Total Installed Cost ($) | N3: Year-1 Screening Savings ($) | O3: Simple Payback (yrs) | P3: Constraint Status
A4: Minimum | B4: 838 | C4: =B4*'Model Assumptions'!$C$5 -> 406.43 | D4: ='Model Assumptions'!$C$7*C4/'Model Assumptions'!$C$6 -> 710207.51 | E4: =D4/'Model Assumptions'!$C$4 -> 1.0009958 | F4: 2 | G4: =F4*'Model Assumptions'!$C$10 -> 430.08 | H4: =F4*'Model Assumptions'!$C$12 -> 215.04 | I4: =IF(F4>='ESS Sizing'!$M$17,"PASS","FAIL") -> PASS | J4: =IF(H4>='ESS Sizing'!$H$17,"PASS","FAIL") -> PASS | K4: =C4*1000*'Model Assumptions'!$C$17 -> 816924.3 | L4: =G4*'Model Assumptions'!$C$18 -> 258048 | M4: =K4+L4 -> 1074972.3 | N4: =Financial!L5 -> 100318.07 | O4: =M4/N4 -> 10.71564 | P4: =IF(AND(E4>='Model Assumptions'!$C$9,I4="PASS",J4="PASS"),"PASS","FAIL") -> PASS
A5: Balanced A | B5: 850 | C5: =B5*'Model Assumptions'!$C$5 -> 412.25 | D5: ='Model Assumptions'!$C$7*C5/'Model Assumptions'!$C$6 -> 720377.55 | E5: =D5/'Model Assumptions'!$C$4 -> 1.0153299 | F5: 2 | G5: =F5*'Model Assumptions'!$C$10 -> 430.08 | H5: =F5*'Model Assumptions'!$C$12 -> 215.04 | I5: =IF(F5>='ESS Sizing'!$M$17,"PASS","FAIL") -> PASS | J5: =IF(H5>='ESS Sizing'!$H$17,"PASS","FAIL") -> PASS | K5: =C5*1000*'Model Assumptions'!$C$17 -> 828622.5 | L5: =G5*'Model Assumptions'!$C$18 -> 258048 | M5: =K5+L5 -> 1086670.5 | N5: =Financial!L6 -> 101051.39 | O5: =M5/N5 -> 10.753643 | P5: =IF(AND(E5>='Model Assumptions'!$C$9,I5="PASS",J5="PASS"),"PASS","FAIL") -> PASS
A6: Balanced B | B6: 875 | C6: =B6*'Model Assumptions'!$C$5 -> 424.375 | D6: ='Model Assumptions'!$C$7*C6/'Model Assumptions'!$C$6 -> 741565.12 | E6: =D6/'Model Assumptions'!$C$4 -> 1.0451925 | F6: 3 | G6: =F6*'Model Assumptions'!$C$10 -> 645.12 | H6: =F6*'Model Assumptions'!$C$12 -> 322.56 | I6: =IF(F6>='ESS Sizing'!$M$17,"PASS","FAIL") -> PASS | J6: =IF(H6>='ESS Sizing'!$H$17,"PASS","FAIL") -> PASS | K6: =C6*1000*'Model Assumptions'!$C$17 -> 852993.75 | L6: =G6*'Model Assumptions'!$C$18 -> 387072 | M6: =K6+L6 -> 1240065.8 | N6: =Financial!L7 -> 102579.13 | O6: =M6/N6 -> 12.088869 | P6: =IF(AND(E6>='Model Assumptions'!$C$9,I6="PASS",J6="PASS"),"PASS","FAIL") -> PASS
A7: Higher Storage | B7: 900 | C7: =B7*'Model Assumptions'!$C$5 -> 436.5 | D7: ='Model Assumptions'!$C$7*C7/'Model Assumptions'!$C$6 -> 762752.7 | E7: =D7/'Model Assumptions'!$C$4 -> 1.0750551 | F7: 4 | G7: =F7*'Model Assumptions'!$C$10 -> 860.16 | H7: =F7*'Model Assumptions'!$C$12 -> 430.08 | I7: =IF(F7>='ESS Sizing'!$M$17,"PASS","FAIL") -> PASS | J7: =IF(H7>='ESS Sizing'!$H$17,"PASS","FAIL") -> PASS | K7: =C7*1000*'Model Assumptions'!$C$17 -> 877365 | L7: =G7*'Model Assumptions'!$C$18 -> 516096 | M7: =K7+L7 -> 1393461 | N7: =Financial!L8 -> 104048.73 | O7: =M7/N7 -> 13.392388 | P7: =IF(AND(E7>='Model Assumptions'!$C$9,I7="PASS",J7="PASS"),"PASS","FAIL") -> PASS
A8: Historical PV Scale | B8: 1000 | C8: =B8*'Model Assumptions'!$C$5 -> 485 | D8: ='Model Assumptions'!$C$7*C8/'Model Assumptions'!$C$6 -> 847503 | E8: =D8/'Model Assumptions'!$C$4 -> 1.1945057 | F8: 6 | G8: =F8*'Model Assumptions'!$C$10 -> 1290.24 | H8: =F8*'Model Assumptions'!$C$12 -> 645.12 | I8: =IF(F8>='ESS Sizing'!$M$17,"PASS","FAIL") -> PASS | J8: =IF(H8>='ESS Sizing'!$H$17,"PASS","FAIL") -> PASS | K8: =C8*1000*'Model Assumptions'!$C$17 -> 974850 | L8: =G8*'Model Assumptions'!$C$18 -> 774144 | M8: =K8+L8 -> 1748994 | N8: =Financial!L9 -> 109696.21 | O8: =M8/N8 -> 15.943979 | P8: =IF(AND(E8>='Model Assumptions'!$C$9,I8="PASS",J8="PASS"),"PASS","FAIL") -> PASS

Sheet Financial
A1: Preliminary Electricity-Cost Savings
A2: PV savings use extracted historical energy-charge intensity for self-consumed load plus an editable export value for surplus. ESS demand savings use the target peak-shave fraction applied to extracted historical demand charges.
A4: Scenario | B4: PV Panels | C4: ESS Units | D4: PV Gen (kWh) | E4: Self-Consumed PV Proxy (kWh) | F4: PV Surplus (kWh) | G4: Historical Energy-Charge Rate ($/kWh) | H4: PV Energy Savings ($) | I4: PV Export Value ($) | J4: ESS Demand Savings ($) | K4: Other ESS TOU Arbitrage ($) | L4: Year-1 Screening Savings ($)
A5: =Scenarios!A4 -> Minimum | B5: =Scenarios!B4 -> 838 | C5: =Scenarios!F4 -> 2 | D5: =Scenarios!D4 -> 710207.51 | E5: =MIN('Combined TOU Profile'!F8,51780*(Scenarios!C4/'Model Assumptions'!$C$6))+MIN('Combined TOU Profile'!F9,55888*(Scenarios!C4/'Model Assumptions'!$C$6))+MIN('Combined TOU Profile'!F10,73686*(Scenarios!C4/'Model Assumptions'!$C$6))+MIN('Combined TOU Profile'!F11,82939*(Scenarios!C4/'Model Assumptions'!$C$6))+MIN('Combined TOU Profile'!F12,91798*(Scenarios!C4/'Model Assumptions'!$C$6))+MIN('Combined TOU Profile'!F13,91057*(Scenarios!C4/'Model Assumptions'!$C$6))+MIN('Combined TOU Profile'!F14,84094*(Scenarios!C4/'Model Assumptions'!$C$6))+MIN('Combined TOU Profile'!F15,83095*(Scenarios!C4/'Model Assumptions'!$C$6))+MIN('Combined TOU Profile'!F16,72370*(Scenarios!C4/'Model Assumptions'!$C$6))+MIN('Combined TOU Profile'!F5,65606*(Scenarios!C4/'Model Assumptions'!$C$6))+MIN('Combined TOU Profile'!F6,51050*(Scenarios!C4/'Model Assumptions'!$C$6))+MIN('Combined TOU Profile'!F7,44140*(Scenarios!C4/'Model Assumptions'!$C$6)) -> 615927.45 | F5: =MAX(D5-E5,0) -> 94280.068 | G5: ='Combined TOU Profile'!P17/'Combined TOU Profile'!F17 -> 0.092346318 | H5: =E5*G5 -> 56878.632 | I5: =F5*'Model Assumptions'!$C$16 -> 4714.0034 | J5: ='Combined TOU Profile'!Q17*MIN('Model Assumptions'!$C$15,(Scenarios!H4/'ESS Sizing'!$G$17)) -> 38725.434 | K5: 0 | L5: =SUM(H5:K5) -> 100318.07
A6: =Scenarios!A5 -> Balanced A | B6: =Scenarios!B5 -> 850 | C6: =Scenarios!F5 -> 2 | D6: =Scenarios!D5 -> 720377.55 | E6: =MIN('Combined TOU Profile'!F8,51780*(Scenarios!C5/'Model Assumptions'!$C$6))+MIN('Combined TOU Profile'!F9,55888*(Scenarios!C5/'Model Assumptions'!$C$6))+MIN('Combined TOU Profile'!F10,73686*(Scenarios!C5/'Model Assumptions'!$C$6))+MIN('Combined TOU Profile'!F11,82939*(Scenarios!C5/'Model Assumptions'!$C$6))+MIN('Combined TOU Profile'!F12,91798*(Scenarios!C5/'Model Assumptions'!$C$6))+MIN('Combined TOU Profile'!F13,91057*(Scenarios!C5/'Model Assumptions'!$C$6))+MIN('Combined TOU Profile'!F14,84094*(Scenarios!C5/'Model Assumptions'!$C$6))+MIN('Combined TOU Profile'!F15,83095*(Scenarios!C5/'Model Assumptions'!$C$6))+MIN('Combined TOU Profile'!F16,72370*(Scenarios!C5/'Model Assumptions'!$C$6))+MIN('Combined TOU Profile'!F5,65606*(Scenarios!C5/'Model Assumptions'!$C$6))+MIN('Combined TOU Profile'!F6,51050*(Scenarios!C5/'Model Assumptions'!$C$6))+MIN('Combined TOU Profile'!F7,44140*(Scenarios!C5/'Model Assumptions'!$C$6)) -> 621236.45 | F6: =MAX(D6-E6,0) -> 99141.1 | G6: ='Combined TOU Profile'!P17/'Combined TOU Profile'!F17 -> 0.092346318 | H6: =E6*G6 -> 57368.898 | I6: =F6*'Model Assumptions'!$C$16 -> 4957.055 | J6: ='Combined TOU Profile'!Q17*MIN('Model Assumptions'!$C$15,(Scenarios!H5/'ESS Sizing'!$G$17)) -> 38725.434 | K6: 0 | L6: =SUM(H6:K6) -> 101051.39
A7: =Scenarios!A6 -> Balanced B | B7: =Scenarios!B6 -> 875 | C7: =Scenarios!F6 -> 3 | D7: =Scenarios!D6 -> 741565.12 | E7: =MIN('Combined TOU Profile'!F8,51780*(Scenarios!C6/'Model Assumptions'!$C$6))+MIN('Combined TOU Profile'!F9,55888*(Scenarios!C6/'Model Assumptions'!$C$6))+MIN('Combined TOU Profile'!F10,73686*(Scenarios!C6/'Model Assumptions'!$C$6))+MIN('Combined TOU Profile'!F11,82939*(Scenarios!C6/'Model Assumptions'!$C$6))+MIN('Combined TOU Profile'!F12,91798*(Scenarios!C6/'Model Assumptions'!$C$6))+MIN('Combined TOU Profile'!F13,91057*(Scenarios!C6/'Model Assumptions'!$C$6))+MIN('Combined TOU Profile'!F14,84094*(Scenarios!C6/'Model Assumptions'!$C$6))+MIN('Combined TOU Profile'!F15,83095*(Scenarios!C6/'Model Assumptions'!$C$6))+MIN('Combined TOU Profile'!F16,72370*(Scenarios!C6/'Model Assumptions'!$C$6))+MIN('Combined TOU Profile'!F5,65606*(Scenarios!C6/'Model Assumptions'!$C$6))+MIN('Combined TOU Profile'!F6,51050*(Scenarios!C6/'Model Assumptions'!$C$6))+MIN('Combined TOU Profile'!F7,44140*(Scenarios!C6/'Model Assumptions'!$C$6)) -> 632296.88 | F7: =MAX(D7-E7,0) -> 109268.25 | G7: ='Combined TOU Profile'!P17/'Combined TOU Profile'!F17 -> 0.092346318 | H7: =E7*G7 -> 58390.288 | I7: =F7*'Model Assumptions'!$C$16 -> 5463.4125 | J7: ='Combined TOU Profile'!Q17*MIN('Model Assumptions'!$C$15,(Scenarios!H6/'ESS Sizing'!$G$17)) -> 38725.434 | K7: 0 | L7: =SUM(H7:K7) -> 102579.13
A8: =Scenarios!A7 -> Higher Storage | B8: =Scenarios!B7 -> 900 | C8: =Scenarios!F7 -> 4 | D8: =Scenarios!D7 -> 762752.7 | E8: =MIN('Combined TOU Profile'!F8,51780*(Scenarios!C7/'Model Assumptions'!$C$6))+MIN('Combined TOU Profile'!F9,55888*(Scenarios!C7/'Model Assumptions'!$C$6))+MIN('Combined TOU Profile'!F10,73686*(Scenarios!C7/'Model Assumptions'!$C$6))+MIN('Combined TOU Profile'!F11,82939*(Scenarios!C7/'Model Assumptions'!$C$6))+MIN('Combined TOU Profile'!F12,91798*(Scenarios!C7/'Model Assumptions'!$C$6))+MIN('Combined TOU Profile'!F13,91057*(Scenarios!C7/'Model Assumptions'!$C$6))+MIN('Combined TOU Profile'!F14,84094*(Scenarios!C7/'Model Assumptions'!$C$6))+MIN('Combined TOU Profile'!F15,83095*(Scenarios!C7/'Model Assumptions'!$C$6))+MIN('Combined TOU Profile'!F16,72370*(Scenarios!C7/'Model Assumptions'!$C$6))+MIN('Combined TOU Profile'!F5,65606*(Scenarios!C7/'Model Assumptions'!$C$6))+MIN('Combined TOU Profile'!F6,51050*(Scenarios!C7/'Model Assumptions'!$C$6))+MIN('Combined TOU Profile'!F7,44140*(Scenarios!C7/'Model Assumptions'!$C$6)) -> 641984.1 | F8: =MAX(D8-E8,0) -> 120768.6 | G8: ='Combined TOU Profile'!P17/'Combined TOU Profile'!F17 -> 0.092346318 | H8: =E8*G8 -> 59284.868 | I8: =F8*'Model Assumptions'!$C$16 -> 6038.43 | J8: ='Combined TOU Profile'!Q17*MIN('Model Assumptions'!$C$15,(Scenarios!H7/'ESS Sizing'!$G$17)) -> 38725.434 | K8: 0 | L8: =SUM(H8:K8) -> 104048.73
A9: =Scenarios!A8 -> Historical PV Scale | B9: =Scenarios!B8 -> 1000 | C9: =Scenarios!F8 -> 6 | D9: =Scenarios!D8 -> 847503 | E9: =MIN('Combined TOU Profile'!F8,51780*(Scenarios!C8/'Model Assumptions'!$C$6))+MIN('Combined TOU Profile'!F9,55888*(Scenarios!C8/'Model Assumptions'!$C$6))+MIN('Combined TOU Profile'!F10,73686*(Scenarios!C8/'Model Assumptions'!$C$6))+MIN('Combined TOU Profile'!F11,82939*(Scenarios!C8/'Model Assumptions'!$C$6))+MIN('Combined TOU Profile'!F12,91798*(Scenarios!C8/'Model Assumptions'!$C$6))+MIN('Combined TOU Profile'!F13,91057*(Scenarios!C8/'Model Assumptions'!$C$6))+MIN('Combined TOU Profile'!F14,84094*(Scenarios!C8/'Model Assumptions'!$C$6))+MIN('Combined TOU Profile'!F15,83095*(Scenarios!C8/'Model Assumptions'!$C$6))+MIN('Combined TOU Profile'!F16,72370*(Scenarios!C8/'Model Assumptions'!$C$6))+MIN('Combined TOU Profile'!F5,65606*(Scenarios!C8/'Model Assumptions'!$C$6))+MIN('Combined TOU Profile'!F6,51050*(Scenarios!C8/'Model Assumptions'!$C$6))+MIN('Combined TOU Profile'!F7,44140*(Scenarios!C8/'Model Assumptions'!$C$6)) -> 675280 | F9: =MAX(D9-E9,0) -> 172223 | G9: ='Combined TOU Profile'!P17/'Combined TOU Profile'!F17 -> 0.092346318 | H9: =E9*G9 -> 62359.621 | I9: =F9*'Model Assumptions'!$C$16 -> 8611.15 | J9: ='Combined TOU Profile'!Q17*MIN('Model Assumptions'!$C$15,(Scenarios!H8/'ESS Sizing'!$G$17)) -> 38725.434 | K9: 0 | L9: =SUM(H9:K9) -> 109696.21
A12: Metric | B12: Value
A13: Historical 12-period bill total | B13: ='Combined TOU Profile'!R17 -> 286732.11
A14: Extracted energy charges | B14: ='Combined TOU Profile'!P17 -> 65519.805
A15: Extracted demand charges | B15: ='Combined TOU Profile'!Q17 -> 193627.17
A16: Residual / other charges | B16: ='Combined TOU Profile'!S17 -> 27585.135
A17: Blended extracted energy-charge rate | B17: =B14/'Combined TOU Profile'!F17 -> 0.092346318

Sheet Recommendation
A1: Recommended Configuration
A3: Metric | B3: Recommended / Result
A4: Recommended scenario | B4: =INDEX(Scenarios!A4:A8,MATCH("PASS",Scenarios!P4:P8,0)) -> Minimum
A5: PV panels | B5: =INDEX(Scenarios!B4:B8,MATCH("PASS",Scenarios!P4:P8,0)) -> 838
A6: PV DC capacity (kW) | B6: =INDEX(Scenarios!C4:C8,MATCH("PASS",Scenarios!P4:P8,0)) -> 406.43
A7: Annual modeled PV generation (kWh) | B7: =INDEX(Scenarios!D4:D8,MATCH("PASS",Scenarios!P4:P8,0)) -> 710207.51
A8: Annual generation coverage | B8: =INDEX(Scenarios!E4:E8,MATCH("PASS",Scenarios!P4:P8,0)) -> 1.0009958
A9: SPT ~215-kWh sizing units | B9: =INDEX(Scenarios!F4:F8,MATCH("PASS",Scenarios!P4:P8,0)) -> 2
A10: Nominal ESS energy (kWh) | B10: =INDEX(Scenarios!G4:G8,MATCH("PASS",Scenarios!P4:P8,0)) -> 430.08
A11: ESS power (kW) | B11: =INDEX(Scenarios!H4:H8,MATCH("PASS",Scenarios!P4:P8,0)) -> 215.04
A13: Interpretation / limitations
A14: The recommendation is the lowest-cost scenario that satisfies two constraints: (1) annual PV generation >= 709,501 kWh; (2) ESS units meet the average-daily On+Mid-Peak energy requirement.

Sheet Sources
A1: Model Sources & Evidence Register
A3: Source | B3: Used For | C3: Status | D3: Key Values | E3: Citation / File
A4: Barstow Historical Load & TOU Profile | B4: Load, TOU, demand, historical bill charges | C4: Verified + one labeled estimate | D4: 709,501 kWh annual baseline; Meter 1 May TOU estimated | E4: Barstow_Historical_Load_TOU_Profile_Completed.xlsx
A5: SPT product introduction | B5: ESS sizing-unit basis | C5: Product source | D5: 215.04 kWh battery cluster; 0.5C design discharge rate | E5: Internal Dataset
A6: Model assumptions | B6: Tech specifications, policy parameters, calculation metrics | C6: Editable assumptions | D6: Analysis horizon, Discount rate, Electricity escalation, PV degradation | E6: Model Assumptions sheet
A18: Grid-Charging Rate Basis | B18: Source / Evidence | C18: Use | D18: Status
A19: Barstow account 8001881589 | B19: Meter 1 TOU Detail — SCE TOU-GS-2-E historical bill category kWh and energy charges | C19: Combined effective low/high TOU energy rates | D19: Historical bill source
A20: Barstow account 8013693720 | B20: Meter 2 TOU Detail — SCE TOU-8-D historical bill category kWh and energy charges | C20: Combined effective low/high TOU energy rates | D20: Historical bill source
A21: SCE TOU periods | B21: SCE TOU-GS-2 / TOU-8 definitions: summer peak 4–9pm; winter super-off-peak daytime and peak/mid-peak 4–9pm | C21: Supports low-price charge / high-price discharge interpretation | D21: External tariff context
A22: Efficiency | B22: Model Specification — 95% discharge efficiency | C22: Converts delivered grid discharge to required grid-charge input | D22: Product specification
A24: Demand-Savings Basis | B24: Source | C24: Use | D24: Status
A25: Meter 1 account | B25: Meter 1 TOU Detail / SCE TOU-GS-2-E bill history | C25: Monthly base + TOU demand $/kW | D25: Historical bill-derived
A26: Meter 2 account | B26: Meter 2 TOU Detail / SCE TOU-8-D bill history | C26: Monthly base + TOU demand $/kW | D26: Historical bill-derived
A27: SCE tariff structure | B27: SCE business TOU guidance: facilities-related demand is based on monthly maximum kW; time-related demand is a separate TOU-period maximum kW charge | C27: Interpretation of demand components | D27: External tariff verification
A28: Physical topology | B28: Barstow site survey report: two meters at surveyed Meter 2 building did not match bills on file; bills were for meters in other buildings | C28: Prevents unsupported cross-meter aggregation | D28: Engineering verified

Sheet Proposal Summary
A1: 3 PROJECT SUMMARY
A3: Payment Options | B3: Cash Purchase
A4: IRR — Term | B4: ='6Detailed Cash Flow'!B42 -> 0.21518283
A5: LCOE PV Generation — screening proxy ($/kWh) | B5: ='1PV Proposal'!E8/('PV Production'!G17*(1-(1-'Model Assumptions'!C22)^30)/'Model Assumptions'!C22) -> 0.015685555
A6: Net Present Value @ 5% | B6: ='6Detailed Cash Flow'!B41 -> 1757719.3
A7: Payback Period | B7: ='6Detailed Cash Flow'!B43 -> 3.8876454
A8: Total Payments | B8: ='6Detailed Cash Flow'!B38 -> 1074972.3
A9: Total Modeled Tax Benefits | B9: ='3Rebates Incentives'!H19 -> 682607.41
A10: Net Economic Cost After Tax Benefits | B10: =B8-B9 -> 392364.89
A11: Electric Bill Savings — 30-Year Term | B11: ='6Detailed Cash Flow'!B40 -> 4694064
A12: Upfront Payment | B12: ='6Detailed Cash Flow'!B38 -> 1074972.3
A13: Year-1 Annual Electricity Savings | B13: ='4Electric Bills'!AA16 -> 106305.62
A15: COMBINED SOLAR PV RATING | B15: Value | C15: COMBINED ESS RATINGS | D15: Value
A16: Power Rating — DC (kW) | B16: ='1PV Proposal'!B8 -> 406.43 | C16: Energy Capacity (kWh) | D16: 430.08
A17: Annual Generation (kWh) | B17: ='1PV Proposal'!B9 -> 710207.51 | C17: Estimated AC PCS Rating (kW) | D17: 200
A18: PV Panels × Rating | B18: 838 × 485 W | C18: Demand-Shave Target (kW) | D18: 100
A31: SCREENING STATUS: PV/load arithmetic is internally consistent. ESS dispatch, demand savings, export compensation, tax timing, and the reconstructed NEW ELECTRIC BILL remain screening-level calculations. The final client-facing proposal should not label these as optimized/final until interval load/dispatch, current tariff/export rules, current equipment quotes, SPT6800 PCS specifications, and current tax eligibility/timing are verified.

Sheet Project Overview
A1: BARSTOW PROJECT OVERVIEW
A3: System | B3: Value | C3: Status / Basis
A4: Solar | B4: ='1PV Proposal'!B8 -> 406.43 | C4: Reconstructed minimum annual-load-coverage case
A5: Installation Type | B5: Carport | C5: Historical proposal/template basis; field configuration should be re-verified
A6: ESS | B6: 430.08 | C6: 2 × 215.04 kWh sizing units
A7: Demand-Shave Target | B7: 100 | C7: kW operating target
A10: Item | B10: Brand / Specification | C10: # of Units
A11: Solar Panel | B11: 485 W standard module | C11: 838
A12: Inverter | B12: To be verified | C12: —
A13: Battery / ESS | B13: SPT6800 platform; 215.04 kWh sizing unit | C13: 2
A14: Estimated AC PCS | B14: 100 kW/unit comparable-product benchmark | C14: 2
A17: Pricing Detail | B17: Solar ($) | C17: ESS ($) | D17: Solar + ESS ($)
A18: System Cost (Selling Price) | B18: ='1PV Proposal'!E4 -> 816924.3 | C18: ='2ESS Proposal'!E4 -> 258048 | D18: =SUM(B18:C18) -> 1074972.3
A19: Federal ITC | B19: =-'1PV Proposal'!E5 -> 245077.29 | C19: =-'2ESS Proposal'!E5 -> 77414.4 | D19: =SUM(B19:C19) -> 322491.69
A20: California Depreciation Tax Benefit | B20: =-'1PV Proposal'!E7 -> 65353.944 | C20: =-'2ESS Proposal'!E7 -> 20643.84 | D20: =SUM(B20:C20) -> 85997.784
A21: Federal MACRS Tax Benefit | B21: =-'1PV Proposal'!E6 -> 208315.7 | C21: =-'2ESS Proposal'!E6 -> 65802.24 | D21: =SUM(B21:C21) -> 274117.94
A22: Net Economic Cost After Tax Benefits | B22: ='1PV Proposal'!E8 -> 298177.37 | C22: ='2ESS Proposal'!E8 -> 94187.52 | D22: =SUM(B22:C22) -> 392364.89
A23: Simple Payback (years) | D23: ='6Detailed Cash Flow'!B43 -> 3.8876454
A26: This page mirrors the historical proposal's project-overview structure using the reconstructed system. Component-level PV cost breakdown from the old 466.6-kW design is intentionally not scaled into the new 406.43-kW case because the source does not establish that each component scales linearly. PV cost uses the historical $2.01/W screening rate; ESS cost uses the historical $600/kWh screening rate. Inverter model and final SPT6800 manufacturer AC PCS rating remain to be verified.

Sheet 0.1Project Overview
A1: BARSTOW PROJECT OVERVIEW
A3: Pricing Detail | B3: Solar ($) | C3: ESS ($) | D3: Solar + ESS ($)
A4: System Cost (Selling Price) | B4: ='1PV Proposal'!E4 -> 816924.3 | C4: ='2ESS Proposal'!E4 -> 258048 | D4: =SUM(B4:C4) -> 1074972.3
A5: Federal ITC | B5: =-'1PV Proposal'!E5 -> 245077.29 | C5: =-'2ESS Proposal'!E5 -> 77414.4 | D5: =SUM(B5:C5) -> 322491.69
A6: California Depreciation Tax Benefit | B6: =-'1PV Proposal'!E7 -> 65353.944 | C6: =-'2ESS Proposal'!E7 -> 20643.84 | D6: =SUM(B6:C6) -> 85997.784
A7: Federal MACRS Tax Benefit | B7: =-'1PV Proposal'!E6 -> 208315.7 | C7: =-'2ESS Proposal'!E6 -> 65802.24 | D7: =SUM(B7:C7) -> 274117.94
A8: Net Economic Cost After Tax Benefits | B8: ='1PV Proposal'!E8 -> 298177.37 | C8: ='2ESS Proposal'!E8 -> 94187.52 | D8: =SUM(B8:C8) -> 392364.89
A9: Simple Payback (years) | D9: ='6Detailed Cash Flow'!B43 -> 3.8876454

Sheet 0.2Proposal Dashboard
A1: BARSTOW PV + ESS PROJECT — RECONSTRUCTED OVERVIEW
A3: Project Input / Configuration | B3: Value | C3: Financial / Savings | D3: Value
A4: Verified Annual Load (kWh) | B4: ='Model Assumptions'!C4 -> 709501 | C4: Gross Project Cost | D4: ='0.1Project Overview'!D4 -> 1074972.3
A5: PV Capacity (kW-DC) | B5: =Recommendation!B6 -> 406.43 | C5: Modeled Incentives | D5: ='0.1Project Overview'!D5+'0.1Project Overview'!D6+'0.1Project Overview'!D7 -> 682607.41
A6: PV Panels | B6: =Recommendation!B5 -> 838 | C6: Net Project Cost | D6: ='0.1Project Overview'!D8 -> 392364.89
A7: Annual PV Generation (kWh) | B7: =Recommendation!B7 -> 710207.51 | C7: Year-1 Screening Savings | D7: ='4Electric Bills'!AA16 -> 106305.62
A8: SPT ESS Units | B8: =Recommendation!B9 -> 2 | C8: IRR | D8: ='5Cash Purchase'!B12 -> 0.21518283
A9: ESS Energy (kWh) | B9: =Recommendation!B10 -> 430.08 | C9: Net Present Value | D9: ='Proposal Summary'!E5 -> 0
A10: ESS Power (kW) | B10: =Recommendation!B11 -> 215.04 | C10: Payback Period (Years) | D10: ='0.1Project Overview'!D9 -> 3.8876454
C11: 30-Year Electric Bill Savings | D11: ='5Cash Purchase'!B11 -> 4694064

Sheet 1PV Proposal
A1: 4.1.1 PV SYSTEM DETAILS
A3: GENERAL INFORMATION | D3: SOLAR PV SYSTEM COST AND INCENTIVES | G3: ENERGY CONSUMPTION MIX | H3: kWh
A4: Facility | B4: Barstow — two-account analytical baseline | D4: Solar PV System Cost | E4: ='1PV Proposal'!B8*1000*'Model Assumptions'!C17 -> 816924.3 | G4: Annual Energy Use | H4: ='PV Production'!B17 -> 709501
A5: Verified Annual Energy Use (kWh) | B5: 709501 | D5: Federal ITC — 30% | E5: =-E4*'3Rebates Incentives'!E4 -> -245077.29 | G5: Solar PV + PV-Charged ESS Served Load | H5: ='4Electric Bills'!S16 -> 623663.61
A6: PV Panel Rating (W) | B6: 485 | D6: Federal MACRS Tax Benefit — Years 1–6 | E6: =-E4*(1-0.5*'3Rebates Incentives'!E4)*'3Rebates Incentives'!E5 -> -208315.7 | G6: Utility-Supplied Load | H6: =H4-H5 -> 85837.392
A7: PV Panel Count | B7: 838 | D7: State (CA) Depreciation Tax Benefit — Years 1–6 | E7: =-E4*'3Rebates Incentives'!E6 -> -65353.944
A8: PV Power Rating (kW-DC) | B8: =Recommendation!B6 -> 406.43 | D8: Net Solar PV System Cost | E8: =SUM(E4:E7) -> 298177.37
A9: Modeled Annual PV Generation (kWh) | B9: =Recommendation!B7 -> 710207.51 | D9: Annual PV Coverage | E9: ='PV Production'!I17 -> 1.0009958
A12: Month | B12: Energy Use (kWh) | C12: Solar Generation (kWh) | D12: Surplus/(Deficit) (kWh)
A13: ='PV Production'!A5 -> Jan 2024 | B13: ='PV Production'!B5 -> 54844 | C13: ='PV Production'!G5 -> 43391.64 | D13: ='PV Production'!H5 -> -11452.36
A14: ='PV Production'!A6 -> Feb 2024 | B14: ='PV Production'!B6 -> 48926 | C14: ='PV Production'!G6 -> 46834.144 | D14: ='PV Production'!H6 -> -2091.856
A15: ='PV Production'!A7 -> Mar 2024 | B15: ='PV Production'!B7 -> 52449 | C15: ='PV Production'!G7 -> 61748.868 | D15: ='PV Production'!H7 -> 9299.868
A16: ='PV Production'!A8 -> Apr 2024 | B16: ='PV Production'!B8 -> 40752 | C16: ='PV Production'!G8 -> 69502.882 | D16: ='PV Production'!H8 -> 28750.882
A17: ='PV Production'!A9 -> May 2024 | B17: ='PV Production'!B9 -> 51220 | C17: ='PV Production'!G9 -> 76926.724 | D17: ='PV Production'!H9 -> 25706.724
A18: ='PV Production'!A10 -> Jun 2024 | B18: ='PV Production'!B10 -> 50744 | C18: ='PV Production'!G10 -> 76305.766 | D18: ='PV Production'!H10 -> 25561.766
A19: ='PV Production'!A11 -> Jul 2024 | B19: ='PV Production'!B11 -> 81109 | C19: ='PV Production'!G11 -> 70470.772 | D19: ='PV Production'!H11 -> -10638.228
A20: ='PV Production'!A12 -> Aug 2024 | B20: ='PV Production'!B12 -> 80723 | C20: ='PV Production'!G12 -> 69633.61 | D20: ='PV Production'!H12 -> -11089.39
A21: ='PV Production'!A13 -> Sep 2024 | B21: ='PV Production'!B13 -> 84369 | C21: ='PV Production'!G13 -> 60646.06 | D21: ='PV Production'!H13 -> -23722.94
A22: ='PV Production'!A14 -> Oct 2023 | B22: ='PV Production'!B14 -> 50017 | C22: ='PV Production'!G14 -> 54977.828 | D22: ='PV Production'!H14 -> 4960.828
A23: ='PV Production'!A15 -> Nov 2023 | B23: ='PV Production'!B15 -> 61096 | C23: ='PV Production'!G15 -> 42779.9 | D23: ='PV Production'!H15 -> -18316.1
A24: ='PV Production'!A16 -> Dec 2023 | B24: ='PV Production'!B16 -> 53252 | C24: ='PV Production'!G16 -> 36989.32 | D24: ='PV Production'!H16 -> -16262.68
A25: Annual | B25: =SUM(B13:B24) -> 709501 | C25: =SUM(C13:C24) -> 710207.51 | D25: =SUM(D13:D24) -> 706.514

Sheet 2ESS Proposal
A1: 4.1.2 ENERGY STORAGE SYSTEM (ESS) DETAILS
A3: GENERAL INFORMATION | D3: ESS COST AND INCENTIVES | G3: ENERGY STORAGE ANNUAL UTILIZATION | H3: Days / billing-cycle-day proxy
A4: ESS Platform | B4: SPT6800 commercial ESS | D4: ESS Cost | E4: ='2ESS Proposal'!B7*'Model Assumptions'!C18 -> 258048 | G4: 0–20% | H4: =SUMPRODUCT(($J$13:$J$24>=0)*($J$13:$J$24<0.2)*$K$13:$K$24) -> 274
A5: Battery Sizing Unit Energy (kWh) | B5: 215.04 | D5: Federal ITC — 30% | E5: =-E4*'3Rebates Incentives'!E4 -> -77414.4 | G5: 20–40% | H5: =SUMPRODUCT(($J$13:$J$24>=0.2)*($J$13:$J$24<0.4)*$K$13:$K$24) -> 63
A6: Recommended Units | B6: 2 | D6: Federal MACRS Tax Benefit — Years 1–6 | E6: =-E4*(1-0.5*'3Rebates Incentives'!E4)*'3Rebates Incentives'!E5 -> -65802.24 | G6: 40–60% | H6: =SUMPRODUCT(($J$13:$J$24>=0.4)*($J$13:$J$24<0.6)*$K$13:$K$24) -> 29
A7: Nominal ESS Energy (kWh) | B7: 430.08 | D7: State (CA) Depreciation Tax Benefit — Years 1–6 | E7: =-E4*'3Rebates Incentives'!E6 -> -20643.84 | G7: 60–80% | H7: =SUMPRODUCT(($J$13:$J$24>=0.6)*($J$13:$J$24<0.8)*$K$13:$K$24) -> 0
A8: AC PCS Rating (kW) | B8: 200 | D8: Net ESS Cost | E8: =SUM(E4:E7) -> 94187.52 | G8: 80–100% | H8: =SUMPRODUCT(($J$13:$J$24>=0.8)*($J$13:$J$24<=1)*$K$13:$K$24) -> 0
A9: Battery-Side Theoretical Power @ 0.5C (kW) | B9: 215.04 | G9: >100% | H9: 0
A10: Demand-Shave Operating Target (kW) | B10: 100
A11: Role | B11: TOU energy shifting + peak-demand shaving
A12: Energy Output and Demand Savings From Solar PV and Energy Storage | J12: Monthly Avg ESS Utilization | K12: Billing Days
A13: Month | B13: ESS Energy Discharge (kWh) | C13: Solar PV Generation (kWh) | D13: ESS Energy as % of PV Energy | E13: Demand Savings — Screening ($) | F13: Grid-Charging Arbitrage Savings ($) | J13: ='PV-ESS Energy Flow'!K4/('PV-ESS Energy Flow'!B4*'PV-ESS Energy Flow'!H4) -> 0.17610643 | K13: ='PV-ESS Energy Flow'!B4 -> 33
A14: ='PV-ESS Energy Flow'!A4 -> Jan | B14: ='PV-ESS Energy Flow'!K4 -> 2137 | C14: ='PV-ESS Energy Flow'!D4 -> 43391.64 | D14: ='PV-ESS Energy Flow'!L4 -> 0.049249118 | E14: ='PV-ESS Energy Flow'!O4 -> 2643.674 | F14: ='PV-ESS Energy Flow'!W4 -> 340.9668 | J14: ='PV-ESS Energy Flow'!K5/('PV-ESS Energy Flow'!B5*'PV-ESS Energy Flow'!H5) -> 0.16334964 | K14: ='PV-ESS Energy Flow'!B5 -> 30
A15: ='PV-ESS Energy Flow'!A5 -> Feb | B15: ='PV-ESS Energy Flow'!K5 -> 1802 | C15: ='PV-ESS Energy Flow'!D5 -> 46834.144 | D15: ='PV-ESS Energy Flow'!L5 -> 0.038476202 | E15: ='PV-ESS Energy Flow'!O5 -> 2702.9719 | F15: ='PV-ESS Energy Flow'!W5 -> 271.36109 | J15: ='PV-ESS Energy Flow'!K6/('PV-ESS Energy Flow'!B6*'PV-ESS Energy Flow'!H6) -> 0.13475454 | K15: ='PV-ESS Energy Flow'!B6 -> 29
A16: ='PV-ESS Energy Flow'!A6 -> Mar | B16: ='PV-ESS Energy Flow'!K6 -> 1437 | C16: ='PV-ESS Energy Flow'!D6 -> 61748.868 | D16: ='PV-ESS Energy Flow'!L6 -> 0.023271682 | E16: ='PV-ESS Energy Flow'!O6 -> 3303.2762 | F16: ='PV-ESS Energy Flow'!W6 -> 0 | J16: ='PV-ESS Energy Flow'!K7/('PV-ESS Energy Flow'!B7*'PV-ESS Energy Flow'!H7) -> 0.11192328 | K16: ='PV-ESS Energy Flow'!B7 -> 32
A17: ='PV-ESS Energy Flow'!A7 -> Apr | B17: ='PV-ESS Energy Flow'!K7 -> 1317 | C17: ='PV-ESS Energy Flow'!D7 -> 69502.882 | D17: ='PV-ESS Energy Flow'!L7 -> 0.018948855 | E17: ='PV-ESS Energy Flow'!O7 -> 3210.7567 | F17: ='PV-ESS Energy Flow'!W7 -> 0 | J17: ='PV-ESS Energy Flow'!K8/('PV-ESS Energy Flow'!B8*'PV-ESS Energy Flow'!H8) -> 0.1200471 | K17: ='PV-ESS Energy Flow'!B8 -> 29
A18: ='PV-ESS Energy Flow'!A8 -> May | B18: ='PV-ESS Energy Flow'!K8 -> 1280.1623 | C18: ='PV-ESS Energy Flow'!D8 -> 76926.724 | D18: ='PV-ESS Energy Flow'!L8 -> 0.016641321 | E18: ='PV-ESS Energy Flow'!O8 -> 3091.3018 | F18: ='PV-ESS Energy Flow'!W8 -> 0 | J18: ='PV-ESS Energy Flow'!K9/('PV-ESS Energy Flow'!B9*'PV-ESS Energy Flow'!H9) -> 0.1813888 | K18: ='PV-ESS Energy Flow'!B9 -> 30
A19: ='PV-ESS Energy Flow'!A9 -> Jun | B19: ='PV-ESS Energy Flow'!K9 -> 2001 | C19: ='PV-ESS Energy Flow'!D9 -> 76305.766 | D19: ='PV-ESS Energy Flow'!L9 -> 0.026223444 | E19: ='PV-ESS Energy Flow'!O9 -> 3039.4649 | F19: ='PV-ESS Energy Flow'!W9 -> 0 | J19: ='PV-ESS Energy Flow'!K10/('PV-ESS Energy Flow'!B10*'PV-ESS Energy Flow'!H10) -> 0.23057829 | K19: ='PV-ESS Energy Flow'!B10 -> 33
A20: ='PV-ESS Energy Flow'!A10 -> Jul | B20: ='PV-ESS Energy Flow'!K10 -> 2798 | C20: ='PV-ESS Energy Flow'!D10 -> 70470.772 | D20: ='PV-ESS Energy Flow'!L10 -> 0.039704404 | E20: ='PV-ESS Energy Flow'!O10 -> 3690.6724 | F20: ='PV-ESS Energy Flow'!W10 -> 1403.1639 | J20: ='PV-ESS Energy Flow'!K11/('PV-ESS Energy Flow'!B11*'PV-ESS Energy Flow'!H11) -> 0.51791881 | K20: ='PV-ESS Energy Flow'!B11 -> 29
A21: ='PV-ESS Energy Flow'!A11 -> Aug | B21: ='PV-ESS Energy Flow'!K11 -> 5523 | C21: ='PV-ESS Energy Flow'!D11 -> 69633.61 | D21: ='PV-ESS Energy Flow'!L11 -> 0.079315147 | E21: ='PV-ESS Energy Flow'!O11 -> 4235.2234 | F21: ='PV-ESS Energy Flow'!W11 -> 1352.6178 | J21: ='PV-ESS Energy Flow'!K12/('PV-ESS Energy Flow'!B12*'PV-ESS Energy Flow'!H12) -> 0.39985308 | K21: ='PV-ESS Energy Flow'!B12 -> 30
A22: ='PV-ESS Energy Flow'!A12 -> Sep | B22: ='PV-ESS Energy Flow'!K12 -> 4411 | C22: ='PV-ESS Energy Flow'!D12 -> 60646.06 | D22: ='PV-ESS Energy Flow'!L12 -> 0.072733497 | E22: ='PV-ESS Energy Flow'!O12 -> 4789.6301 | F22: ='PV-ESS Energy Flow'!W12 -> 1041.5336 | J22: ='PV-ESS Energy Flow'!K13/('PV-ESS Energy Flow'!B13*'PV-ESS Energy Flow'!H13) -> 0.15951112 | K22: ='PV-ESS Energy Flow'!B13 -> 29
A23: ='PV-ESS Energy Flow'!A13 -> Oct | B23: ='PV-ESS Energy Flow'!K13 -> 1701 | C23: ='PV-ESS Energy Flow'!D13 -> 54977.828 | D23: ='PV-ESS Energy Flow'!L13 -> 0.030939745 | E23: ='PV-ESS Energy Flow'!O13 -> 2887.8498 | F23: ='PV-ESS Energy Flow'!W13 -> 0 | J23: ='PV-ESS Energy Flow'!K14/('PV-ESS Energy Flow'!B14*'PV-ESS Energy Flow'!H14) -> 0.14056272 | K23: ='PV-ESS Energy Flow'!B14 -> 32
A24: ='PV-ESS Energy Flow'!A14 -> Nov | B24: ='PV-ESS Energy Flow'!K14 -> 1654 | C24: ='PV-ESS Energy Flow'!D14 -> 42779.9 | D24: ='PV-ESS Energy Flow'!L14 -> 0.038663017 | E24: ='PV-ESS Energy Flow'!O14 -> 2623.63 | F24: ='PV-ESS Energy Flow'!W14 -> 270.6417 | J24: ='PV-ESS Energy Flow'!K15/('PV-ESS Energy Flow'!B15*'PV-ESS Energy Flow'!H15) -> 0.18347373 | K24: ='PV-ESS Energy Flow'!B15 -> 30
A25: ='PV-ESS Energy Flow'!A15 -> Dec | B25: ='PV-ESS Energy Flow'!K15 -> 2024 | C25: ='PV-ESS Energy Flow'!D15 -> 36989.32 | D25: ='PV-ESS Energy Flow'!L15 -> 0.054718497 | E25: ='PV-ESS Energy Flow'!O15 -> 3154.3021 | F25: ='PV-ESS Energy Flow'!W15 -> 332.35377 | J25: =SUMPRODUCT(J13:J24,K13:K24)/SUM(K13:K24) -> 0.20867984 | K25: =SUM(K13:K24) -> 366
A26: Total | B26: ='PV-ESS Energy Flow'!K16 -> 28085.162 | C26: ='PV-ESS Energy Flow'!D16 -> 710207.51 | D26: ='PV-ESS Energy Flow'!L16 -> 0.039545009 | E26: ='PV-ESS Energy Flow'!O16 -> 39372.753 | F26: ='PV-ESS Energy Flow'!W16 -> 5012.6387

Sheet 3Rebates Incentives
A1: 4.1.3 ITC + MACRS — Original Barstow Schedule Applied to Reconstructed Cost Basis
A3: Item | B3: PV Cost Basis ($) | C3: ESS Cost Basis ($) | D3: Combined Cost ($) | E3: Tax / Credit Rate | F3: Total Tax Benefit ($) | G3: Timing | H3: Basis
A4: Federal ITC | B4: ='1PV Proposal'!E4 -> 816924.3 | C4: ='2ESS Proposal'!E4 -> 258048 | D4: =B4+C4 -> 1074972.3 | E4: 0.3 | F4: =D4*E4 -> 322491.69 | G4: Year 1 | H4: Original proposal: 30% ITC
A5: Federal MACRS depreciation tax shield | B5: ='1PV Proposal'!E4 -> 816924.3 | C5: ='2ESS Proposal'!E4 -> 258048 | D5: =B5+C5 -> 1074972.3 | E5: 0.3 | F5: =D5*(1-0.5*E4)*E5 -> 274117.94 | G5: Years 1–6 | H5: 30% federal income tax rate applied to depreciation deductions
A6: California depreciation tax shield | B6: ='1PV Proposal'!E4 -> 816924.3 | C6: ='2ESS Proposal'!E4 -> 258048 | D6: =B6+C6 -> 1074972.3 | E6: 0.08 | F6: =D6*E6 -> 85997.784 | G6: Years 1–6 | H6: 8% state income tax rate applied to depreciation deductions
A9: Tax Schedule | B9: Basis ($) | C9: Y1 | D9: Y2 | E9: Y3 | F9: Y4 | G9: Y5 | H9: Y6 | I9: Total | J9: Tax Rate | K9: Total Tax Benefit
A10: Federal MACRS depreciation % of reduced basis | B10: =D5*(1-0.5*$E$4) -> 913726.45 | C10: 0.68 | D10: 0.128 | E10: 0.0768 | F10: 0.04608 | G10: 0.04608 | H10: 0.02304 | I10: =SUM(C10:H10) -> 1 | J10: 0.3 | K10: =B10*I10*J10 -> 274117.94
A11: California MACRS depreciation % of full basis | B11: =D6 -> 1074972.3 | C11: 0.2 | D11: 0.32 | E11: 0.192 | F11: 0.1152 | G11: 0.1152 | H11: 0.0576 | I11: =SUM(C11:H11) -> 1 | J11: 0.08 | K11: =B11*I11*J11 -> 85997.784
A12: Federal ITC | B12: =D4 -> 1074972.3 | C12: 0.3 | D12: 0 | E12: 0 | F12: 0 | G12: 0 | H12: 0 | I12: =SUM(C12:H12) -> 0.3 | J12: 1 | K12: =B12*C12 -> 322491.69
A15: Annual Tax Benefit | B15: Year 1 | C15: Year 2 | D15: Year 3 | E15: Year 4 | F15: Year 5 | G15: Year 6 | H15: Total
A16: Federal ITC | B16: =$B$12*C12 -> 322491.69 | C16: =$B$12*D12 -> 0 | D16: =$B$12*E12 -> 0 | E16: =$B$12*F12 -> 0 | F16: =$B$12*G12 -> 0 | G16: =$B$12*H12 -> 0 | H16: =SUM(B16:G16) -> 322491.69
A17: Federal MACRS tax shield | B17: =$B$10*C10*$J$10 -> 186400.2 | C17: =$B$10*D10*$J$10 -> 35087.096 | D17: =$B$10*E10*$J$10 -> 21052.258 | E17: =$B$10*F10*$J$10 -> 12631.355 | F17: =$B$10*G10*$J$10 -> 12631.355 | G17: =$B$10*H10*$J$10 -> 6315.6773 | H17: =SUM(B17:G17) -> 274117.94
A18: California depreciation tax shield | B18: =$B$11*C11*$J$11 -> 17199.557 | C18: =$B$11*D11*$J$11 -> 27519.291 | D18: =$B$11*E11*$J$11 -> 16511.575 | E18: =$B$11*F11*$J$11 -> 9906.9447 | F18: =$B$11*G11*$J$11 -> 9906.9447 | G18: =$B$11*H11*$J$11 -> 4953.4724 | H18: =SUM(B18:G18) -> 85997.784
A19: Total Tax Benefit | B19: =SUM(B16:B18) -> 526091.44 | C19: =SUM(C16:C18) -> 62606.387 | D19: =SUM(D16:D18) -> 37563.832 | E19: =SUM(E16:E18) -> 22538.299 | F19: =SUM(F16:F18) -> 22538.299 | G19: =SUM(G16:G18) -> 11269.15 | H19: =SUM(B19:G19) -> 682607.41
A22: California depreciation uses 20%, 32%, 19.2%, 11.52%, 11.52%, 5.76% over Years 1–6 on full project cost. Federal depreciation first reduces basis by 50% of the 30% ITC (85% basis), then applies 2024 60% bonus depreciation plus MACRS to produce 68%, 12.8%, 7.68%, 4.608%, 4.608%, 2.304% over Years 1–6. Federal tax shield = depreciation deduction × 30%; California tax shield = depreciation deduction × 8%. ITC is recognized in Year 1.
A28: 4.1.3 REBATES & INCENTIVES — PROJECT AMOUNTS
A30: Incentive / Tax Benefit | B30: PV ($) | C30: ESS ($) | D30: Combined ($) | E30: Timing
A31: Federal ITC — 30% | B31: ='1PV Proposal'!E4*'3Rebates Incentives'!E4 -> 245077.29 | C31: ='2ESS Proposal'!E4*'3Rebates Incentives'!E4 -> 77414.4 | D31: =B31+C31 -> 322491.69 | E31: Year 1
A32: Federal MACRS tax benefit | B32: ='1PV Proposal'!E4*(1-0.5*'3Rebates Incentives'!E4)*'3Rebates Incentives'!E5 -> 208315.7 | C32: ='2ESS Proposal'!E4*(1-0.5*'3Rebates Incentives'!E4)*'3Rebates Incentives'!E5 -> 65802.24 | D32: =B32+C32 -> 274117.94 | E32: Years 1–6
A33: California depreciation tax benefit | B33: ='1PV Proposal'!E4*'3Rebates Incentives'!E6 -> 65353.944 | C33: ='2ESS Proposal'!E4*'3Rebates Incentives'!E6 -> 20643.84 | D33: =B33+C33 -> 85997.784 | E33: Years 1–6
A34: Total modeled tax benefits | B34: =SUM(B31:B33) -> 518746.93 | C34: =SUM(C31:C33) -> 163860.48 | D34: =SUM(D31:D33) -> 682607.41 | E34: Per 30-year cash-flow model

Sheet 4Electric Bills
A1: 4.1.5 CURRENT ELECTRIC BILL | B1: 4.1.5 CURRENT ELECTRIC BILL — Reconstructed Historical Baseline | C1: 4.1.5 CURRENT ELECTRIC BILL — Reconstructed Historical Baseline | D1: 4.1.5 CURRENT ELECTRIC BILL — Reconstructed Historical Baseline | E1: 4.1.5 CURRENT ELECTRIC BILL — Reconstructed Historical Baseline | F1: 4.1.5 CURRENT ELECTRIC BILL — Reconstructed Historical Baseline | G1: 4.1.5 CURRENT ELECTRIC BILL — Reconstructed Historical Baseline | H1: 4.1.5 CURRENT ELECTRIC BILL — Reconstructed Historical Baseline | I1: 4.1.5 CURRENT ELECTRIC BILL — Reconstructed Historical Baseline | J1: 4.1.5 CURRENT ELECTRIC BILL — Reconstructed Historical Baseline | K1: 4.1.5 CURRENT ELECTRIC BILL — Reconstructed Historical Baseline | L1: 4.1.5 CURRENT ELECTRIC BILL — Reconstructed Historical Baseline | M1: 4.1.5 CURRENT ELECTRIC BILL — Reconstructed Historical Baseline | N1: 4.1.5 CURRENT ELECTRIC BILL — Reconstructed Historical Baseline | P1: 4.1.6 NEW ELECTRIC BILL
A3: Period | B3: Load kWh | C3: On-Peak | D3: Mid-Peak | E3: Off-Peak | F3: Super-Off | G3: Max Demand kW | H3: Energy Charges | I3: Demand Charges | J3: Other/Residual | K3: Current Bill | L3: PV Gen | P3: Period | Q3: Load (kWh) | R3: PV Generation (kWh) | S3: PV Self-Consumed (kWh) | T3: PV Export Proxy (kWh) | U3: Max Demand (kW) | V3: PV Energy Savings ($) | W3: Demand Savings ($) | X3: Export Value ($) | Y3: Grid-Charging Arbitrage Savings ($) | Z3: New Bill ($) | AA3: Total Savings ($) | AB3: Grid-Charge Input (kWh) | AC3: Grid-Charged Discharge (kWh)
A4: ='Combined TOU Profile'!A5 -> Oct 2023 | B4: ='Combined TOU Profile'!F5 -> 50017 | C4: ='Combined TOU Profile'!G5 -> 444 | D4: ='Combined TOU Profile'!H5 -> 1257 | E4: ='Combined TOU Profile'!I5 -> 23266 | F4: ='Combined TOU Profile'!J5 -> 25050 | G4: ='Combined TOU Profile'!M5 -> 552 | H4: ='Combined TOU Profile'!P5 -> 4394.39 | I4: ='Combined TOU Profile'!Q5 -> 14230.24 | J4: ='Combined TOU Profile'!S5 -> 1948.6 | K4: ='Combined TOU Profile'!R5 -> 20573.23 | L4: =INDEX('PV Production'!$G$5:$G$16,MATCH(A4,'PV Production'!$A$5:$A$16,0)) -> 54977.828 | P4: =A4 -> Oct 2023 | Q4: =B4 -> 50017 | R4: =L4 -> 54977.828 | S4: ='PV-ESS Energy Flow'!E13+'PV-ESS Energy Flow'!I13 -> 51718 | T4: =MAX(R4-S4,0) -> 3259.828 | U4: =G4 -> 552 | V4: ='PV-ESS Energy Flow'!P13 -> 4775.9669 | W4: ='PV-ESS Energy Flow'!O13 -> 2887.8498 | X4: ='PV-ESS Energy Flow'!Q13 -> 162.9914 | Y4: ='PV-ESS Energy Flow'!W13 -> 0 | Z4: =MAX(K4-SUM(V4:Y4),0) -> 12746.422 | AA4: =K4-Z4 -> 7826.8081 | AB4: ='PV-ESS Energy Flow'!R13 -> 0 | AC4: ='PV-ESS Energy Flow'!J13 -> 0
A5: ='Combined TOU Profile'!A6 -> Nov 2023 | B5: ='Combined TOU Profile'!F6 -> 61096 | C5: ='Combined TOU Profile'!G6 -> 0 | D5: ='Combined TOU Profile'!H6 -> 1654 | E5: ='Combined TOU Profile'!I6 -> 7943 | F5: ='Combined TOU Profile'!J6 -> 51499 | G5: ='Combined TOU Profile'!M6 -> 622 | H5: ='Combined TOU Profile'!P6 -> 3045.26 | I5: ='Combined TOU Profile'!Q6 -> 15037.2 | J5: ='Combined TOU Profile'!S6 -> 3765.68 | K5: ='Combined TOU Profile'!R6 -> 21848.14 | L5: =INDEX('PV Production'!$G$5:$G$16,MATCH(A5,'PV Production'!$A$5:$A$16,0)) -> 42779.9 | P5: =A5 -> Nov 2023 | Q5: =B5 -> 61096 | R5: =L5 -> 42779.9 | S5: ='PV-ESS Energy Flow'!E14+'PV-ESS Energy Flow'!I14 -> 42779.9 | T5: =MAX(R5-S5,0) -> 0 | U5: =G5 -> 622 | V5: ='PV-ESS Energy Flow'!P14 -> 3950.5662 | W5: ='PV-ESS Energy Flow'!O14 -> 2623.63 | X5: ='PV-ESS Energy Flow'!Q14 -> 0 | Y5: ='PV-ESS Energy Flow'!W14 -> 270.6417 | Z5: =MAX(K5-SUM(V5:Y5),0) -> 15003.302 | AA5: =K5-Z5 -> 6844.838 | AB5: ='PV-ESS Energy Flow'!R14 -> 1837.7778 | AC5: ='PV-ESS Energy Flow'!J14 -> 1654
A6: ='Combined TOU Profile'!A7 -> Dec 2023 | B6: ='Combined TOU Profile'!F7 -> 53252 | C6: ='Combined TOU Profile'!G7 -> 0 | D6: ='Combined TOU Profile'!H7 -> 2024 | E6: ='Combined TOU Profile'!I7 -> 9061 | F6: ='Combined TOU Profile'!J7 -> 42167 | G6: ='Combined TOU Profile'!M7 -> 513 | H6: ='Combined TOU Profile'!P7 -> 3003.59 | I6: ='Combined TOU Profile'!Q7 -> 13768.43 | J6: ='Combined TOU Profile'!S7 -> 2828.81 | K6: ='Combined TOU Profile'!R7 -> 19600.83 | L6: =INDEX('PV Production'!$G$5:$G$16,MATCH(A6,'PV Production'!$A$5:$A$16,0)) -> 36989.32 | P6: =A6 -> Dec 2023 | Q6: =B6 -> 53252 | R6: =L6 -> 36989.32 | S6: ='PV-ESS Energy Flow'!E15+'PV-ESS Energy Flow'!I15 -> 36989.32 | T6: =MAX(R6-S6,0) -> 0 | U6: =G6 -> 513 | V6: ='PV-ESS Energy Flow'!P15 -> 3415.8275 | W6: ='PV-ESS Energy Flow'!O15 -> 3154.3021 | X6: ='PV-ESS Energy Flow'!Q15 -> 0 | Y6: ='PV-ESS Energy Flow'!W15 -> 332.35377 | Z6: =MAX(K6-SUM(V6:Y6),0) -> 12698.347 | AA6: =K6-Z6 -> 6902.4834 | AB6: ='PV-ESS Energy Flow'!R15 -> 2248.8889 | AC6: ='PV-ESS Energy Flow'!J15 -> 2024
A7: ='Combined TOU Profile'!A8 -> Jan 2024 | B7: ='Combined TOU Profile'!F8 -> 54844 | C7: ='Combined TOU Profile'!G8 -> 0 | D7: ='Combined TOU Profile'!H8 -> 2137 | E7: ='Combined TOU Profile'!I8 -> 9236 | F7: ='Combined TOU Profile'!J8 -> 43471 | G7: ='Combined TOU Profile'!M8 -> 655 | H7: ='Combined TOU Profile'!P8 -> 3229.29 | I7: ='Combined TOU Profile'!Q8 -> 16264.68 | J7: ='Combined TOU Profile'!S8 -> 3250.73 | K7: ='Combined TOU Profile'!R8 -> 22744.7 | L7: =INDEX('PV Production'!$G$5:$G$16,MATCH(A7,'PV Production'!$A$5:$A$16,0)) -> 43391.64 | P7: =A7 -> Jan 2024 | Q7: =B7 -> 54844 | R7: =L7 -> 43391.64 | S7: ='PV-ESS Energy Flow'!E4+'PV-ESS Energy Flow'!I4 -> 43391.64 | T7: =MAX(R7-S7,0) -> 0 | U7: =G7 -> 655 | V7: ='PV-ESS Energy Flow'!P4 -> 4007.0582 | W7: ='PV-ESS Energy Flow'!O4 -> 2643.674 | X7: ='PV-ESS Energy Flow'!Q4 -> 0 | Y7: ='PV-ESS Energy Flow'!W4 -> 340.9668 | Z7: =MAX(K7-SUM(V7:Y7),0) -> 15753.001 | AA7: =K7-Z7 -> 6991.6989 | AB7: ='PV-ESS Energy Flow'!R4 -> 2374.4444 | AC7: ='PV-ESS Energy Flow'!J4 -> 2137
A8: ='Combined TOU Profile'!A9 -> Feb 2024 | B8: ='Combined TOU Profile'!F9 -> 48926 | C8: ='Combined TOU Profile'!G9 -> 0 | D8: ='Combined TOU Profile'!H9 -> 1802 | E8: ='Combined TOU Profile'!I9 -> 7990 | F8: ='Combined TOU Profile'!J9 -> 39134 | G8: ='Combined TOU Profile'!M9 -> 640 | H8: ='Combined TOU Profile'!P9 -> 2906.09 | I8: ='Combined TOU Profile'!Q9 -> 16287.34 | J8: ='Combined TOU Profile'!S9 -> 2948.41 | K8: ='Combined TOU Profile'!R9 -> 22141.84 | L8: =INDEX('PV Production'!$G$5:$G$16,MATCH(A8,'PV Production'!$A$5:$A$16,0)) -> 46834.144 | P8: =A8 -> Feb 2024 | Q8: =B8 -> 48926 | R8: =L8 -> 46834.144 | S8: ='PV-ESS Energy Flow'!E5+'PV-ESS Energy Flow'!I5 -> 46834.144 | T8: =MAX(R8-S8,0) -> 0 | U8: =G8 -> 640 | V8: ='PV-ESS Energy Flow'!P5 -> 4324.9607 | W8: ='PV-ESS Energy Flow'!O5 -> 2702.9719 | X8: ='PV-ESS Energy Flow'!Q5 -> 0 | Y8: ='PV-ESS Energy Flow'!W5 -> 271.36109 | Z8: =MAX(K8-SUM(V8:Y8),0) -> 14842.546 | AA8: =K8-Z8 -> 7299.2937 | AB8: ='PV-ESS Energy Flow'!R5 -> 2002.2222 | AC8: ='PV-ESS Energy Flow'!J5 -> 1802
A9: ='Combined TOU Profile'!A10 -> Mar 2024 | B9: ='Combined TOU Profile'!F10 -> 52449 | C9: ='Combined TOU Profile'!G10 -> 0 | D9: ='Combined TOU Profile'!H10 -> 1437 | E9: ='Combined TOU Profile'!I10 -> 7826 | F9: ='Combined TOU Profile'!J10 -> 43186 | G9: ='Combined TOU Profile'!M10 -> 500 | H9: ='Combined TOU Profile'!P10 -> 2933.55 | I9: ='Combined TOU Profile'!Q10 -> 14743.12 | J9: ='Combined TOU Profile'!S10 -> 2706.73 | K9: ='Combined TOU Profile'!R10 -> 20383.4 | L9: =INDEX('PV Production'!$G$5:$G$16,MATCH(A9,'PV Production'!$A$5:$A$16,0)) -> 61748.868 | P9: =A9 -> Mar 2024 | Q9: =B9 -> 52449 | R9: =L9 -> 61748.868 | S9: ='PV-ESS Energy Flow'!E6+'PV-ESS Energy Flow'!I6 -> 53886 | T9: =MAX(R9-S9,0) -> 7862.868 | U9: =G9 -> 500 | V9: ='PV-ESS Energy Flow'!P6 -> 4976.1737 | W9: ='PV-ESS Energy Flow'!O6 -> 3303.2762 | X9: ='PV-ESS Energy Flow'!Q6 -> 393.1434 | Y9: ='PV-ESS Energy Flow'!W6 -> 0 | Z9: =MAX(K9-SUM(V9:Y9),0) -> 11710.807 | AA9: =K9-Z9 -> 8672.5933 | AB9: ='PV-ESS Energy Flow'!R6 -> 0 | AC9: ='PV-ESS Energy Flow'!J6 -> 0
A10: ='Combined TOU Profile'!A11 -> Apr 2024 | B10: ='Combined TOU Profile'!F11 -> 40752 | C10: ='Combined TOU Profile'!G11 -> 0 | D10: ='Combined TOU Profile'!H11 -> 1317 | E10: ='Combined TOU Profile'!I11 -> 6094 | F10: ='Combined TOU Profile'!J11 -> 33341 | G10: ='Combined TOU Profile'!M11 -> 442 | H10: ='Combined TOU Profile'!P11 -> 2317.62 | I10: ='Combined TOU Profile'!Q11 -> 12325.74 | J10: ='Combined TOU Profile'!S11 -> 2416.7 | K10: ='Combined TOU Profile'!R11 -> 17060.06 | L10: =INDEX('PV Production'!$G$5:$G$16,MATCH(A10,'PV Production'!$A$5:$A$16,0)) -> 69502.882 | P10: =A10 -> Apr 2024 | Q10: =B10 -> 40752 | R10: =L10 -> 69502.882 | S10: ='PV-ESS Energy Flow'!E7+'PV-ESS Energy Flow'!I7 -> 42069 | T10: =MAX(R10-S10,0) -> 27433.882 | U10: =G10 -> 442 | V10: ='PV-ESS Energy Flow'!P7 -> 3884.9172 | W10: ='PV-ESS Energy Flow'!O7 -> 3210.7567 | X10: ='PV-ESS Energy Flow'!Q7 -> 1371.6941 | Y10: ='PV-ESS Energy Flow'!W7 -> 0 | Z10: =MAX(K10-SUM(V10:Y10),0) -> 8592.692 | AA10: =K10-Z10 -> 8467.368 | AB10: ='PV-ESS Energy Flow'!R7 -> 0 | AC10: ='PV-ESS Energy Flow'!J7 -> 0
A11: ='Combined TOU Profile'!A12 -> May 2024 | B11: ='Combined TOU Profile'!F12 -> 51220 | C11: ='Combined TOU Profile'!G12 -> 403.83324 | D11: ='Combined TOU Profile'!H12 -> 876.32908 | E11: ='Combined TOU Profile'!I12 -> 7752.3609 | F11: ='Combined TOU Profile'!J12 -> 42187.477 | G11: ='Combined TOU Profile'!M12 -> 466 | H11: ='Combined TOU Profile'!P12 -> 3298.4046 | I11: ='Combined TOU Profile'!Q12 -> 12968.12 | J11: ='Combined TOU Profile'!S12 -> 2217.6954 | K11: ='Combined TOU Profile'!R12 -> 18484.22 | L11: =INDEX('PV Production'!$G$5:$G$16,MATCH(A11,'PV Production'!$A$5:$A$16,0)) -> 76926.724 | P11: =A11 -> May 2024 | Q11: =B11 -> 51220 | R11: =L11 -> 76926.724 | S11: ='PV-ESS Energy Flow'!E8+'PV-ESS Energy Flow'!I8 -> 52500.162 | T11: =MAX(R11-S11,0) -> 24426.562 | U11: =G11 -> 466 | V11: ='PV-ESS Energy Flow'!P8 -> 4848.1967 | W11: ='PV-ESS Energy Flow'!O8 -> 3091.3018 | X11: ='PV-ESS Energy Flow'!Q8 -> 1221.3281 | Y11: ='PV-ESS Energy Flow'!W8 -> 0 | Z11: =MAX(K11-SUM(V11:Y11),0) -> 9323.3935 | AA11: =K11-Z11 -> 9160.8265 | AB11: ='PV-ESS Energy Flow'!R8 -> 0 | AC11: ='PV-ESS Energy Flow'!J8 -> 0
A12: ='Combined TOU Profile'!A13 -> Jun 2024 | B12: ='Combined TOU Profile'!F13 -> 50744 | C12: ='Combined TOU Profile'!G13 -> 1008 | D12: ='Combined TOU Profile'!H13 -> 993 | E12: ='Combined TOU Profile'!I13 -> 32110 | F12: ='Combined TOU Profile'!J13 -> 16633 | G12: ='Combined TOU Profile'!M13 -> 471 | H12: ='Combined TOU Profile'!P13 -> 5727.94 | I12: ='Combined TOU Profile'!Q13 -> 13151.58 | J12: ='Combined TOU Profile'!S13 -> 1894.9 | K12: ='Combined TOU Profile'!R13 -> 20774.42 | L12: =INDEX('PV Production'!$G$5:$G$16,MATCH(A12,'PV Production'!$A$5:$A$16,0)) -> 76305.766 | P12: =A12 -> Jun 2024 | Q12: =B12 -> 50744 | R12: =L12 -> 76305.766 | S12: ='PV-ESS Energy Flow'!E9+'PV-ESS Energy Flow'!I9 -> 52745 | T12: =MAX(R12-S12,0) -> 23560.766 | U12: =G12 -> 471 | V12: ='PV-ESS Energy Flow'!P9 -> 4870.8065 | W12: ='PV-ESS Energy Flow'!O9 -> 3039.4649 | X12: ='PV-ESS Energy Flow'!Q9 -> 1178.0383 | Y12: ='PV-ESS Energy Flow'!W9 -> 0 | Z12: =MAX(K12-SUM(V12:Y12),0) -> 11686.11 | AA12: =K12-Z12 -> 9088.3097 | AB12: ='PV-ESS Energy Flow'!R9 -> 0 | AC12: ='PV-ESS Energy Flow'!J9 -> 0
A13: ='Combined TOU Profile'!A14 -> Jul 2024 | B13: ='Combined TOU Profile'!F14 -> 81109 | C13: ='Combined TOU Profile'!G14 -> 2075 | D13: ='Combined TOU Profile'!H14 -> 723 | E13: ='Combined TOU Profile'!I14 -> 78311 | F13: ='Combined TOU Profile'!J14 -> 0 | G13: ='Combined TOU Profile'!M14 -> 725 | H13: ='Combined TOU Profile'!P14 -> 11449.52 | I13: ='Combined TOU Profile'!Q14 -> 20856.59 | J13: ='Combined TOU Profile'!S14 -> 1207.97 | K13: ='Combined TOU Profile'!R14 -> 33514.08 | L13: =INDEX('PV Production'!$G$5:$G$16,MATCH(A13,'PV Production'!$A$5:$A$16,0)) -> 70470.772 | P13: =A13 -> Jul 2024 | Q13: =B13 -> 81109 | R13: =L13 -> 70470.772 | S13: ='PV-ESS Energy Flow'!E10+'PV-ESS Energy Flow'!I10 -> 70470.772 | T13: =MAX(R13-S13,0) -> 0 | U13: =G13 -> 725 | V13: ='PV-ESS Energy Flow'!P10 -> 6507.7163 | W13: ='PV-ESS Energy Flow'!O10 -> 3690.6724 | X13: ='PV-ESS Energy Flow'!Q10 -> 0 | Y13: ='PV-ESS Energy Flow'!W10 -> 1403.1639 | Z13: =MAX(K13-SUM(V13:Y13),0) -> 21912.527 | AA13: =K13-Z13 -> 11601.553 | AB13: ='PV-ESS Energy Flow'!R10 -> 3108.8889 | AC13: ='PV-ESS Energy Flow'!J10 -> 2798
A14: ='Combined TOU Profile'!A15 -> Aug 2024 | B14: ='Combined TOU Profile'!F15 -> 80723 | C14: ='Combined TOU Profile'!G15 -> 4892 | D14: ='Combined TOU Profile'!H15 -> 631 | E14: ='Combined TOU Profile'!I15 -> 75200 | F14: ='Combined TOU Profile'!J15 -> 0 | G14: ='Combined TOU Profile'!M15 -> 705 | H14: ='Combined TOU Profile'!P15 -> 11656.92 | I14: ='Combined TOU Profile'!Q15 -> 21310.7 | J14: ='Combined TOU Profile'!S15 -> 1162.57 | K14: ='Combined TOU Profile'!R15 -> 34130.19 | L14: =INDEX('PV Production'!$G$5:$G$16,MATCH(A14,'PV Production'!$A$5:$A$16,0)) -> 69633.61 | P14: =A14 -> Aug 2024 | Q14: =B14 -> 80723 | R14: =L14 -> 69633.61 | S14: ='PV-ESS Energy Flow'!E11+'PV-ESS Energy Flow'!I11 -> 69633.61 | T14: =MAX(R14-S14,0) -> 0 | U14: =G14 -> 705 | V14: ='PV-ESS Energy Flow'!P11 -> 6430.4075 | W14: ='PV-ESS Energy Flow'!O11 -> 4235.2234 | X14: ='PV-ESS Energy Flow'!Q11 -> 0 | Y14: ='PV-ESS Energy Flow'!W11 -> 1352.6178 | Z14: =MAX(K14-SUM(V14:Y14),0) -> 22111.941 | AA14: =K14-Z14 -> 12018.249 | AB14: ='PV-ESS Energy Flow'!R11 -> 6136.6667 | AC14: ='PV-ESS Energy Flow'!J11 -> 5523
A15: ='Combined TOU Profile'!A16 -> Sep 2024 | B15: ='Combined TOU Profile'!F16 -> 84369 | C15: ='Combined TOU Profile'!G16 -> 3782 | D15: ='Combined TOU Profile'!H16 -> 629 | E15: ='Combined TOU Profile'!I16 -> 79958 | F15: ='Combined TOU Profile'!J16 -> 0 | G15: ='Combined TOU Profile'!M16 -> 730 | H15: ='Combined TOU Profile'!P16 -> 11557.23 | I15: ='Combined TOU Profile'!Q16 -> 22683.43 | J15: ='Combined TOU Profile'!S16 -> 1236.34 | K15: ='Combined TOU Profile'!R16 -> 35477 | L15: =INDEX('PV Production'!$G$5:$G$16,MATCH(A15,'PV Production'!$A$5:$A$16,0)) -> 60646.06 | P15: =A15 -> Sep 2024 | Q15: =B15 -> 84369 | R15: =L15 -> 60646.06 | S15: ='PV-ESS Energy Flow'!E12+'PV-ESS Energy Flow'!I12 -> 60646.06 | T15: =MAX(R15-S15,0) -> 0 | U15: =G15 -> 730 | V15: ='PV-ESS Energy Flow'!P12 -> 5600.4403 | W15: ='PV-ESS Energy Flow'!O12 -> 4789.6301 | X15: ='PV-ESS Energy Flow'!Q12 -> 0 | Y15: ='PV-ESS Energy Flow'!W12 -> 1041.5336 | Z15: =MAX(K15-SUM(V15:Y15),0) -> 24045.396 | AA15: =K15-Z15 -> 11431.604 | AB15: ='PV-ESS Energy Flow'!R12 -> 4901.1111 | AC15: ='PV-ESS Energy Flow'!J12 -> 4411
A16: Annual | B16: =SUM(B4:B15) -> 709501 | C16: =SUM(C4:C15) -> 12604.833 | D16: =SUM(D4:D15) -> 15480.329 | E16: =SUM(E4:E15) -> 344747.36 | F16: =SUM(F4:F15) -> 336668.48 | G16: =MAX(G4:G15) -> 730 | H16: =SUM(H4:H15) -> 65519.805 | I16: =SUM(I4:I15) -> 193627.17 | J16: =SUM(J4:J15) -> 27585.135 | K16: =SUM(K4:K15) -> 286732.11 | L16: =SUM(L4:L15) -> 710207.51 | P16: Annual | Q16: =SUM(Q4:Q15) -> 709501 | R16: =SUM(R4:R15) -> 710207.51 | S16: =SUM(S4:S15) -> 623663.61 | T16: =SUM(T4:T15) -> 86543.906 | U16: =MAX(U4:U15) -> 730 | V16: =SUM(V4:V15) -> 57593.038 | W16: =SUM(W4:W15) -> 39372.753 | X16: =SUM(X4:X15) -> 4327.1953 | Y16: =SUM(Y4:Y15) -> 5012.6387 | Z16: =SUM(Z4:Z15) -> 180426.49 | AA16: =SUM(AA4:AA15) -> 106305.62 | AB16: =SUM(AB4:AB15) -> 22610 | AC16: =SUM(AC4:AC15) -> 20349

Sheet 5Cash Purchase
A1: 5 CASH PURCHASE — 30-Year Proposal View
A3: Cash Purchase Summary | B3: Value
A4: Gross Project Cost | B4: ='3Rebates Incentives'!D4 -> 1074972.3
A5: Federal ITC (30% proposal case) | B5: ='3Rebates Incentives'!H16 -> 322491.69
A6: Federal Depreciation Tax Benefit | B6: ='3Rebates Incentives'!H17 -> 274117.94
A7: California Depreciation Tax Benefit | B7: ='3Rebates Incentives'!H18 -> 85997.784
A8: Total Modeled Tax Benefits | B8: ='3Rebates Incentives'!H19 -> 682607.41
A9: Net Economic Cost After Tax Benefits | B9: =B4-B8 -> 392364.89
A10: Year-1 Operating Savings | B10: ='4Electric Bills'!AA16 -> 106305.62
A11: 30-Year Operating Savings | B11: ='6Detailed Cash Flow'!B40 -> 4694064
A12: IRR | B12: ='6Detailed Cash Flow'!B42 -> 0.21518283
A13: NPV @ 5% | B13: ='6Detailed Cash Flow'!B41 -> 1757719.3
A14: Simple Payback (years) | B14: ='6Detailed Cash Flow'!B43 -> 3.8876454
A17: Year | B17: 0 | C17: 1 | D17: 2 | E17: 3 | F17: 4 | G17: 5 | H17: 6 | I17: 7 | J17: 8 | K17: 9 | L17: 10 | M17: 11 | N17: 12 | O17: 13 | P17: 14 | Q17: 15 | R17: 16 | S17: 17 | T17: 18 | U17: 19 | V17: 20 | W17: 21 | X17: 22 | Y17: 23 | Z17: 24 | AA17: 25 | AB17: 26 | AC17: 27 | AD17: 28 | AE17: 29 | AF17: 30
A18: Net Cash Flow ($) | B18: ='6Detailed Cash Flow'!I4 -> -1074972.3 | C18: ='6Detailed Cash Flow'!I5 -> 632397.07 | D18: ='6Detailed Cash Flow'!I6 -> 171590.96 | E18: ='6Detailed Cash Flow'!I7 -> 149296.62 | F18: ='6Detailed Cash Flow'!I8 -> 137090.4 | G18: ='6Detailed Cash Flow'!I9 -> 139982.7 | H18: ='6Detailed Cash Flow'!I10 -> 131680.78 | I18: ='6Detailed Cash Flow'!I11 -> 123455.77 | J18: ='6Detailed Cash Flow'!I12 -> 126578.88 | K18: ='6Detailed Cash Flow'!I13 -> 129783.04 | L18: ='6Detailed Cash Flow'!I14 -> 133070.43 | M18: ='6Detailed Cash Flow'!I15 -> 136443.24 | N18: ='6Detailed Cash Flow'!I16 -> 139903.76 | O18: ='6Detailed Cash Flow'!I17 -> 143454.33 | P18: ='6Detailed Cash Flow'!I18 -> 147097.35 | Q18: ='6Detailed Cash Flow'!I19 -> 150835.28 | R18: ='6Detailed Cash Flow'!I20 -> 154670.67 | S18: ='6Detailed Cash Flow'!I21 -> 158606.11 | T18: ='6Detailed Cash Flow'!I22 -> 162644.27 | U18: ='6Detailed Cash Flow'!I23 -> 166787.92 | V18: ='6Detailed Cash Flow'!I24 -> 171039.86 | W18: ='6Detailed Cash Flow'!I25 -> 175403.01 | X18: ='6Detailed Cash Flow'!I26 -> 179880.34 | Y18: ='6Detailed Cash Flow'!I27 -> 184474.91 | Z18: ='6Detailed Cash Flow'!I28 -> 189189.87 | AA18: ='6Detailed Cash Flow'!I29 -> 194028.46 | AB18: ='6Detailed Cash Flow'!I30 -> 198993.98 | AC18: ='6Detailed Cash Flow'!I31 -> 204089.86 | AD18: ='6Detailed Cash Flow'!I32 -> 209319.6 | AE18: ='6Detailed Cash Flow'!I33 -> 214686.79 | AF18: ='6Detailed Cash Flow'!I34 -> 220195.16
A19: Cumulative Cash Flow ($) | B19: ='6Detailed Cash Flow'!J4 -> -1074972.3 | C19: ='6Detailed Cash Flow'!J5 -> -442575.23 | D19: ='6Detailed Cash Flow'!J6 -> -270984.27 | E19: ='6Detailed Cash Flow'!J7 -> -121687.66 | F19: ='6Detailed Cash Flow'!J8 -> 15402.738 | G19: ='6Detailed Cash Flow'!J9 -> 155385.44 | H19: ='6Detailed Cash Flow'!J10 -> 287066.22 | I19: ='6Detailed Cash Flow'!J11 -> 410521.99 | J19: ='6Detailed Cash Flow'!J12 -> 537100.87 | K19: ='6Detailed Cash Flow'!J13 -> 666883.91 | L19: ='6Detailed Cash Flow'!J14 -> 799954.34 | M19: ='6Detailed Cash Flow'!J15 -> 936397.58 | N19: ='6Detailed Cash Flow'!J16 -> 1076301.3 | O19: ='6Detailed Cash Flow'!J17 -> 1219755.7 | P19: ='6Detailed Cash Flow'!J18 -> 1366853 | Q19: ='6Detailed Cash Flow'!J19 -> 1517688.3 | R19: ='6Detailed Cash Flow'!J20 -> 1672359 | S19: ='6Detailed Cash Flow'!J21 -> 1830965.1 | T19: ='6Detailed Cash Flow'!J22 -> 1993609.4 | U19: ='6Detailed Cash Flow'!J23 -> 2160397.3 | V19: ='6Detailed Cash Flow'!J24 -> 2331437.1 | W19: ='6Detailed Cash Flow'!J25 -> 2506840.2 | X19: ='6Detailed Cash Flow'!J26 -> 2686720.5 | Y19: ='6Detailed Cash Flow'!J27 -> 2871195.4 | Z19: ='6Detailed Cash Flow'!J28 -> 3060385.3 | AA19: ='6Detailed Cash Flow'!J29 -> 3254413.7 | AB19: ='6Detailed Cash Flow'!J30 -> 3453407.7 | AC19: ='6Detailed Cash Flow'!J31 -> 3657497.6 | AD19: ='6Detailed Cash Flow'!J32 -> 3866817.2 | AE19: ='6Detailed Cash Flow'!J33 -> 4081504 | AF19: ='6Detailed Cash Flow'!J34 -> 4301699.1
A20: PV of Net Cash Flow ($) | B20: ='6Detailed Cash Flow'!L4 -> -1074972.3 | C20: ='6Detailed Cash Flow'!L5 -> 602282.92 | D20: ='6Detailed Cash Flow'!L6 -> 155638.06 | E20: ='6Detailed Cash Flow'!L7 -> 128968.03 | F20: ='6Detailed Cash Flow'!L8 -> 112784.61 | G20: ='6Detailed Cash Flow'!L9 -> 109680.11 | H20: ='6Detailed Cash Flow'!L10 -> 98262.224 | I20: ='6Detailed Cash Flow'!L11 -> 87737.714 | J20: ='6Detailed Cash Flow'!L12 -> 85673.568 | K20: ='6Detailed Cash Flow'!L13 -> 83659.307 | L20: ='6Detailed Cash Flow'!L14 -> 81693.698 | M20: ='6Detailed Cash Flow'!L15 -> 79775.537 | N20: ='6Detailed Cash Flow'!L16 -> 77903.65 | O20: ='6Detailed Cash Flow'!L17 -> 76076.896 | P20: ='6Detailed Cash Flow'!L18 -> 74294.158 | Q20: ='6Detailed Cash Flow'!L19 -> 72554.351 | R20: ='6Detailed Cash Flow'!L20 -> 70856.415 | S20: ='6Detailed Cash Flow'!L21 -> 69199.319 | T20: ='6Detailed Cash Flow'!L22 -> 67582.055 | U20: ='6Detailed Cash Flow'!L23 -> 66003.643 | V20: ='6Detailed Cash Flow'!L24 -> 64463.126 | W20: ='6Detailed Cash Flow'!L25 -> 62959.571 | X20: ='6Detailed Cash Flow'!L26 -> 61492.071 | Y20: ='6Detailed Cash Flow'!L27 -> 60059.738 | Z20: ='6Detailed Cash Flow'!L28 -> 58661.709 | AA20: ='6Detailed Cash Flow'!L29 -> 57297.141 | AB20: ='6Detailed Cash Flow'!L30 -> 55965.213 | AC20: ='6Detailed Cash Flow'!L31 -> 54665.125 | AD20: ='6Detailed Cash Flow'!L32 -> 53396.097 | AE20: ='6Detailed Cash Flow'!L33 -> 52157.367 | AF20: ='6Detailed Cash Flow'!L34 -> 50948.193
A21: Cumulative PV ($) | B21: ='6Detailed Cash Flow'!M4 -> -1074972.3 | C21: ='6Detailed Cash Flow'!M5 -> -472689.38 | D21: ='6Detailed Cash Flow'!M6 -> -317051.32 | E21: ='6Detailed Cash Flow'!M7 -> -188083.29 | F21: ='6Detailed Cash Flow'!M8 -> -75298.683 | G21: ='6Detailed Cash Flow'!M9 -> 34381.425 | H21: ='6Detailed Cash Flow'!M10 -> 132643.65 | I21: ='6Detailed Cash Flow'!M11 -> 220381.36 | J21: ='6Detailed Cash Flow'!M12 -> 306054.93 | K21: ='6Detailed Cash Flow'!M13 -> 389714.24 | L21: ='6Detailed Cash Flow'!M14 -> 471407.94 | M21: ='6Detailed Cash Flow'!M15 -> 551183.47 | N21: ='6Detailed Cash Flow'!M16 -> 629087.12 | O21: ='6Detailed Cash Flow'!M17 -> 705164.02 | P21: ='6Detailed Cash Flow'!M18 -> 779458.18 | Q21: ='6Detailed Cash Flow'!M19 -> 852012.53 | R21: ='6Detailed Cash Flow'!M20 -> 922868.94 | S21: ='6Detailed Cash Flow'!M21 -> 992068.26 | T21: ='6Detailed Cash Flow'!M22 -> 1059650.3 | U21: ='6Detailed Cash Flow'!M23 -> 1125654 | V21: ='6Detailed Cash Flow'!M24 -> 1190117.1 | W21: ='6Detailed Cash Flow'!M25 -> 1253076.7 | X21: ='6Detailed Cash Flow'!M26 -> 1314568.7 | Y21: ='6Detailed Cash Flow'!M27 -> 1374628.5 | Z21: ='6Detailed Cash Flow'!M28 -> 1433290.2 | AA21: ='6Detailed Cash Flow'!M29 -> 1490587.3 | AB21: ='6Detailed Cash Flow'!M30 -> 1546552.5 | AC21: ='6Detailed Cash Flow'!M31 -> 1601217.7 | AD21: ='6Detailed Cash Flow'!M32 -> 1654613.7 | AE21: ='6Detailed Cash Flow'!M33 -> 1706771.1 | AF21: ='6Detailed Cash Flow'!M34 -> 1757719.3
A22: No-Project Utility Cost ($) | B22: ='6Detailed Cash Flow'!N4 -> 0 | C22: ='6Detailed Cash Flow'!N5 -> 295334.07 | D22: ='6Detailed Cash Flow'!N6 -> 304194.1 | E22: ='6Detailed Cash Flow'!N7 -> 313319.92 | F22: ='6Detailed Cash Flow'!N8 -> 322719.52 | G22: ='6Detailed Cash Flow'!N9 -> 332401.1 | H22: ='6Detailed Cash Flow'!N10 -> 342373.13 | I22: ='6Detailed Cash Flow'!N11 -> 352644.33 | J22: ='6Detailed Cash Flow'!N12 -> 363223.66 | K22: ='6Detailed Cash Flow'!N13 -> 374120.37 | L22: ='6Detailed Cash Flow'!N14 -> 385343.98 | M22: ='6Detailed Cash Flow'!N15 -> 396904.3 | N22: ='6Detailed Cash Flow'!N16 -> 408811.43 | O22: ='6Detailed Cash Flow'!N17 -> 421075.77 | P22: ='6Detailed Cash Flow'!N18 -> 433708.04 | Q22: ='6Detailed Cash Flow'!N19 -> 446719.28 | R22: ='6Detailed Cash Flow'!N20 -> 460120.86 | S22: ='6Detailed Cash Flow'!N21 -> 473924.49 | T22: ='6Detailed Cash Flow'!N22 -> 488142.22 | U22: ='6Detailed Cash Flow'!N23 -> 502786.49 | V22: ='6Detailed Cash Flow'!N24 -> 517870.09 | W22: ='6Detailed Cash Flow'!N25 -> 533406.19 | X22: ='6Detailed Cash Flow'!N26 -> 549408.37 | Y22: ='6Detailed Cash Flow'!N27 -> 565890.62 | Z22: ='6Detailed Cash Flow'!N28 -> 582867.34 | AA22: ='6Detailed Cash Flow'!N29 -> 600353.36 | AB22: ='6Detailed Cash Flow'!N30 -> 618363.96 | AC22: ='6Detailed Cash Flow'!N31 -> 636914.88 | AD22: ='6Detailed Cash Flow'!N32 -> 656022.33 | AE22: ='6Detailed Cash Flow'!N33 -> 675703 | AF22: ='6Detailed Cash Flow'!N34 -> 695974.09
A23: With-Project Utility Cost ($) | B23: ='6Detailed Cash Flow'!O4 -> 0 | C23: ='6Detailed Cash Flow'!O5 -> 189028.45 | D23: ='6Detailed Cash Flow'!O6 -> 195209.52 | E23: ='6Detailed Cash Flow'!O7 -> 201587.14 | F23: ='6Detailed Cash Flow'!O8 -> 208167.42 | G23: ='6Detailed Cash Flow'!O9 -> 214956.7 | H23: ='6Detailed Cash Flow'!O10 -> 221961.51 | I23: ='6Detailed Cash Flow'!O11 -> 229188.55 | J23: ='6Detailed Cash Flow'!O12 -> 236644.78 | K23: ='6Detailed Cash Flow'!O13 -> 244337.32 | L23: ='6Detailed Cash Flow'!O14 -> 252273.55 | M23: ='6Detailed Cash Flow'!O15 -> 260461.06 | N23: ='6Detailed Cash Flow'!O16 -> 268907.66 | O23: ='6Detailed Cash Flow'!O17 -> 277621.44 | P23: ='6Detailed Cash Flow'!O18 -> 286610.69 | Q23: ='6Detailed Cash Flow'!O19 -> 295884 | R23: ='6Detailed Cash Flow'!O20 -> 305450.2 | S23: ='6Detailed Cash Flow'!O21 -> 315318.38 | T23: ='6Detailed Cash Flow'!O22 -> 325497.95 | U23: ='6Detailed Cash Flow'!O23 -> 335998.57 | V23: ='6Detailed Cash Flow'!O24 -> 346830.22 | W23: ='6Detailed Cash Flow'!O25 -> 358003.18 | X23: ='6Detailed Cash Flow'!O26 -> 369528.03 | Y23: ='6Detailed Cash Flow'!O27 -> 381415.71 | Z23: ='6Detailed Cash Flow'!O28 -> 393677.47 | AA23: ='6Detailed Cash Flow'!O29 -> 406324.91 | AB23: ='6Detailed Cash Flow'!O30 -> 419369.98 | AC23: ='6Detailed Cash Flow'!O31 -> 432825.03 | AD23: ='6Detailed Cash Flow'!O32 -> 446702.73 | AE23: ='6Detailed Cash Flow'!O33 -> 461016.21 | AF23: ='6Detailed Cash Flow'!O34 -> 475778.93
A24: Cumulative Tax Benefits ($) | B24: 0 | C24: =B24+'6Detailed Cash Flow'!C5 -> 526091.44 | D24: =C24+'6Detailed Cash Flow'!C6 -> 588697.83 | E24: =D24+'6Detailed Cash Flow'!C7 -> 626261.66 | F24: =E24+'6Detailed Cash Flow'!C8 -> 648799.96 | G24: =F24+'6Detailed Cash Flow'!C9 -> 671338.26 | H24: =G24+'6Detailed Cash Flow'!C10 -> 682607.41 | I24: =H24+'6Detailed Cash Flow'!C11 -> 682607.41 | J24: =I24+'6Detailed Cash Flow'!C12 -> 682607.41 | K24: =J24+'6Detailed Cash Flow'!C13 -> 682607.41 | L24: =K24+'6Detailed Cash Flow'!C14 -> 682607.41 | M24: =L24+'6Detailed Cash Flow'!C15 -> 682607.41 | N24: =M24+'6Detailed Cash Flow'!C16 -> 682607.41 | O24: =N24+'6Detailed Cash Flow'!C17 -> 682607.41 | P24: =O24+'6Detailed Cash Flow'!C18 -> 682607.41 | Q24: =P24+'6Detailed Cash Flow'!C19 -> 682607.41 | R24: =Q24+'6Detailed Cash Flow'!C20 -> 682607.41 | S24: =R24+'6Detailed Cash Flow'!C21 -> 682607.41 | T24: =S24+'6Detailed Cash Flow'!C22 -> 682607.41 | U24: =T24+'6Detailed Cash Flow'!C23 -> 682607.41 | V24: =U24+'6Detailed Cash Flow'!C24 -> 682607.41 | W24: =V24+'6Detailed Cash Flow'!C25 -> 682607.41 | X24: =W24+'6Detailed Cash Flow'!C26 -> 682607.41 | Y24: =X24+'6Detailed Cash Flow'!C27 -> 682607.41 | Z24: =Y24+'6Detailed Cash Flow'!C28 -> 682607.41 | AA24: =Z24+'6Detailed Cash Flow'!C29 -> 682607.41 | AB24: =AA24+'6Detailed Cash Flow'!C30 -> 682607.41 | AC24: =AB24+'6Detailed Cash Flow'!C31 -> 682607.41 | AD24: =AC24+'6Detailed Cash Flow'!C32 -> 682607.41 | AE24: =AD24+'6Detailed Cash Flow'!C33 -> 682607.41 | AF24: =AE24+'6Detailed Cash Flow'!C34 -> 682607.41
A25: Cash Purchase Cumulative Energy Cost ($) | B25: =$B$4 -> 1074972.3 | C25: =$B$4+SUM('6Detailed Cash Flow'!$O$5:O5)-C24 -> 737909.3 | D25: =$B$4+SUM('6Detailed Cash Flow'!$O$5:O6)-D24 -> 870512.44 | E25: =$B$4+SUM('6Detailed Cash Flow'!$O$5:O7)-E24 -> 1034535.7 | F25: =$B$4+SUM('6Detailed Cash Flow'!$O$5:O8)-F24 -> 1220164.9 | G25: =$B$4+SUM('6Detailed Cash Flow'!$O$5:O9)-G24 -> 1412583.3 | H25: =$B$4+SUM('6Detailed Cash Flow'!$O$5:O10)-H24 -> 1623275.6 | I25: =$B$4+SUM('6Detailed Cash Flow'!$O$5:O11)-I24 -> 1852464.2 | J25: =$B$4+SUM('6Detailed Cash Flow'!$O$5:O12)-J24 -> 2089109 | K25: =$B$4+SUM('6Detailed Cash Flow'!$O$5:O13)-K24 -> 2333446.3 | L25: =$B$4+SUM('6Detailed Cash Flow'!$O$5:O14)-L24 -> 2585719.8 | M25: =$B$4+SUM('6Detailed Cash Flow'!$O$5:O15)-M24 -> 2846180.9 | N25: =$B$4+SUM('6Detailed Cash Flow'!$O$5:O16)-N24 -> 3115088.6 | O25: =$B$4+SUM('6Detailed Cash Flow'!$O$5:O17)-O24 -> 3392710 | P25: =$B$4+SUM('6Detailed Cash Flow'!$O$5:O18)-P24 -> 3679320.7 | Q25: =$B$4+SUM('6Detailed Cash Flow'!$O$5:O19)-Q24 -> 3975204.7 | R25: =$B$4+SUM('6Detailed Cash Flow'!$O$5:O20)-R24 -> 4280654.9 | S25: =$B$4+SUM('6Detailed Cash Flow'!$O$5:O21)-S24 -> 4595973.3 | T25: =$B$4+SUM('6Detailed Cash Flow'!$O$5:O22)-T24 -> 4921471.2 | U25: =$B$4+SUM('6Detailed Cash Flow'!$O$5:O23)-U24 -> 5257469.8 | V25: =$B$4+SUM('6Detailed Cash Flow'!$O$5:O24)-V24 -> 5604300 | W25: =$B$4+SUM('6Detailed Cash Flow'!$O$5:O25)-W24 -> 5962303.2 | X25: =$B$4+SUM('6Detailed Cash Flow'!$O$5:O26)-X24 -> 6331831.2 | Y25: =$B$4+SUM('6Detailed Cash Flow'!$O$5:O27)-Y24 -> 6713246.9 | Z25: =$B$4+SUM('6Detailed Cash Flow'!$O$5:O28)-Z24 -> 7106924.4 | AA25: =$B$4+SUM('6Detailed Cash Flow'!$O$5:O29)-AA24 -> 7513249.3 | AB25: =$B$4+SUM('6Detailed Cash Flow'!$O$5:O30)-AB24 -> 7932619.3 | AC25: =$B$4+SUM('6Detailed Cash Flow'!$O$5:O31)-AC24 -> 8365444.3 | AD25: =$B$4+SUM('6Detailed Cash Flow'!$O$5:O32)-AD24 -> 8812147.1 | AE25: =$B$4+SUM('6Detailed Cash Flow'!$O$5:O33)-AE24 -> 9273163.3 | AF25: =$B$4+SUM('6Detailed Cash Flow'!$O$5:O34)-AF24 -> 9748942.2
A26: Avoided Utility Cost — Cumulative ($) | B26: 0 | C26: =B26+'6Detailed Cash Flow'!N5 -> 295334.07 | D26: =C26+'6Detailed Cash Flow'!N6 -> 599528.17 | E26: =D26+'6Detailed Cash Flow'!N7 -> 912848.09 | F26: =E26+'6Detailed Cash Flow'!N8 -> 1235567.6 | G26: =F26+'6Detailed Cash Flow'!N9 -> 1567968.7 | H26: =G26+'6Detailed Cash Flow'!N10 -> 1910341.8 | I26: =H26+'6Detailed Cash Flow'!N11 -> 2262986.2 | J26: =I26+'6Detailed Cash Flow'!N12 -> 2626209.8 | K26: =J26+'6Detailed Cash Flow'!N13 -> 3000330.2 | L26: =K26+'6Detailed Cash Flow'!N14 -> 3385674.2 | M26: =L26+'6Detailed Cash Flow'!N15 -> 3782578.5 | N26: =M26+'6Detailed Cash Flow'!N16 -> 4191389.9 | O26: =N26+'6Detailed Cash Flow'!N17 -> 4612465.7 | P26: =O26+'6Detailed Cash Flow'!N18 -> 5046173.7 | Q26: =P26+'6Detailed Cash Flow'!N19 -> 5492893 | R26: =Q26+'6Detailed Cash Flow'!N20 -> 5953013.9 | S26: =R26+'6Detailed Cash Flow'!N21 -> 6426938.3 | T26: =S26+'6Detailed Cash Flow'!N22 -> 6915080.6 | U26: =T26+'6Detailed Cash Flow'!N23 -> 7417867.1 | V26: =U26+'6Detailed Cash Flow'!N24 -> 7935737.1 | W26: =V26+'6Detailed Cash Flow'!N25 -> 8469143.3 | X26: =W26+'6Detailed Cash Flow'!N26 -> 9018551.7 | Y26: =X26+'6Detailed Cash Flow'!N27 -> 9584442.3 | Z26: =Y26+'6Detailed Cash Flow'!N28 -> 10167310 | AA26: =Z26+'6Detailed Cash Flow'!N29 -> 10767663 | AB26: =AA26+'6Detailed Cash Flow'!N30 -> 11386027 | AC26: =AB26+'6Detailed Cash Flow'!N31 -> 12022942 | AD26: =AC26+'6Detailed Cash Flow'!N32 -> 12678964 | AE26: =AD26+'6Detailed Cash Flow'!N33 -> 13354667 | AF26: =AE26+'6Detailed Cash Flow'!N34 -> 14050641
A28: Tax timing follows the original Barstow proposal: ITC in Year 1; federal MACRS and California depreciation tax shields in Years 1–6. The cumulative-cost chart compares the no-project cumulative utility spend against gross project purchase + cumulative with-project utility bills − cumulative modeled tax benefits. Operating savings remain based on the audited NEW ELECTRIC BILL / ESS savings model.

Sheet 6Detailed Cash Flow
A1: 6.1 DETAILED CASH FLOW ANALYSIS — 30-Year Cash Purchase
A3: Year | B3: Gross Project Purchase ($) | C3: ITC + MACRS Tax Benefits ($) | D3: PV Energy Savings ($) | E3: Export Credit ($) | F3: Grid Arbitrage Savings ($) | G3: Demand-Charge Savings ($) | H3: Total Operating Savings ($) | I3: Net Cash Flow ($) | J3: Cumulative Cash Flow ($) | K3: Discount Factor | L3: PV of Net Cash Flow ($) | M3: Cumulative PV ($) | N3: No-Project Utility Bill ($) | O3: With-Project Utility Bill ($) | P3: Cumulative No-Project Cost ($) | Q3: Cumulative Cash-Purchase Cost ($)
A4: 0 | B4: =-'3Rebates Incentives'!D4 -> -1074972.3 | C4: 0 | D4: 0 | E4: 0 | F4: 0 | G4: 0 | H4: 0 | I4: =B4+C4+H4 -> -1074972.3 | J4: =I4 -> -1074972.3 | K4: =1 -> 1 | L4: =I4 -> -1074972.3 | M4: =L4 -> -1074972.3 | N4: 0 | O4: 0 | P4: 0 | Q4: =-I4 -> 1074972.3
A5: 1 | B5: 0 | C5: ='3Rebates Incentives'!B19 -> 526091.44 | D5: ='4Electric Bills'!V16*(1+'Model Assumptions'!$C$21)^(A5-1)*(1-'Model Assumptions'!$C$22)^(A5-1) -> 57593.038 | E5: ='4Electric Bills'!X16*(1+'Model Assumptions'!$C$21)^(A5-1)*(1-'Model Assumptions'!$C$22)^(A5-1) -> 4327.1953 | F5: ='4Electric Bills'!Y16*(1+'Model Assumptions'!$C$21)^(A5-1) -> 5012.6387 | G5: ='4Electric Bills'!W16*(1+'Model Assumptions'!$C$21)^(A5-1) -> 39372.753 | H5: =SUM(D5:G5) -> 106305.62 | I5: =B5+C5+H5 -> 632397.07 | J5: =J4+I5 -> -442575.23 | K5: =1/(1+'Model Assumptions'!$C$20)^A5 -> 0.95238095 | L5: =I5*K5 -> 602282.92 | M5: =M4+L5 -> -472689.38 | N5: ='4Electric Bills'!K16*(1+'Model Assumptions'!$C$21)^A5 -> 295334.07 | O5: =MAX(N5-H5,0) -> 189028.45 | P5: =P4+N5 -> 295334.07 | Q5: =Q4+O5 -> 1264000.7
A6: 2 | B6: 0 | C6: ='3Rebates Incentives'!C19 -> 62606.387 | D6: ='4Electric Bills'!V16*(1+'Model Assumptions'!$C$21)^(A6-1)*(1-'Model Assumptions'!$C$22)^(A6-1) -> 58846.262 | E6: ='4Electric Bills'!X16*(1+'Model Assumptions'!$C$21)^(A6-1)*(1-'Model Assumptions'!$C$22)^(A6-1) -> 4421.3551 | F6: ='4Electric Bills'!Y16*(1+'Model Assumptions'!$C$21)^(A6-1) -> 5163.0178 | G6: ='4Electric Bills'!W16*(1+'Model Assumptions'!$C$21)^(A6-1) -> 40553.936 | H6: =SUM(D6:G6) -> 108984.57 | I6: =B6+C6+H6 -> 171590.96 | J6: =J5+I6 -> -270984.27 | K6: =1/(1+'Model Assumptions'!$C$20)^A6 -> 0.90702948 | L6: =I6*K6 -> 155638.06 | M6: =M5+L6 -> -317051.32 | N6: ='4Electric Bills'!K16*(1+'Model Assumptions'!$C$21)^A6 -> 304194.1 | O6: =MAX(N6-H6,0) -> 195209.52 | P6: =P5+N6 -> 599528.17 | Q6: =Q5+O6 -> 1459210.3
A7: 3 | B7: 0 | C7: ='3Rebates Incentives'!D19 -> 37563.832 | D7: ='4Electric Bills'!V16*(1+'Model Assumptions'!$C$21)^(A7-1)*(1-'Model Assumptions'!$C$22)^(A7-1) -> 60126.757 | E7: ='4Electric Bills'!X16*(1+'Model Assumptions'!$C$21)^(A7-1)*(1-'Model Assumptions'!$C$22)^(A7-1) -> 4517.5637 | F7: ='4Electric Bills'!Y16*(1+'Model Assumptions'!$C$21)^(A7-1) -> 5317.9084 | G7: ='4Electric Bills'!W16*(1+'Model Assumptions'!$C$21)^(A7-1) -> 41770.554 | H7: =SUM(D7:G7) -> 111732.78 | I7: =B7+C7+H7 -> 149296.62 | J7: =J6+I7 -> -121687.66 | K7: =1/(1+'Model Assumptions'!$C$20)^A7 -> 0.8638376 | L7: =I7*K7 -> 128968.03 | M7: =M6+L7 -> -188083.29 | N7: ='4Electric Bills'!K16*(1+'Model Assumptions'!$C$21)^A7 -> 313319.92 | O7: =MAX(N7-H7,0) -> 201587.14 | P7: =P6+N7 -> 912848.09 | Q7: =Q6+O7 -> 1660797.4
A8: 4 | B8: 0 | C8: ='3Rebates Incentives'!E19 -> 22538.299 | D8: ='4Electric Bills'!V16*(1+'Model Assumptions'!$C$21)^(A8-1)*(1-'Model Assumptions'!$C$22)^(A8-1) -> 61435.115 | E8: ='4Electric Bills'!X16*(1+'Model Assumptions'!$C$21)^(A8-1)*(1-'Model Assumptions'!$C$22)^(A8-1) -> 4615.8659 | F8: ='4Electric Bills'!Y16*(1+'Model Assumptions'!$C$21)^(A8-1) -> 5477.4456 | G8: ='4Electric Bills'!W16*(1+'Model Assumptions'!$C$21)^(A8-1) -> 43023.671 | H8: =SUM(D8:G8) -> 114552.1 | I8: =B8+C8+H8 -> 137090.4 | J8: =J7+I8 -> 15402.738 | K8: =1/(1+'Model Assumptions'!$C$20)^A8 -> 0.82270247 | L8: =I8*K8 -> 112784.61 | M8: =M7+L8 -> -75298.683 | N8: ='4Electric Bills'!K16*(1+'Model Assumptions'!$C$21)^A8 -> 322719.52 | O8: =MAX(N8-H8,0) -> 208167.42 | P8: =P7+N8 -> 1235567.6 | Q8: =Q7+O8 -> 1868964.8
A9: 5 | B9: 0 | C9: ='3Rebates Incentives'!F19 -> 22538.299 | D9: ='4Electric Bills'!V16*(1+'Model Assumptions'!$C$21)^(A9-1)*(1-'Model Assumptions'!$C$22)^(A9-1) -> 62771.943 | E9: ='4Electric Bills'!X16*(1+'Model Assumptions'!$C$21)^(A9-1)*(1-'Model Assumptions'!$C$22)^(A9-1) -> 4716.3072 | F9: ='4Electric Bills'!Y16*(1+'Model Assumptions'!$C$21)^(A9-1) -> 5641.769 | G9: ='4Electric Bills'!W16*(1+'Model Assumptions'!$C$21)^(A9-1) -> 44314.381 | H9: =SUM(D9:G9) -> 117444.4 | I9: =B9+C9+H9 -> 139982.7 | J9: =J8+I9 -> 155385.44 | K9: =1/(1+'Model Assumptions'!$C$20)^A9 -> 0.78352617 | L9: =I9*K9 -> 109680.11 | M9: =M8+L9 -> 34381.425 | N9: ='4Electric Bills'!K16*(1+'Model Assumptions'!$C$21)^A9 -> 332401.1 | O9: =MAX(N9-H9,0) -> 214956.7 | P9: =P8+N9 -> 1567968.7 | Q9: =Q8+O9 -> 2083921.5
A10: 6 | B10: 0 | C10: ='3Rebates Incentives'!G19 -> 11269.15 | D10: ='4Electric Bills'!V16*(1+'Model Assumptions'!$C$21)^(A10-1)*(1-'Model Assumptions'!$C$22)^(A10-1) -> 64137.861 | E10: ='4Electric Bills'!X16*(1+'Model Assumptions'!$C$21)^(A10-1)*(1-'Model Assumptions'!$C$22)^(A10-1) -> 4818.934 | F10: ='4Electric Bills'!Y16*(1+'Model Assumptions'!$C$21)^(A10-1) -> 5811.022 | G10: ='4Electric Bills'!W16*(1+'Model Assumptions'!$C$21)^(A10-1) -> 45643.812 | H10: =SUM(D10:G10) -> 120411.63 | I10: =B10+C10+H10 -> 131680.78 | J10: =J9+I10 -> 287066.22 | K10: =1/(1+'Model Assumptions'!$C$20)^A10 -> 0.7462154 | L10: =I10*K10 -> 98262.224 | M10: =M9+L10 -> 132643.65 | N10: ='4Electric Bills'!K16*(1+'Model Assumptions'!$C$21)^A10 -> 342373.13 | O10: =MAX(N10-H10,0) -> 221961.51 | P10: =P9+N10 -> 1910341.8 | Q10: =Q9+O10 -> 2305883
A11: 7 | B11: 0 | C11: 0 | D11: ='4Electric Bills'!V16*(1+'Model Assumptions'!$C$21)^(A11-1)*(1-'Model Assumptions'!$C$22)^(A11-1) -> 65533.5 | E11: ='4Electric Bills'!X16*(1+'Model Assumptions'!$C$21)^(A11-1)*(1-'Model Assumptions'!$C$22)^(A11-1) -> 4923.794 | F11: ='4Electric Bills'!Y16*(1+'Model Assumptions'!$C$21)^(A11-1) -> 5985.3527 | G11: ='4Electric Bills'!W16*(1+'Model Assumptions'!$C$21)^(A11-1) -> 47013.127 | H11: =SUM(D11:G11) -> 123455.77 | I11: =B11+C11+H11 -> 123455.77 | J11: =J10+I11 -> 410521.99 | K11: =1/(1+'Model Assumptions'!$C$20)^A11 -> 0.71068133 | L11: =I11*K11 -> 87737.714 | M11: =M10+L11 -> 220381.36 | N11: ='4Electric Bills'!K16*(1+'Model Assumptions'!$C$21)^A11 -> 352644.33 | O11: =MAX(N11-H11,0) -> 229188.55 | P11: =P10+N11 -> 2262986.2 | Q11: =Q10+O11 -> 2535071.6
A12: 8 | B12: 0 | C12: 0 | D12: ='4Electric Bills'!V16*(1+'Model Assumptions'!$C$21)^(A12-1)*(1-'Model Assumptions'!$C$22)^(A12-1) -> 66959.509 | E12: ='4Electric Bills'!X16*(1+'Model Assumptions'!$C$21)^(A12-1)*(1-'Model Assumptions'!$C$22)^(A12-1) -> 5030.9358 | F12: ='4Electric Bills'!Y16*(1+'Model Assumptions'!$C$21)^(A12-1) -> 6164.9133 | G12: ='4Electric Bills'!W16*(1+'Model Assumptions'!$C$21)^(A12-1) -> 48423.52 | H12: =SUM(D12:G12) -> 126578.88 | I12: =B12+C12+H12 -> 126578.88 | J12: =J11+I12 -> 537100.87 | K12: =1/(1+'Model Assumptions'!$C$20)^A12 -> 0.67683936 | L12: =I12*K12 -> 85673.568 | M12: =M11+L12 -> 306054.93 | N12: ='4Electric Bills'!K16*(1+'Model Assumptions'!$C$21)^A12 -> 363223.66 | O12: =MAX(N12-H12,0) -> 236644.78 | P12: =P11+N12 -> 2626209.8 | Q12: =Q11+O12 -> 2771716.4
A13: 9 | B13: 0 | C13: 0 | D13: ='4Electric Bills'!V16*(1+'Model Assumptions'!$C$21)^(A13-1)*(1-'Model Assumptions'!$C$22)^(A13-1) -> 68416.548 | E13: ='4Electric Bills'!X16*(1+'Model Assumptions'!$C$21)^(A13-1)*(1-'Model Assumptions'!$C$22)^(A13-1) -> 5140.4089 | F13: ='4Electric Bills'!Y16*(1+'Model Assumptions'!$C$21)^(A13-1) -> 6349.8607 | G13: ='4Electric Bills'!W16*(1+'Model Assumptions'!$C$21)^(A13-1) -> 49876.226 | H13: =SUM(D13:G13) -> 129783.04 | I13: =B13+C13+H13 -> 129783.04 | J13: =J12+I13 -> 666883.91 | K13: =1/(1+'Model Assumptions'!$C$20)^A13 -> 0.64460892 | L13: =I13*K13 -> 83659.307 | M13: =M12+L13 -> 389714.24 | N13: ='4Electric Bills'!K16*(1+'Model Assumptions'!$C$21)^A13 -> 374120.37 | O13: =MAX(N13-H13,0) -> 244337.32 | P13: =P12+N13 -> 3000330.2 | Q13: =Q12+O13 -> 3016053.7
A14: 10 | B14: 0 | C14: 0 | D14: ='4Electric Bills'!V16*(1+'Model Assumptions'!$C$21)^(A14-1)*(1-'Model Assumptions'!$C$22)^(A14-1) -> 69905.292 | E14: ='4Electric Bills'!X16*(1+'Model Assumptions'!$C$21)^(A14-1)*(1-'Model Assumptions'!$C$22)^(A14-1) -> 5252.2642 | F14: ='4Electric Bills'!Y16*(1+'Model Assumptions'!$C$21)^(A14-1) -> 6540.3565 | G14: ='4Electric Bills'!W16*(1+'Model Assumptions'!$C$21)^(A14-1) -> 51372.513 | H14: =SUM(D14:G14) -> 133070.43 | I14: =B14+C14+H14 -> 133070.43 | J14: =J13+I14 -> 799954.34 | K14: =1/(1+'Model Assumptions'!$C$20)^A14 -> 0.61391325 | L14: =I14*K14 -> 81693.698 | M14: =M13+L14 -> 471407.94 | N14: ='4Electric Bills'!K16*(1+'Model Assumptions'!$C$21)^A14 -> 385343.98 | O14: =MAX(N14-H14,0) -> 252273.55 | P14: =P13+N14 -> 3385674.2 | Q14: =Q13+O14 -> 3268327.2
A15: 11 | B15: 0 | C15: 0 | D15: ='4Electric Bills'!V16*(1+'Model Assumptions'!$C$21)^(A15-1)*(1-'Model Assumptions'!$C$22)^(A15-1) -> 71426.432 | E15: ='4Electric Bills'!X16*(1+'Model Assumptions'!$C$21)^(A15-1)*(1-'Model Assumptions'!$C$22)^(A15-1) -> 5366.5535 | F15: ='4Electric Bills'!Y16*(1+'Model Assumptions'!$C$21)^(A15-1) -> 6736.5672 | G15: ='4Electric Bills'!W16*(1+'Model Assumptions'!$C$21)^(A15-1) -> 52913.688 | H15: =SUM(D15:G15) -> 136443.24 | I15: =B15+C15+H15 -> 136443.24 | J15: =J14+I15 -> 936397.58 | K15: =1/(1+'Model Assumptions'!$C$20)^A15 -> 0.58467929 | L15: =I15*K15 -> 79775.537 | M15: =M14+L15 -> 551183.47 | N15: ='4Electric Bills'!K16*(1+'Model Assumptions'!$C$21)^A15 -> 396904.3 | O15: =MAX(N15-H15,0) -> 260461.06 | P15: =P14+N15 -> 3782578.5 | Q15: =Q14+O15 -> 3528788.3
A16: 12 | B16: 0 | C16: 0 | D16: ='4Electric Bills'!V16*(1+'Model Assumptions'!$C$21)^(A16-1)*(1-'Model Assumptions'!$C$22)^(A16-1) -> 72980.671 | E16: ='4Electric Bills'!X16*(1+'Model Assumptions'!$C$21)^(A16-1)*(1-'Model Assumptions'!$C$22)^(A16-1) -> 5483.3297 | F16: ='4Electric Bills'!Y16*(1+'Model Assumptions'!$C$21)^(A16-1) -> 6938.6642 | G16: ='4Electric Bills'!W16*(1+'Model Assumptions'!$C$21)^(A16-1) -> 54501.099 | H16: =SUM(D16:G16) -> 139903.76 | I16: =B16+C16+H16 -> 139903.76 | J16: =J15+I16 -> 1076301.3 | K16: =1/(1+'Model Assumptions'!$C$20)^A16 -> 0.55683742 | L16: =I16*K16 -> 77903.65 | M16: =M15+L16 -> 629087.12 | N16: ='4Electric Bills'!K16*(1+'Model Assumptions'!$C$21)^A16 -> 408811.43 | O16: =MAX(N16-H16,0) -> 268907.66 | P16: =P15+N16 -> 4191389.9 | Q16: =Q15+O16 -> 3797696
A17: 13 | B17: 0 | C17: 0 | D17: ='4Electric Bills'!V16*(1+'Model Assumptions'!$C$21)^(A17-1)*(1-'Model Assumptions'!$C$22)^(A17-1) -> 74568.73 | E17: ='4Electric Bills'!X16*(1+'Model Assumptions'!$C$21)^(A17-1)*(1-'Model Assumptions'!$C$22)^(A17-1) -> 5602.647 | F17: ='4Electric Bills'!Y16*(1+'Model Assumptions'!$C$21)^(A17-1) -> 7146.8241 | G17: ='4Electric Bills'!W16*(1+'Model Assumptions'!$C$21)^(A17-1) -> 56136.132 | H17: =SUM(D17:G17) -> 143454.33 | I17: =B17+C17+H17 -> 143454.33 | J17: =J16+I17 -> 1219755.7 | K17: =1/(1+'Model Assumptions'!$C$20)^A17 -> 0.53032135 | L17: =I17*K17 -> 76076.896 | M17: =M16+L17 -> 705164.02 | N17: ='4Electric Bills'!K16*(1+'Model Assumptions'!$C$21)^A17 -> 421075.77 | O17: =MAX(N17-H17,0) -> 277621.44 | P17: =P16+N17 -> 4612465.7 | Q17: =Q16+O17 -> 4075317.4
A18: 14 | B18: 0 | C18: 0 | D18: ='4Electric Bills'!V16*(1+'Model Assumptions'!$C$21)^(A18-1)*(1-'Model Assumptions'!$C$22)^(A18-1) -> 76191.346 | E18: ='4Electric Bills'!X16*(1+'Model Assumptions'!$C$21)^(A18-1)*(1-'Model Assumptions'!$C$22)^(A18-1) -> 5724.5606 | F18: ='4Electric Bills'!Y16*(1+'Model Assumptions'!$C$21)^(A18-1) -> 7361.2289 | G18: ='4Electric Bills'!W16*(1+'Model Assumptions'!$C$21)^(A18-1) -> 57820.216 | H18: =SUM(D18:G18) -> 147097.35 | I18: =B18+C18+H18 -> 147097.35 | J18: =J17+I18 -> 1366853 | K18: =1/(1+'Model Assumptions'!$C$20)^A18 -> 0.50506795 | L18: =I18*K18 -> 74294.158 | M18: =M17+L18 -> 779458.18 | N18: ='4Electric Bills'!K16*(1+'Model Assumptions'!$C$21)^A18 -> 433708.04 | O18: =MAX(N18-H18,0) -> 286610.69 | P18: =P17+N18 -> 5046173.7 | Q18: =Q17+O18 -> 4361928.1
A19: 15 | B19: 0 | C19: 0 | D19: ='4Electric Bills'!V16*(1+'Model Assumptions'!$C$21)^(A19-1)*(1-'Model Assumptions'!$C$22)^(A19-1) -> 77849.269 | E19: ='4Electric Bills'!X16*(1+'Model Assumptions'!$C$21)^(A19-1)*(1-'Model Assumptions'!$C$22)^(A19-1) -> 5849.127 | F19: ='4Electric Bills'!Y16*(1+'Model Assumptions'!$C$21)^(A19-1) -> 7582.0657 | G19: ='4Electric Bills'!W16*(1+'Model Assumptions'!$C$21)^(A19-1) -> 59554.822 | H19: =SUM(D19:G19) -> 150835.28 | I19: =B19+C19+H19 -> 150835.28 | J19: =J18+I19 -> 1517688.3 | K19: =1/(1+'Model Assumptions'!$C$20)^A19 -> 0.4810171 | L19: =I19*K19 -> 72554.351 | M19: =M18+L19 -> 852012.53 | N19: ='4Electric Bills'!K16*(1+'Model Assumptions'!$C$21)^A19 -> 446719.28 | O19: =MAX(N19-H19,0) -> 295884 | P19: =P18+N19 -> 5492893 | Q19: =Q18+O19 -> 4657812.1
A20: 16 | B20: 0 | C20: 0 | D20: ='4Electric Bills'!V16*(1+'Model Assumptions'!$C$21)^(A20-1)*(1-'Model Assumptions'!$C$22)^(A20-1) -> 79543.269 | E20: ='4Electric Bills'!X16*(1+'Model Assumptions'!$C$21)^(A20-1)*(1-'Model Assumptions'!$C$22)^(A20-1) -> 5976.404 | F20: ='4Electric Bills'!Y16*(1+'Model Assumptions'!$C$21)^(A20-1) -> 7809.5277 | G20: ='4Electric Bills'!W16*(1+'Model Assumptions'!$C$21)^(A20-1) -> 61341.467 | H20: =SUM(D20:G20) -> 154670.67 | I20: =B20+C20+H20 -> 154670.67 | J20: =J19+I20 -> 1672359 | K20: =1/(1+'Model Assumptions'!$C$20)^A20 -> 0.45811152 | L20: =I20*K20 -> 70856.415 | M20: =M19+L20 -> 922868.94 | N20: ='4Electric Bills'!K16*(1+'Model Assumptions'!$C$21)^A20 -> 460120.86 | O20: =MAX(N20-H20,0) -> 305450.2 | P20: =P19+N20 -> 5953013.9 | Q20: =Q19+O20 -> 4963262.3
A21: 17 | B21: 0 | C21: 0 | D21: ='4Electric Bills'!V16*(1+'Model Assumptions'!$C$21)^(A21-1)*(1-'Model Assumptions'!$C$22)^(A21-1) -> 81274.131 | E21: ='4Electric Bills'!X16*(1+'Model Assumptions'!$C$21)^(A21-1)*(1-'Model Assumptions'!$C$22)^(A21-1) -> 6106.4506 | F21: ='4Electric Bills'!Y16*(1+'Model Assumptions'!$C$21)^(A21-1) -> 8043.8135 | G21: ='4Electric Bills'!W16*(1+'Model Assumptions'!$C$21)^(A21-1) -> 63181.711 | H21: =SUM(D21:G21) -> 158606.11 | I21: =B21+C21+H21 -> 158606.11 | J21: =J20+I21 -> 1830965.1 | K21: =1/(1+'Model Assumptions'!$C$20)^A21 -> 0.43629669 | L21: =I21*K21 -> 69199.319 | M21: =M20+L21 -> 992068.26 | N21: ='4Electric Bills'!K16*(1+'Model Assumptions'!$C$21)^A21 -> 473924.49 | O21: =MAX(N21-H21,0) -> 315318.38 | P21: =P20+N21 -> 6426938.3 | Q21: =Q20+O21 -> 5278580.7
A22: 18 | B22: 0 | C22: 0 | D22: ='4Electric Bills'!V16*(1+'Model Assumptions'!$C$21)^(A22-1)*(1-'Model Assumptions'!$C$22)^(A22-1) -> 83042.656 | E22: ='4Electric Bills'!X16*(1+'Model Assumptions'!$C$21)^(A22-1)*(1-'Model Assumptions'!$C$22)^(A22-1) -> 6239.3269 | F22: ='4Electric Bills'!Y16*(1+'Model Assumptions'!$C$21)^(A22-1) -> 8285.1279 | G22: ='4Electric Bills'!W16*(1+'Model Assumptions'!$C$21)^(A22-1) -> 65077.162 | H22: =SUM(D22:G22) -> 162644.27 | I22: =B22+C22+H22 -> 162644.27 | J22: =J21+I22 -> 1993609.4 | K22: =1/(1+'Model Assumptions'!$C$20)^A22 -> 0.41552065 | L22: =I22*K22 -> 67582.055 | M22: =M21+L22 -> 1059650.3 | N22: ='4Electric Bills'!K16*(1+'Model Assumptions'!$C$21)^A22 -> 488142.22 | O22: =MAX(N22-H22,0) -> 325497.95 | P22: =P21+N22 -> 6915080.6 | Q22: =Q21+O22 -> 5604078.6
A23: 19 | B23: 0 | C23: 0 | D23: ='4Electric Bills'!V16*(1+'Model Assumptions'!$C$21)^(A23-1)*(1-'Model Assumptions'!$C$22)^(A23-1) -> 84849.664 | E23: ='4Electric Bills'!X16*(1+'Model Assumptions'!$C$21)^(A23-1)*(1-'Model Assumptions'!$C$22)^(A23-1) -> 6375.0947 | F23: ='4Electric Bills'!Y16*(1+'Model Assumptions'!$C$21)^(A23-1) -> 8533.6818 | G23: ='4Electric Bills'!W16*(1+'Model Assumptions'!$C$21)^(A23-1) -> 67029.477 | H23: =SUM(D23:G23) -> 166787.92 | I23: =B23+C23+H23 -> 166787.92 | J23: =J22+I23 -> 2160397.3 | K23: =1/(1+'Model Assumptions'!$C$20)^A23 -> 0.39573396 | L23: =I23*K23 -> 66003.643 | M23: =M22+L23 -> 1125654 | N23: ='4Electric Bills'!K16*(1+'Model Assumptions'!$C$21)^A23 -> 502786.49 | O23: =MAX(N23-H23,0) -> 335998.57 | P23: =P22+N23 -> 7417867.1 | Q23: =Q22+O23 -> 5940077.2
A24: 20 | B24: 0 | C24: 0 | D24: ='4Electric Bills'!V16*(1+'Model Assumptions'!$C$21)^(A24-1)*(1-'Model Assumptions'!$C$22)^(A24-1) -> 86695.993 | E24: ='4Electric Bills'!X16*(1+'Model Assumptions'!$C$21)^(A24-1)*(1-'Model Assumptions'!$C$22)^(A24-1) -> 6513.8167 | F24: ='4Electric Bills'!Y16*(1+'Model Assumptions'!$C$21)^(A24-1) -> 8789.6922 | G24: ='4Electric Bills'!W16*(1+'Model Assumptions'!$C$21)^(A24-1) -> 69040.361 | H24: =SUM(D24:G24) -> 171039.86 | I24: =B24+C24+H24 -> 171039.86 | J24: =J23+I24 -> 2331437.1 | K24: =1/(1+'Model Assumptions'!$C$20)^A24 -> 0.37688948 | L24: =I24*K24 -> 64463.126 | M24: =M23+L24 -> 1190117.1 | N24: ='4Electric Bills'!K16*(1+'Model Assumptions'!$C$21)^A24 -> 517870.09 | O24: =MAX(N24-H24,0) -> 346830.22 | P24: =P23+N24 -> 7935737.1 | Q24: =Q23+O24 -> 6286907.4
A25: 21 | B25: 0 | C25: 0 | D25: ='4Electric Bills'!V16*(1+'Model Assumptions'!$C$21)^(A25-1)*(1-'Model Assumptions'!$C$22)^(A25-1) -> 88582.498 | E25: ='4Electric Bills'!X16*(1+'Model Assumptions'!$C$21)^(A25-1)*(1-'Model Assumptions'!$C$22)^(A25-1) -> 6655.5574 | F25: ='4Electric Bills'!Y16*(1+'Model Assumptions'!$C$21)^(A25-1) -> 9053.383 | G25: ='4Electric Bills'!W16*(1+'Model Assumptions'!$C$21)^(A25-1) -> 71111.572 | H25: =SUM(D25:G25) -> 175403.01 | I25: =B25+C25+H25 -> 175403.01 | J25: =J24+I25 -> 2506840.2 | K25: =1/(1+'Model Assumptions'!$C$20)^A25 -> 0.35894236 | L25: =I25*K25 -> 62959.571 | M25: =M24+L25 -> 1253076.7 | N25: ='4Electric Bills'!K16*(1+'Model Assumptions'!$C$21)^A25 -> 533406.19 | O25: =MAX(N25-H25,0) -> 358003.18 | P25: =P24+N25 -> 8469143.3 | Q25: =Q24+O25 -> 6644910.6
A26: 22 | B26: 0 | C26: 0 | D26: ='4Electric Bills'!V16*(1+'Model Assumptions'!$C$21)^(A26-1)*(1-'Model Assumptions'!$C$22)^(A26-1) -> 90510.053 | E26: ='4Electric Bills'!X16*(1+'Model Assumptions'!$C$21)^(A26-1)*(1-'Model Assumptions'!$C$22)^(A26-1) -> 6800.3823 | F26: ='4Electric Bills'!Y16*(1+'Model Assumptions'!$C$21)^(A26-1) -> 9324.9845 | G26: ='4Electric Bills'!W16*(1+'Model Assumptions'!$C$21)^(A26-1) -> 73244.919 | H26: =SUM(D26:G26) -> 179880.34 | I26: =B26+C26+H26 -> 179880.34 | J26: =J25+I26 -> 2686720.5 | K26: =1/(1+'Model Assumptions'!$C$20)^A26 -> 0.34184987 | L26: =I26*K26 -> 61492.071 | M26: =M25+L26 -> 1314568.7 | N26: ='4Electric Bills'!K16*(1+'Model Assumptions'!$C$21)^A26 -> 549408.37 | O26: =MAX(N26-H26,0) -> 369528.03 | P26: =P25+N26 -> 9018551.7 | Q26: =Q25+O26 -> 7014438.6
A27: 23 | B27: 0 | C27: 0 | D27: ='4Electric Bills'!V16*(1+'Model Assumptions'!$C$21)^(A27-1)*(1-'Model Assumptions'!$C$22)^(A27-1) -> 92479.552 | E27: ='4Electric Bills'!X16*(1+'Model Assumptions'!$C$21)^(A27-1)*(1-'Model Assumptions'!$C$22)^(A27-1) -> 6948.3586 | F27: ='4Electric Bills'!Y16*(1+'Model Assumptions'!$C$21)^(A27-1) -> 9604.734 | G27: ='4Electric Bills'!W16*(1+'Model Assumptions'!$C$21)^(A27-1) -> 75442.267 | H27: =SUM(D27:G27) -> 184474.91 | I27: =B27+C27+H27 -> 184474.91 | J27: =J26+I27 -> 2871195.4 | K27: =1/(1+'Model Assumptions'!$C$20)^A27 -> 0.32557131 | L27: =I27*K27 -> 60059.738 | M27: =M26+L27 -> 1374628.5 | N27: ='4Electric Bills'!K16*(1+'Model Assumptions'!$C$21)^A27 -> 565890.62 | O27: =MAX(N27-H27,0) -> 381415.71 | P27: =P26+N27 -> 9584442.3 | Q27: =Q26+O27 -> 7395854.3
A28: 24 | B28: 0 | C28: 0 | D28: ='4Electric Bills'!V16*(1+'Model Assumptions'!$C$21)^(A28-1)*(1-'Model Assumptions'!$C$22)^(A28-1) -> 94491.907 | E28: ='4Electric Bills'!X16*(1+'Model Assumptions'!$C$21)^(A28-1)*(1-'Model Assumptions'!$C$22)^(A28-1) -> 7099.5549 | F28: ='4Electric Bills'!Y16*(1+'Model Assumptions'!$C$21)^(A28-1) -> 9892.876 | G28: ='4Electric Bills'!W16*(1+'Model Assumptions'!$C$21)^(A28-1) -> 77705.535 | H28: =SUM(D28:G28) -> 189189.87 | I28: =B28+C28+H28 -> 189189.87 | J28: =J27+I28 -> 3060385.3 | K28: =1/(1+'Model Assumptions'!$C$20)^A28 -> 0.31006791 | L28: =I28*K28 -> 58661.709 | M28: =M27+L28 -> 1433290.2 | N28: ='4Electric Bills'!K16*(1+'Model Assumptions'!$C$21)^A28 -> 582867.34 | O28: =MAX(N28-H28,0) -> 393677.47 | P28: =P27+N28 -> 10167310 | Q28: =Q27+O28 -> 7789531.8
A29: 25 | B29: 0 | C29: 0 | D29: ='4Electric Bills'!V16*(1+'Model Assumptions'!$C$21)^(A29-1)*(1-'Model Assumptions'!$C$22)^(A29-1) -> 96548.051 | E29: ='4Electric Bills'!X16*(1+'Model Assumptions'!$C$21)^(A29-1)*(1-'Model Assumptions'!$C$22)^(A29-1) -> 7254.0412 | F29: ='4Electric Bills'!Y16*(1+'Model Assumptions'!$C$21)^(A29-1) -> 10189.662 | G29: ='4Electric Bills'!W16*(1+'Model Assumptions'!$C$21)^(A29-1) -> 80036.701 | H29: =SUM(D29:G29) -> 194028.46 | I29: =B29+C29+H29 -> 194028.46 | J29: =J28+I29 -> 3254413.7 | K29: =1/(1+'Model Assumptions'!$C$20)^A29 -> 0.29530277 | L29: =I29*K29 -> 57297.141 | M29: =M28+L29 -> 1490587.3 | N29: ='4Electric Bills'!K16*(1+'Model Assumptions'!$C$21)^A29 -> 600353.36 | O29: =MAX(N29-H29,0) -> 406324.91 | P29: =P28+N29 -> 10767663 | Q29: =Q28+O29 -> 8195856.7
A30: 26 | B30: 0 | C30: 0 | D30: ='4Electric Bills'!V16*(1+'Model Assumptions'!$C$21)^(A30-1)*(1-'Model Assumptions'!$C$22)^(A30-1) -> 98648.936 | E30: ='4Electric Bills'!X16*(1+'Model Assumptions'!$C$21)^(A30-1)*(1-'Model Assumptions'!$C$22)^(A30-1) -> 7411.8892 | F30: ='4Electric Bills'!Y16*(1+'Model Assumptions'!$C$21)^(A30-1) -> 10495.352 | G30: ='4Electric Bills'!W16*(1+'Model Assumptions'!$C$21)^(A30-1) -> 82437.802 | H30: =SUM(D30:G30) -> 198993.98 | I30: =B30+C30+H30 -> 198993.98 | J30: =J29+I30 -> 3453407.7 | K30: =1/(1+'Model Assumptions'!$C$20)^A30 -> 0.28124073 | L30: =I30*K30 -> 55965.213 | M30: =M29+L30 -> 1546552.5 | N30: ='4Electric Bills'!K16*(1+'Model Assumptions'!$C$21)^A30 -> 618363.96 | O30: =MAX(N30-H30,0) -> 419369.98 | P30: =P29+N30 -> 11386027 | Q30: =Q29+O30 -> 8615226.7
A31: 27 | B31: 0 | C31: 0 | D31: ='4Electric Bills'!V16*(1+'Model Assumptions'!$C$21)^(A31-1)*(1-'Model Assumptions'!$C$22)^(A31-1) -> 100795.54 | E31: ='4Electric Bills'!X16*(1+'Model Assumptions'!$C$21)^(A31-1)*(1-'Model Assumptions'!$C$22)^(A31-1) -> 7573.1719 | F31: ='4Electric Bills'!Y16*(1+'Model Assumptions'!$C$21)^(A31-1) -> 10810.213 | G31: ='4Electric Bills'!W16*(1+'Model Assumptions'!$C$21)^(A31-1) -> 84910.936 | H31: =SUM(D31:G31) -> 204089.86 | I31: =B31+C31+H31 -> 204089.86 | J31: =J30+I31 -> 3657497.6 | K31: =1/(1+'Model Assumptions'!$C$20)^A31 -> 0.26784832 | L31: =I31*K31 -> 54665.125 | M31: =M30+L31 -> 1601217.7 | N31: ='4Electric Bills'!K16*(1+'Model Assumptions'!$C$21)^A31 -> 636914.88 | O31: =MAX(N31-H31,0) -> 432825.03 | P31: =P30+N31 -> 12022942 | Q31: =Q30+O31 -> 9048051.7
A32: 28 | B32: 0 | C32: 0 | D32: ='4Electric Bills'!V16*(1+'Model Assumptions'!$C$21)^(A32-1)*(1-'Model Assumptions'!$C$22)^(A32-1) -> 102988.85 | E32: ='4Electric Bills'!X16*(1+'Model Assumptions'!$C$21)^(A32-1)*(1-'Model Assumptions'!$C$22)^(A32-1) -> 7737.9641 | F32: ='4Electric Bills'!Y16*(1+'Model Assumptions'!$C$21)^(A32-1) -> 11134.519 | G32: ='4Electric Bills'!W16*(1+'Model Assumptions'!$C$21)^(A32-1) -> 87458.264 | H32: =SUM(D32:G32) -> 209319.6 | I32: =B32+C32+H32 -> 209319.6 | J32: =J31+I32 -> 3866817.2 | K32: =1/(1+'Model Assumptions'!$C$20)^A32 -> 0.25509364 | L32: =I32*K32 -> 53396.097 | M32: =M31+L32 -> 1654613.7 | N32: ='4Electric Bills'!K16*(1+'Model Assumptions'!$C$21)^A32 -> 656022.33 | O32: =MAX(N32-H32,0) -> 446702.73 | P32: =P31+N32 -> 12678964 | Q32: =Q31+O32 -> 9494754.5
A33: 29 | B33: 0 | C33: 0 | D33: ='4Electric Bills'!V16*(1+'Model Assumptions'!$C$21)^(A33-1)*(1-'Model Assumptions'!$C$22)^(A33-1) -> 105229.89 | E33: ='4Electric Bills'!X16*(1+'Model Assumptions'!$C$21)^(A33-1)*(1-'Model Assumptions'!$C$22)^(A33-1) -> 7906.3422 | F33: ='4Electric Bills'!Y16*(1+'Model Assumptions'!$C$21)^(A33-1) -> 11468.555 | G33: ='4Electric Bills'!W16*(1+'Model Assumptions'!$C$21)^(A33-1) -> 90082.012 | H33: =SUM(D33:G33) -> 214686.79 | I33: =B33+C33+H33 -> 214686.79 | J33: =J32+I33 -> 4081504 | K33: =1/(1+'Model Assumptions'!$C$20)^A33 -> 0.24294632 | L33: =I33*K33 -> 52157.367 | M33: =M32+L33 -> 1706771.1 | N33: ='4Electric Bills'!K16*(1+'Model Assumptions'!$C$21)^A33 -> 675703 | O33: =MAX(N33-H33,0) -> 461016.21 | P33: =P32+N33 -> 13354667 | Q33: =Q32+O33 -> 9955770.7
A34: 30 | B34: 0 | C34: 0 | D34: ='4Electric Bills'!V16*(1+'Model Assumptions'!$C$21)^(A34-1)*(1-'Model Assumptions'!$C$22)^(A34-1) -> 107519.69 | E34: ='4Electric Bills'!X16*(1+'Model Assumptions'!$C$21)^(A34-1)*(1-'Model Assumptions'!$C$22)^(A34-1) -> 8078.3842 | F34: ='4Electric Bills'!Y16*(1+'Model Assumptions'!$C$21)^(A34-1) -> 11812.611 | G34: ='4Electric Bills'!W16*(1+'Model Assumptions'!$C$21)^(A34-1) -> 92784.473 | H34: =SUM(D34:G34) -> 220195.16 | I34: =B34+C34+H34 -> 220195.16 | J34: =J33+I34 -> 4301699.1 | K34: =1/(1+'Model Assumptions'!$C$20)^A34 -> 0.23137745 | L34: =I34*K34 -> 50948.193 | M34: =M33+L34 -> 1757719.3 | N34: ='4Electric Bills'!K16*(1+'Model Assumptions'!$C$21)^A34 -> 695974.09 | O34: =MAX(N34-H34,0) -> 475778.93 | P34: =P33+N34 -> 14050641 | Q34: =Q33+O34 -> 10431550
A37: 30-Year Financial Metrics | B37: Value | C37: Unit | D37: Method / Interpretation
A38: Gross Project Cost | B38: ='3Rebates Incentives'!D4 -> 1074972.3 | C38: $ | D38: Year-0 cash purchase
A39: Modeled Year-1 ITC + MACRS Benefits | B39: ='3Rebates Incentives'!H19 -> 682607.41 | C39: $ | D39: Proposal-template tax case
A40: 30-Year Operating Savings | B40: =SUM(H5:H34) -> 4694064 | C40: $ | D40: PV + export + grid arbitrage + demand savings
A41: NPV @ 5% | B41: =SUM(L4:L34) -> 1757719.3 | C41: $ | D41: NPV of all project cash flows including Year-0 cost and Year-1 tax benefits
A42: IRR | B42: =IRR(I4:I34) -> 0.21518283 | C42: % | D42: Annual project IRR on modeled cash flows
A43: Simple Payback | B43: =IF(J5>=0,0+ABS(J4)/I5,IF(J6>=0,1+ABS(J5)/I6,IF(J7>=0,2+ABS(J6)/I7,IF(J8>=0,3+ABS(J7)/I8,IF(J9>=0,4+ABS(J8)/I9,IF(J10>=0,5+ABS(J9)/I10,IF(J11>=0,6+ABS(J10)/I11,IF(J12>=0,7+ABS(J11)/I12,IF(J13>=0,8+ABS(J12)/I13,IF(J14>=0,9+ABS(J13)/I14,IF(J15>=0,10+ABS(J14)/I15,IF(J16>=0,11+ABS(J15)/I16,IF(J17>=0,12+ABS(J16)/I17,IF(J18>=0,13+ABS(J17)/I18,IF(J19>=0,14+ABS(J18)/I19,IF(J20>=0,15+ABS(J19)/I20,IF(J21>=0,16+ABS(J20)/I21,IF(J22>=0,17+ABS(J21)/I22,IF(J23>=0,18+ABS(J22)/I23,IF(J24>=0,19+ABS(J23)/I24,IF(J25>=0,20+ABS(J24)/I25,IF(J26>=0,21+ABS(J25)/I26,IF(J27>=0,22+ABS(J26)/I27,IF(J28>=0,23+ABS(J27)/I28,IF(J29>=0,24+ABS(J28)/I29,IF(J30>=0,25+ABS(J29)/I30,IF(J31>=0,26+ABS(J30)/I31,IF(J32>=0,27+ABS(J31)/I32,IF(J33>=0,28+ABS(J32)/I33,IF(J34>=0,29+ABS(J33)/I34,NA())))))))))))))))))))))))))))))) -> 3.8876454 | C43: years | D43: Interpolated first year cumulative cash flow becomes non-negative
A44: Discounted Payback | B44: =IF(M5>=0,0+ABS(M4)/L5,IF(M6>=0,1+ABS(M5)/L6,IF(M7>=0,2+ABS(M6)/L7,IF(M8>=0,3+ABS(M7)/L8,IF(M9>=0,4+ABS(M8)/L9,IF(M10>=0,5+ABS(M9)/L10,IF(M11>=0,6+ABS(M10)/L11,IF(M12>=0,7+ABS(M11)/L12,IF(M13>=0,8+ABS(M12)/L13,IF(M14>=0,9+ABS(M13)/L14,IF(M15>=0,10+ABS(M14)/L15,IF(M16>=0,11+ABS(M15)/L16,IF(M17>=0,12+ABS(M16)/L17,IF(M18>=0,13+ABS(M17)/L18,IF(M19>=0,14+ABS(M18)/L19,IF(M20>=0,15+ABS(M19)/L20,IF(M21>=0,16+ABS(M20)/L21,IF(M22>=0,17+ABS(M21)/L22,IF(M23>=0,18+ABS(M22)/L23,IF(M24>=0,19+ABS(M23)/L24,IF(M25>=0,20+ABS(M24)/L25,IF(M26>=0,21+ABS(M25)/L26,IF(M27>=0,22+ABS(M26)/L27,IF(M28>=0,23+ABS(M27)/L28,IF(M29>=0,24+ABS(M28)/L29,IF(M30>=0,25+ABS(M29)/L30,IF(M31>=0,26+ABS(M30)/L31,IF(M32>=0,27+ABS(M31)/L32,IF(M33>=0,28+ABS(M32)/L33,IF(M34>=0,29+ABS(M33)/L34,NA())))))))))))))))))))))))))))))) -> 4.68653 | C44: years | D44: Interpolated first year cumulative discounted cash flow becomes non-negative

Sheet Proposal Checklist
A1: PROPOSAL CONTENT CHECKLIST
A3: Requested item | B3: Sheet | C3: Range / chart area | D3: Status
A4: Solar PV System Cost and Incentives | B4: PV Proposal | C4: D3:E9 | D4: Included
A5: ENERGY CONSUMPTION MIX — pie chart | B5: PV Proposal | C5: G3:J20 | D5: Included
A6: MONTHLY ENERGY USE VS SOLAR GENERATION — line chart | B6: PV Proposal | C6: F22:N38 | D6: Included
A7: MONTHLY ENERGY USE VS SOLAR GENERATION — bar chart | B7: PV Proposal | C7: A28:E44 | D7: Included
A8: ESS Cost and Incentives | B8: ESS Proposal | C8: D3:E9 | D8: Included
A9: ENERGY STORAGE ANNUAL UTILIZATION — bar chart | B9: ESS Proposal | C9: G3:L25 | D9: Included
A10: Energy Output and Demand Savings From Solar PV and Energy Storage | B10: ESS Proposal | C10: A13:E26 | D10: Included
A11: 4.1.3 REBATES & INCENTIVES | B11: Rebates Incentives | C11: A1:F17 | D11: Included
A12: CURRENT ELECTRIC BILL — standalone table | B12: Electric Bills | C12: A3:K16 | D12: Included / separated
A13: NEW ELECTRIC BILL — standalone table | B13: Electric Bills | C13: P3:Z16 | D13: Included / separated
A14: Cash Purchase — vertical table | B14: Cash Purchase | C14: A3:B13 | D14: Included
... A18: Page 3 project overview table | B18: Proposal Dashboard | C18: A1:D10 | D18: Included

Sheet PV-ESS Energy Flow
A1: PV + ESS MONTHLY DISPATCH
A3: Month | B3: Days | C3: Load kWh | D3: PV Gen kWh | E3: PV Self-Consumed Before ESS | F3: PV Surplus Before ESS | G3: Peak-Window Load kWh | H3: ESS Delivered Capacity / Day | I3: PV-Surplus-Charged ESS Discharge | J3: Grid-Charged ESS Discharge | K3: Total ESS Discharge | L3: ESS Discharge / PV Gen | M3: Historical Max Demand kW | N3: Target Shave kW | O3: Demand Savings $ | P3: PV Energy Savings $ | Q3: Export Value $ | R3: Grid Charge Input (kWh) | S3: Low-Price Charge Rate ($/kWh) | T3: High-Price Avoided Rate ($/kWh) | U3: Grid Charging Cost ($) | V3: Avoided Peak Energy Cost ($) | W3: Net Grid-Charging Arbitrage Savings ($)
A4: Jan | B4: ='ESS Sizing'!B8 -> 33 | C4: ='PV Production'!B5 -> 54844 | D4: ='PV Production'!G5 -> 43391.64 | E4: =MIN(C4,D4) -> 43391.64 | F4: =MAX(D4-C4,0) -> 0 | G4: ='ESS Sizing'!E8 -> 2137 | H4: ='ESS Sizing'!I8*Recommendation!B9 -> 367.7184 | I4: =MIN(F4,G4,H4*B4) -> 0 | J4: =MAX(MIN(G4,H4*B4)-I4,0) -> 2137 | K4: =I4+J4 -> 2137 | L4: =K4/D4 -> 0.049249118 | M4: ='Combined TOU Profile'!M8 -> 655 | N4: ='Demand Charge'!$B$20 -> 100 | O4: ='Demand Charge'!Q7 -> 2643.674 | P4: =(E4+I4)*Financial!$B$17 -> 4007.0582 | Q4: =MAX(F4-I4,0)*'Model Assumptions'!$C$16 -> 0 | R4: =J4/'Model Assumptions'!$C$13 -> 2374.4444 | S4: =IFERROR(('Meter1 TOU Detail'!R8+'Meter2 TOU Detail'!R8)/('Meter1 TOU Detail'!Q8+'Meter2 TOU Detail'!Q8),0) -> 0.036022406 | T4: =IFERROR(('Meter1 TOU Detail'!N8+'Meter2 TOU Detail'!N8)/('Meter1 TOU Detail'!M8+'Meter2 TOU Detail'!M8),0) -> 0.19957885 | U4: =R4*S4 -> 85.533201 | V4: =J4*T4 -> 426.5 | W4: =V4-U4 -> 340.9668
A5: Feb | B5: ='ESS Sizing'!B9 -> 30 | C5: ='PV Production'!B6 -> 48926 | D5: ='PV Production'!G6 -> 46834.144 | E5: =MIN(C5,D5) -> 46834.144 | F5: =MAX(D5-C5,0) -> 0 | G5: ='ESS Sizing'!E9 -> 1802 | H5: ='ESS Sizing'!I9*Recommendation!B9 -> 367.7184 | I5: =MIN(F5,G5,H5*B5) -> 0 | J5: =MAX(MIN(G5,H5*B5)-I5,0) -> 1802 | K5: =I5+J5 -> 1802 | L5: =K5/D5 -> 0.038476202 | M5: ='Combined TOU Profile'!M9 -> 640 | N5: ='Demand Charge'!$B$20 -> 100 | O5: ='Demand Charge'!Q8 -> 2702.9719 | P5: =(E5+I5)*Financial!$B$17 -> 4324.9607 | Q5: =MAX(F5-I5,0)*'Model Assumptions'!$C$16 -> 0 | R5: =J5/'Model Assumptions'!$C$13 -> 2002.2222 | S5: =IFERROR(('Meter1 TOU Detail'!R9+'Meter2 TOU Detail'!R9)/('Meter1 TOU Detail'!Q9+'Meter2 TOU Detail'!Q9),0) -> 0.038341851 | T5: =IFERROR(('Meter1 TOU Detail'!N9+'Meter2 TOU Detail'!N9)/('Meter1 TOU Detail'!M9+'Meter2 TOU Detail'!M9),0) -> 0.1931909 | U5: =R5*S5 -> 76.768906 | V5: =J5*T5 -> 348.13 | W5: =V5-U5 -> 271.36109
A6: Mar | B6: ='ESS Sizing'!B10 -> 29 | C6: ='PV Production'!B7 -> 52449 | D6: ='PV Production'!G7 -> 61748.868 | E6: =MIN(C6,D6) -> 52449 | F6: =MAX(D6-C6,0) -> 9299.868 | G6: ='ESS Sizing'!E10 -> 1437 | H6: ='ESS Sizing'!I10*Recommendation!B9 -> 367.7184 | I6: =MIN(F6,G6,H6*B6) -> 1437 | J6: =MAX(MIN(G6,H6*B6)-I6,0) -> 0 | K6: =I6+J6 -> 1437 | L6: =K6/D6 -> 0.023271682 | M6: ='Combined TOU Profile'!M10 -> 500 | N6: ='Demand Charge'!$B$20 -> 100 | O6: ='Demand Charge'!Q9 -> 3303.2762 | P6: =(E6+I6)*Financial!$B$17 -> 4976.1737 | Q6: =MAX(F6-I6,0)*'Model Assumptions'!$C$16 -> 393.1434 | R6: =J6/'Model Assumptions'!$C$13 -> 0 | S6: =IFERROR(('Meter1 TOU Detail'!R10+'Meter2 TOU Detail'!R10)/('Meter1 TOU Detail'!Q10+'Meter2 TOU Detail'!Q10),0) -> 0.037896077 | T6: =IFERROR(('Meter1 TOU Detail'!N10+'Meter2 TOU Detail'!N10)/('Meter1 TOU Detail'!M10+'Meter2 TOU Detail'!M10),0) -> 0.18547669 | U6: =R6*S6 -> 0 | V6: =J6*T6 -> 0 | W6: =V6-U6 -> 0
A7: Apr | B7: ='ESS Sizing'!B11 -> 32 | C7: ='PV Production'!B8 -> 40752 | D7: ='PV Production'!G8 -> 69502.882 | E7: =MIN(C7,D7) -> 40752 | F7: =MAX(D7-C7,0) -> 28750.882 | G7: ='ESS Sizing'!E11 -> 1317 | H7: ='ESS Sizing'!I11*Recommendation!B9 -> 367.7184 | I7: =MIN(F7,G7,H7*B7) -> 1317 | J7: =MAX(MIN(G7,H7*B7)-I7,0) -> 0 | K7: =I7+J7 -> 1317 | L7: =K7/D7 -> 0.018948855 | M7: ='Combined TOU Profile'!M11 -> 442 | N7: ='Demand Charge'!$B$20 -> 100 | O7: ='Demand Charge'!Q10 -> 3210.7567 | P7: =(E7+I7)*Financial!$B$17 -> 3884.9172 | Q7: =MAX(F7-I7,0)*'Model Assumptions'!$C$16 -> 1371.6941 | R7: =J7/'Model Assumptions'!$C$13 -> 0 | S7: =IFERROR(('Meter1 TOU Detail'!R11+'Meter2 TOU Detail'!R11)/('Meter1 TOU Detail'!Q11+'Meter2 TOU Detail'!Q11),0) -> 0.038208212 | T7: =IFERROR(('Meter1 TOU Detail'!N11+'Meter2 TOU Detail'!N11)/('Meter1 TOU Detail'!M11+'Meter2 TOU Detail'!M11),0) -> 0.18214123 | U7: =R7*S7 -> 0 | V7: =J7*T7 -> 0 | W7: =V7-U7 -> 0
A8: May | B8: ='ESS Sizing'!B12 -> 29 | C8: ='PV Production'!B9 -> 51220 | D8: ='PV Production'!G9 -> 76926.724 | E8: =MIN(C8,D8) -> 51220 | F8: =MAX(D8-C8,0) -> 25706.724 | G8: ='ESS Sizing'!E12 -> 1280.1623 | H8: ='ESS Sizing'!I12*Recommendation!B9 -> 367.7184 | I8: =MIN(F8,G8,H8*B8) -> 1280.1623 | J8: =MAX(MIN(G8,H8*B8)-I8,0) -> 0 | K8: =I8+J8 -> 1280.1623 | L8: =K8/D8 -> 0.016641321 | M8: ='Combined TOU Profile'!M12 -> 466 | N8: ='Demand Charge'!$B$20 -> 100 | O8: ='Demand Charge'!Q11 -> 3091.3018 | P8: =(E8+I8)*Financial!$B$17 -> 4848.1967 | Q8: =MAX(F8-I8,0)*'Model Assumptions'!$C$16 -> 1221.3281 | R8: =J8/'Model Assumptions'!$C$13 -> 0 | S8: =IFERROR(('Meter1 TOU Detail'!R12+'Meter2 TOU Detail'!R12)/('Meter1 TOU Detail'!Q12+'Meter2 TOU Detail'!Q12),0) -> 0.037269903 | T8: =IFERROR(('Meter1 TOU Detail'!N12+'Meter2 TOU Detail'!N12)/('Meter1 TOU Detail'!M12+'Meter2 TOU Detail'!M12),0) -> 0.17572111 | U8: =R8*S8 -> 0 | V8: =J8*T8 -> 0 | W8: =V8-U8 -> 0
A9: Jun | B9: ='ESS Sizing'!B13 -> 30 | C9: ='PV Production'!B10 -> 50744 | D9: ='PV Production'!G10 -> 76305.766 | E9: =MIN(C9,D9) -> 50744 | F9: =MAX(D9-C9,0) -> 25561.766 | G9: ='ESS Sizing'!E13 -> 2001 | H9: ='ESS Sizing'!I13*Recommendation!B9 -> 367.7184 | I9: =MIN(F9,G9,H9*B9) -> 2001 | J9: =MAX(MIN(G9,H9*B9)-I9,0) -> 0 | K9: =I9+J9 -> 2001 | L9: =K9/D9 -> 0.026223444 | M9: ='Combined TOU Profile'!M13 -> 471 | N9: ='Demand Charge'!$B$20 -> 100 | O9: ='Demand Charge'!Q12 -> 3039.4649 | P9: =(E9+I9)*Financial!$B$17 -> 4870.8065 | Q9: =MAX(F9-I9,0)*'Model Assumptions'!$C$16 -> 1178.0383 | R9: =J9/'Model Assumptions'!$C$13 -> 0 | S9: =IFERROR(('Meter1 TOU Detail'!L13+'Meter2 TOU Detail'!L13)/('Meter1 TOU Detail'!K13+'Meter2 TOU Detail'!K13),0) -> 0.12877808 | T9: =IFERROR(('Meter1 TOU Detail'!H13+'Meter2 TOU Detail'!H13)/('Meter1 TOU Detail'!G13+'Meter2 TOU Detail'!G13),0) -> 0.71430556 | U9: =R9*S9 -> 0 | V9: =J9*T9 -> 0 | W9: =V9-U9 -> 0
A10: Jul | B10: ='ESS Sizing'!B14 -> 33 | C10: ='PV Production'!B11 -> 81109 | D10: ='PV Production'!G11 -> 70470.772 | E10: =MIN(C10,D10) -> 70470.772 | F10: =MAX(D10-C10,0) -> 0 | G10: ='ESS Sizing'!E14 -> 2798 | H10: ='ESS Sizing'!I14*Recommendation!B9 -> 367.7184 | I10: =MIN(F10,G10,H10*B10) -> 0 | J10: =MAX(MIN(G10,H10*B10)-I10,0) -> 2798 | K10: =I10+J10 -> 2798 | L10: =K10/D10 -> 0.039704404 | M10: ='Combined TOU Profile'!M14 -> 725 | N10: ='Demand Charge'!$B$20 -> 100 | O10: ='Demand Charge'!Q13 -> 3690.6724 | P10: =(E10+I10)*Financial!$B$17 -> 6507.7163 | Q10: =MAX(F10-I10,0)*'Model Assumptions'!$C$16 -> 0 | R10: =J10/'Model Assumptions'!$C$13 -> 3108.8889 | S10: =IFERROR(('Meter1 TOU Detail'!L14+'Meter2 TOU Detail'!L14)/('Meter1 TOU Detail'!K14+'Meter2 TOU Detail'!K14),0) -> 0.12645197 | T10: =IFERROR(('Meter1 TOU Detail'!H14+'Meter2 TOU Detail'!H14)/('Meter1 TOU Detail'!G14+'Meter2 TOU Detail'!G14),0) -> 0.64199036 | U10: =R10*S10 -> 393.12512 | V10: =J10*T10 -> 1796.289 | W10: =V10-U10 -> 1403.1639
A11: Aug | B11: ='ESS Sizing'!B15 -> 29 | C11: ='PV Production'!B12 -> 80723 | D11: ='PV Production'!G12 -> 69633.61 | E11: =MIN(C11,D11) -> 69633.61 | F11: =MAX(D11-C11,0) -> 0 | G11: ='ESS Sizing'!E15 -> 5523 | H11: ='ESS Sizing'!I15*Recommendation!B9 -> 367.7184 | I11: =MIN(F11,G11,H11*B11) -> 0 | J11: =MAX(MIN(G11,H11*B11)-I11,0) -> 5523 | K11: =I11+J11 -> 5523 | L11: =K11/D11 -> 0.079315147 | M11: ='Combined TOU Profile'!M15 -> 705 | N11: ='Demand Charge'!$B$20 -> 100 | O11: ='Demand Charge'!Q14 -> 4235.2234 | P11: =(E11+I11)*Financial!$B$17 -> 6430.4075 | Q11: =MAX(F11-I11,0)*'Model Assumptions'!$C$16 -> 0 | R11: =J11/'Model Assumptions'!$C$13 -> 6136.6667 | S11: =IFERROR(('Meter1 TOU Detail'!L15+'Meter2 TOU Detail'!L15)/('Meter1 TOU Detail'!K15+'Meter2 TOU Detail'!K15),0) -> 0.12734082 | T11: =IFERROR(('Meter1 TOU Detail'!H15+'Meter2 TOU Detail'!H15)/('Meter1 TOU Detail'!G15+'Meter2 TOU Detail'!G15),0) -> 0.38639616 | U11: =R11*S11 -> 781.44819 | V11: =J11*T11 -> 2134.066 | W11: =V11-U11 -> 1352.6178
A12: Sep | B12: ='ESS Sizing'!B16 -> 30 | C12: ='PV Production'!B13 -> 84369 | D12: ='PV Production'!G13 -> 60646.06 | E12: =MIN(C12,D12) -> 60646.06 | F12: =MAX(D12-C12,0) -> 0 | G12: ='ESS Sizing'!E16 -> 4411 | H12: ='ESS Sizing'!I16*Recommendation!B9 -> 367.7184 | I12: =MIN(F12,G12,H12*B12) -> 0 | J12: =MAX(MIN(G12,H12*B12)-I12,0) -> 4411 | K12: =I12+J12 -> 4411 | L12: =K12/D12 -> 0.072733497 | M12: ='Combined TOU Profile'!M16 -> 730 | N12: ='Demand Charge'!$B$20 -> 100 | O12: ='Demand Charge'!Q15 -> 4789.6301 | P12: =(E12+I12)*Financial!$B$17 -> 5600.4403 | Q12: =MAX(F12-I12,0)*'Model Assumptions'!$C$16 -> 0 | R12: =J12/'Model Assumptions'!$C$13 -> 4901.1111 | S12: =IFERROR(('Meter1 TOU Detail'!L16+'Meter2 TOU Detail'!L16)/('Meter1 TOU Detail'!K16+'Meter2 TOU Detail'!K16),0) -> 0.12451199 | T12: =IFERROR(('Meter1 TOU Detail'!H16+'Meter2 TOU Detail'!H16)/('Meter1 TOU Detail'!G16+'Meter2 TOU Detail'!G16),0) -> 0.37446854 | U12: =R12*S12 -> 610.24712 | V12: =J12*T12 -> 1651.7807 | W12: =V12-U12 -> 1041.5336
A13: Oct | B13: ='ESS Sizing'!B5 -> 29 | C13: ='PV Production'!B14 -> 50017 | D13: ='PV Production'!G14 -> 54977.828 | E13: =MIN(C13,D13) -> 50017 | F13: =MAX(D13-C13,0) -> 4960.828 | G13: ='ESS Sizing'!E5 -> 1701 | H13: ='ESS Sizing'!I5*Recommendation!B9 -> 367.7184 | I13: =MIN(F13,G13,H13*B13) -> 1701 | J13: =MAX(MIN(G13,H13*B13)-I13,0) -> 0 | K13: =I13+J13 -> 1701 | L13: =K13/D13 -> 0.030939745 | M13: ='Combined TOU Profile'!M5 -> 552 | N13: ='Demand Charge'!$B$20 -> 100 | O13: ='Demand Charge'!Q4 -> 2887.8498 | P13: =(E13+I13)*Financial!$B$17 -> 4775.9669 | Q13: =MAX(F13-I13,0)*'Model Assumptions'!$C$16 -> 162.9914 | R13: =J13/'Model Assumptions'!$C$13 -> 0 | S13: =IFERROR(('Meter1 TOU Detail'!R5+'Meter2 TOU Detail'!R5)/('Meter1 TOU Detail'!Q5+'Meter2 TOU Detail'!Q5),0) -> 0.031974451 | T13: =IFERROR(('Meter1 TOU Detail'!N5+'Meter2 TOU Detail'!N5)/('Meter1 TOU Detail'!M5+'Meter2 TOU Detail'!M5),0) -> 0.18494149 | U13: =R13*S13 -> 0 | V13: =J13*T13 -> 0 | W13: =V13-U13 -> 0
A14: Nov | B14: ='ESS Sizing'!B6 -> 32 | C14: ='PV Production'!B15 -> 61096 | D14: ='PV Production'!G15 -> 42779.9 | E14: =MIN(C14,D14) -> 42779.9 | F14: =MAX(D14-C14,0) -> 0 | G14: ='ESS Sizing'!E6 -> 1654 | H14: ='ESS Sizing'!I6*Recommendation!B9 -> 367.7184 | I14: =MIN(F14,G14,H14*B14) -> 0 | J14: =MAX(MIN(G14,H14*B14)-I14,0) -> 1654 | K14: =I14+J14 -> 1654 | L14: =K14/D14 -> 0.038663017 | M14: ='Combined TOU Profile'!M6 -> 622 | N14: ='Demand Charge'!$B$20 -> 100 | O14: ='Demand Charge'!Q5 -> 2623.63 | P14: =(E14+I14)*Financial!$B$17 -> 3950.5662 | Q14: =MAX(F14-I14,0)*'Model Assumptions'!$C$16 -> 0 | R14: =J14/'Model Assumptions'!$C$13 -> 1837.7778 | S14: =IFERROR(('Meter1 TOU Detail'!R6+'Meter2 TOU Detail'!R6)/('Meter1 TOU Detail'!Q6+'Meter2 TOU Detail'!Q6),0) -> 0.031722169 | T14: =IFERROR(('Meter1 TOU Detail'!N6+'Meter2 TOU Detail'!N6)/('Meter1 TOU Detail'!M6+'Meter2 TOU Detail'!M6),0) -> 0.19887545 | U14: =R14*S14 -> 58.298298 | V14: =J14*T14 -> 328.94 | W14: =V14-U14 -> 270.6417
A15: Dec | B15: ='ESS Sizing'!B7 -> 30 | C15: ='PV Production'!B16 -> 53252 | D15: ='PV Production'!G16 -> 36989.32 | E15: =MIN(C15,D15) -> 36989.32 | F15: =MAX(D15-C15,0) -> 0 | G15: ='ESS Sizing'!E7 -> 2024 | H15: ='ESS Sizing'!I7*Recommendation!B9 -> 367.7184 | I15: =MIN(F15,G15,H15*B15) -> 0 | J15: =MAX(MIN(G15,H15*B15)-I15,0) -> 2024 | K15: =I15+J15 -> 2024 | L15: =K15/D15 -> 0.054718497 | M15: ='Combined TOU Profile'!M7 -> 513 | N15: ='Demand Charge'!$B$20 -> 100 | O15: ='Demand Charge'!Q6 -> 3154.3021 | P15: =(E15+I15)*Financial!$B$17 -> 3415.8275 | Q15: =MAX(F15-I15,0)*'Model Assumptions'!$C$16 -> 0 | R15: =J15/'Model Assumptions'!$C$13 -> 2248.8889 | S15: =IFERROR(('Meter1 TOU Detail'!R7+'Meter2 TOU Detail'!R7)/('Meter1 TOU Detail'!Q7+'Meter2 TOU Detail'!Q7),0) -> 0.032227571 | T15: =IFERROR(('Meter1 TOU Detail'!N7+'Meter2 TOU Detail'!N7)/('Meter1 TOU Detail'!M7+'Meter2 TOU Detail'!M7),0) -> 0.20001482 | U15: =R15*S15 -> 72.476227 | V15: =J15*T15 -> 404.83 | W15: =V15-U15 -> 332.35377
A16: Annual | B16: =SUM(B4:B15) -> 366 | C16: =SUM(C4:C15) -> 709501 | D16: =SUM(D4:D15) -> 710207.51 | E16: =SUM(E4:E15) -> 615927.45 | F16: =SUM(F4:F15) -> 94280.068 | G16: =SUM(G4:G15) -> 28085.162 | H16: =MAX(H4:H15) -> 367.7184 | I16: =SUM(I4:I15) -> 7736.1623 | J16: =SUM(J4:J15) -> 20349 | K16: =SUM(K4:K15) -> 28085.162 | L16: =K16/D16 -> 0.039545009 | M16: =MAX(M4:M15) -> 730 | N16: ='Demand Charge'!$B$20 -> 100 | O16: =SUM(O4:O15) -> 39372.753 | P16: =SUM(P4:P15) -> 57593.038 | Q16: =SUM(Q4:Q15) -> 4327.1953 | R16: =SUM(R4:R15) -> 22610 | S16: =IFERROR(U16/R16,0) -> 0.091901683 | T16: =IFERROR(V16/J16,0) -> 0.3484464 | U16: =SUM(U4:U15) -> 2077.8971 | V16: =SUM(V4:V15) -> 7090.5357 | W16: =SUM(W4:W15) -> 5012.6387
A19: Grid-charging estimate: for months where PV surplus is insufficient, the model charges the ESS in the lowest-price historical TOU bucket and discharges into the highest-price energy bucket. Summer uses Off-Peak → On-Peak; winter uses Super-Off-Peak → Mid-Peak. Rates are reconstructed directly from the two Barstow utility-account bill details as combined effective $/kWh = category energy charge / category kWh. Grid-charge input kWh = delivered grid-charged discharge / 95% screening discharge efficiency. Net arbitrage savings = avoided high-price energy cost − low-price charging cost. This is a billing-data-based estimate, not an interval dispatch simulation; it assumes the battery can schedule the identified energy into those TOU windows. Demand-charge savings are calculated separately and are not included in the arbitrage value.

Sheet Demand Charge
A1: ESS DEMAND-CHARGE SAVINGS — ACCOUNT-SPECIFIC
A3: Month | B3: Meter 1 Max kW | C3: Meter 1 Base Demand $ | D3: Meter 1 Base $/kW | E3: Meter 1 TOU Demand kW | F3: Meter 1 TOU Demand $ | G3: Meter 1 TOU $/kW | H3: Meter 2 Max kW | I3: Meter 2 Base Demand $ | J3: Meter 2 Base $/kW | K3: Meter 2 TOU Demand kW | L3: Meter 2 TOU Demand $ | M3: Meter 2 TOU $/kW | N3: ESS Target kW | O3: Meter 2 Base Savings $ | P3: Meter 2 TOU Savings $ | Q3: Meter 2 Total Demand Savings $
A4: ='Meter2 TOU Detail'!A5 -> Oct 2023 | B4: ='Meter1 TOU Detail'!S5 -> 32 | C4: ='Meter1 TOU Detail'!T5 -> 506.81 | D4: =IFERROR(C4/B4,0) -> 15.837813 | E4: =MAX('Meter1 TOU Detail'!U5,'Meter1 TOU Detail'!W5) -> 24 | F4: ='Meter1 TOU Detail'!V5+'Meter1 TOU Detail'!X5 -> 107.17 | G4: =IFERROR(F4/E4,0) -> 4.4654167 | H4: ='Meter2 TOU Detail'!S5 -> 552 | I4: ='Meter2 TOU Detail'!T5 -> 12811.13 | J4: =IFERROR(I4/H4,0) -> 23.208569 | K4: =MAX('Meter2 TOU Detail'!U5,'Meter2 TOU Detail'!W5) -> 142 | L4: ='Meter2 TOU Detail'!V5+'Meter2 TOU Detail'!X5 -> 805.13 | M4: =IFERROR(L4/K4,0) -> 5.6699296 | N4: =$B$20 -> 100 | O4: =MIN(N4,H4)*J4 -> 2320.8569 | P4: =MIN(N4,K4)*M4 -> 566.99296 | Q4: =O4+P4 -> 2887.8498
A5: ='Meter2 TOU Detail'!A6 -> Nov 2023 | B5: ='Meter1 TOU Detail'!S6 -> 39 | C5: ='Meter1 TOU Detail'!T6 -> 562.14 | D5: =IFERROR(C5/B5,0) -> 14.413846 | E5: =MAX('Meter1 TOU Detail'!U6,'Meter1 TOU Detail'!W6) -> 24 | F5: ='Meter1 TOU Detail'!V6+'Meter1 TOU Detail'!X6 -> 74.64 | G5: =IFERROR(F5/E5,0) -> 3.11 | H5: ='Meter2 TOU Detail'!S6 -> 622 | I5: ='Meter2 TOU Detail'!T6 -> 14032.88 | J5: =IFERROR(I5/H5,0) -> 22.5609 | K5: =MAX('Meter2 TOU Detail'!U6,'Meter2 TOU Detail'!W6) -> 47 | L5: ='Meter2 TOU Detail'!V6+'Meter2 TOU Detail'!X6 -> 367.54 | M5: =IFERROR(L5/K5,0) -> 7.82 | N5: =$B$20 -> 100 | O5: =MIN(N5,H5)*J5 -> 2256.09 | P5: =MIN(N5,K5)*M5 -> 367.54 | Q5: =O5+P5 -> 2623.63
A6: ='Meter2 TOU Detail'!A7 -> Dec 2023 | B6: ='Meter1 TOU Detail'!S7 -> 43 | C6: ='Meter1 TOU Detail'!T7 -> 618.36 | D6: =IFERROR(C6/B6,0) -> 14.380465 | E6: =MAX('Meter1 TOU Detail'!U7,'Meter1 TOU Detail'!W7) -> 26 | F6: ='Meter1 TOU Detail'!V7+'Meter1 TOU Detail'!X7 -> 80.86 | G6: =IFERROR(F6/E6,0) -> 3.11 | H6: ='Meter2 TOU Detail'!S7 -> 513 | I6: ='Meter2 TOU Detail'!T7 -> 12169.91 | J6: =IFERROR(I6/H6,0) -> 23.723021 | K6: =MAX('Meter2 TOU Detail'!U7,'Meter2 TOU Detail'!W7) -> 115 | L6: ='Meter2 TOU Detail'!V7+'Meter2 TOU Detail'!X7 -> 899.3 | M6: =IFERROR(L6/K6,0) -> 7.82 | N6: =$B$20 -> 100 | O6: =MIN(N6,H6)*J6 -> 2372.3021 | P6: =MIN(N6,K6)*M6 -> 782 | Q6: =O6+P6 -> 3154.3021
A7: ='Meter2 TOU Detail'!A8 -> Jan 2024 | B7: ='Meter1 TOU Detail'!S8 -> 44 | C7: ='Meter1 TOU Detail'!T8 -> 628.02 | D7: =IFERROR(C7/B7,0) -> 14.273182 | E7: =MAX('Meter1 TOU Detail'!U8,'Meter1 TOU Detail'!W8) -> 24 | F7: ='Meter1 TOU Detail'!V8+'Meter1 TOU Detail'!X8 -> 69.9 | G7: =IFERROR(F7/E7,0) -> 2.9125 | H7: ='Meter2 TOU Detail'!S8 -> 655 | I7: ='Meter2 TOU Detail'!T8 -> 15251.57 | J7: =IFERROR(I7/H7,0) -> 23.28484 | K7: =MAX('Meter2 TOU Detail'!U8,'Meter2 TOU Detail'!W8) -> 43 | L7: ='Meter2 TOU Detail'!V8+'Meter2 TOU Detail'!X8 -> 315.19 | M7: =IFERROR(L7/K7,0) -> 7.33 | N7: =$B$20 -> 100 | O7: =MIN(N7,H7)*J7 -> 2328.484 | P7: =MIN(N7,K7)*M7 -> 315.19 | Q7: =O7+P7 -> 2643.674
A8: ='Meter2 TOU Detail'!A9 -> Feb 2024 | B8: ='Meter1 TOU Detail'!S9 -> 46 | C8: ='Meter1 TOU Detail'!T9 -> 663.94 | D8: =IFERROR(C8/B8,0) -> 14.433478 | E8: =MAX('Meter1 TOU Detail'!U9,'Meter1 TOU Detail'!W9) -> 27 | F8: ='Meter1 TOU Detail'!V9+'Meter1 TOU Detail'!X9 -> 75.6 | G8: =IFERROR(F8/E8,0) -> 2.8 | H8: ='Meter2 TOU Detail'!S9 -> 640 | I8: ='Meter2 TOU Detail'!T9 -> 15223.5 | J8: =IFERROR(I8/H8,0) -> 23.786719 | K8: =MAX('Meter2 TOU Detail'!U9,'Meter2 TOU Detail'!W9) -> 46 | L8: ='Meter2 TOU Detail'!V9+'Meter2 TOU Detail'!X9 -> 324.3 | M8: =IFERROR(L8/K8,0) -> 7.05 | N8: =$B$20 -> 100 | O8: =MIN(N8,H8)*J8 -> 2378.6719 | P8: =MIN(N8,K8)*M8 -> 324.3 | Q8: =O8+P8 -> 2702.9719
A9: ='Meter2 TOU Detail'!A10 -> Mar 2024 | B9: ='Meter1 TOU Detail'!S10 -> 36 | C9: ='Meter1 TOU Detail'!T10 -> 510.71 | D9: =IFERROR(C9/B9,0) -> 14.186389 | E9: =MAX('Meter1 TOU Detail'!U10,'Meter1 TOU Detail'!W10) -> 16 | F9: ='Meter1 TOU Detail'!V10+'Meter1 TOU Detail'!X10 -> 44.8 | G9: =IFERROR(F9/E9,0) -> 2.8 | H9: ='Meter2 TOU Detail'!S10 -> 500 | I9: ='Meter2 TOU Detail'!T10 -> 12987.94 | J9: =IFERROR(I9/H9,0) -> 25.97588 | K9: =MAX('Meter2 TOU Detail'!U10,'Meter2 TOU Detail'!W10) -> 170 | L9: ='Meter2 TOU Detail'!V10+'Meter2 TOU Detail'!X10 -> 1199.67 | M9: =IFERROR(L9/K9,0) -> 7.0568824 | N9: =$B$20 -> 100 | O9: =MIN(N9,H9)*J9 -> 2597.588 | P9: =MIN(N9,K9)*M9 -> 705.68824 | Q9: =O9+P9 -> 3303.2762
A10: ='Meter2 TOU Detail'!A11 -> Apr 2024 | B10: ='Meter1 TOU Detail'!S11 -> 28 | C10: ='Meter1 TOU Detail'!T11 -> 420.28 | D10: =IFERROR(C10/B10,0) -> 15.01 | E10: =MAX('Meter1 TOU Detail'!U11,'Meter1 TOU Detail'!W11) -> 20 | F10: ='Meter1 TOU Detail'!V11+'Meter1 TOU Detail'!X11 -> 56 | G10: =IFERROR(F10/E10,0) -> 2.8 | H10: ='Meter2 TOU Detail'!S11 -> 442 | I10: ='Meter2 TOU Detail'!T11 -> 11164.64 | J10: =IFERROR(I10/H10,0) -> 25.259367 | K10: =MAX('Meter2 TOU Detail'!U11,'Meter2 TOU Detail'!W11) -> 97 | L10: ='Meter2 TOU Detail'!V11+'Meter2 TOU Detail'!X11 -> 684.82 | M10: =IFERROR(L10/K10,0) -> 7.06 | N10: =$B$20 -> 100 | O10: =MIN(N10,H10)*J10 -> 2525.9367 | P10: =MIN(N10,K10)*M10 -> 684.82 | Q10: =O10+P10 -> 3210.7567
A11: ='Meter2 TOU Detail'!A12 -> May 2024 | B11: ='Meter1 TOU Detail'!S12 -> 34.5 | C11: ='Meter1 TOU Detail'!T12 -> 553.21 | D11: =IFERROR(C11/B11,0) -> 16.035072 | E11: =MAX('Meter1 TOU Detail'!U12,'Meter1 TOU Detail'!W12) -> 29 | F11: ='Meter1 TOU Detail'!V12+'Meter1 TOU Detail'!X12 -> 179.97 | G11: =IFERROR(F11/E11,0) -> 6.2058621 | H11: ='Meter2 TOU Detail'!S12 -> 466 | I11: ='Meter2 TOU Detail'!T12 -> 11641.9 | J11: =IFERROR(I11/H11,0) -> 24.982618 | K11: =MAX('Meter2 TOU Detail'!U12,'Meter2 TOU Detail'!W12) -> 84 | L11: ='Meter2 TOU Detail'!V12+'Meter2 TOU Detail'!X12 -> 593.04 | M11: =IFERROR(L11/K11,0) -> 7.06 | N11: =$B$20 -> 100 | O11: =MIN(N11,H11)*J11 -> 2498.2618 | P11: =MIN(N11,K11)*M11 -> 593.04 | Q11: =O11+P11 -> 3091.3018
A12: ='Meter2 TOU Detail'!A13 -> Jun 2024 | B12: ='Meter1 TOU Detail'!S13 -> 41 | C12: ='Meter1 TOU Detail'!T13 -> 686.14 | D12: =IFERROR(C12/B12,0) -> 16.735122 | E12: =MAX('Meter1 TOU Detail'!U13,'Meter1 TOU Detail'!W13) -> 29 | F12: ='Meter1 TOU Detail'!V13+'Meter1 TOU Detail'!X13 -> 150.66 | G12: =IFERROR(F12/E12,0) -> 5.1951724 | H12: ='Meter2 TOU Detail'!S13 -> 471 | I12: ='Meter2 TOU Detail'!T13 -> 11775.4 | J12: =IFERROR(I12/H12,0) -> 25.000849 | K12: =MAX('Meter2 TOU Detail'!U13,'Meter2 TOU Detail'!W13) -> 36 | L12: ='Meter2 TOU Detail'!V13+'Meter2 TOU Detail'!X13 -> 539.38 | M12: =IFERROR(L12/K12,0) -> 14.982778 | N12: =$B$20 -> 100 | O12: =MIN(N12,H12)*J12 -> 2500.0849 | P12: =MIN(N12,K12)*M12 -> 539.38 | Q12: =O12+P12 -> 3039.4649
A13: ='Meter2 TOU Detail'!A14 -> Jul 2024 | B13: ='Meter1 TOU Detail'!S14 -> 51 | C13: ='Meter1 TOU Detail'!T14 -> 944.34 | D13: =IFERROR(C13/B13,0) -> 18.516471 | E13: =MAX('Meter1 TOU Detail'!U14,'Meter1 TOU Detail'!W14) -> 41 | F13: ='Meter1 TOU Detail'!V14+'Meter1 TOU Detail'!X14 -> 276.75 | G13: =IFERROR(F13/E13,0) -> 6.75 | H13: ='Meter2 TOU Detail'!S14 -> 725 | I13: ='Meter2 TOU Detail'!T14 -> 18496 | J13: =IFERROR(I13/H13,0) -> 25.511724 | K13: =MAX('Meter2 TOU Detail'!U14,'Meter2 TOU Detail'!W14) -> 53 | L13: ='Meter2 TOU Detail'!V14+'Meter2 TOU Detail'!X14 -> 1139.5 | M13: =IFERROR(L13/K13,0) -> 21.5 | N13: =$B$20 -> 100 | O13: =MIN(N13,H13)*J13 -> 2551.1724 | P13: =MIN(N13,K13)*M13 -> 1139.5 | Q13: =O13+P13 -> 3690.6724
A14: ='Meter2 TOU Detail'!A15 -> Aug 2024 | B14: ='Meter1 TOU Detail'!S15 -> 50 | C14: ='Meter1 TOU Detail'!T15 -> 931.25 | D14: =IFERROR(C14/B14,0) -> 18.625 | E14: =MAX('Meter1 TOU Detail'!U15,'Meter1 TOU Detail'!W15) -> 41 | F14: ='Meter1 TOU Detail'!V15+'Meter1 TOU Detail'!X15 -> 276.75 | G14: =IFERROR(F14/E14,0) -> 6.75 | H14: ='Meter2 TOU Detail'!S15 -> 705 | I14: ='Meter2 TOU Detail'!T15 -> 18490.2 | J14: =IFERROR(I14/H14,0) -> 26.227234 | K14: =MAX('Meter2 TOU Detail'!U15,'Meter2 TOU Detail'!W15) -> 75 | L14: ='Meter2 TOU Detail'!V15+'Meter2 TOU Detail'!X15 -> 1612.5 | M14: =IFERROR(L14/K14,0) -> 21.5 | N14: =$B$20 -> 100 | O14: =MIN(N14,H14)*J14 -> 2622.7234 | P14: =MIN(N14,K14)*M14 -> 1612.5 | Q14: =O14+P14 -> 4235.2234
A15: ='Meter2 TOU Detail'!A16 -> Sep 2024 | B15: ='Meter1 TOU Detail'!S16 -> 47 | C15: ='Meter1 TOU Detail'!T16 -> 804.23 | D15: =IFERROR(C15/B15,0) -> 17.111277 | E15: =MAX('Meter1 TOU Detail'!U16,'Meter1 TOU Detail'!W16) -> 28 | F15: ='Meter1 TOU Detail'!V16+'Meter1 TOU Detail'!X16 -> 189 | G15: =IFERROR(F15/E15,0) -> 6.75 | H15: ='Meter2 TOU Detail'!S16 -> 730 | I15: ='Meter2 TOU Detail'!T16 -> 19583.2 | J15: =IFERROR(I15/H15,0) -> 26.826301 | K15: =MAX('Meter2 TOU Detail'!U16,'Meter2 TOU Detail'!W16) -> 98 | L15: ='Meter2 TOU Detail'!V16+'Meter2 TOU Detail'!X16 -> 2107 | M15: =IFERROR(L15/K15,0) -> 21.5 | N15: =$B$20 -> 100 | O15: =MIN(N15,H15)*J15 -> 2682.6301 | P15: =MIN(N15,K15)*M15 -> 2107 | Q15: =O15+P15 -> 4789.6301
A16: Annual / Max | B16: =MAX(B4:B15) -> 51 | C16: =SUM(C4:C15) -> 7829.43 | E16: =MAX(E4:E15) -> 41 | F16: =SUM(F4:F15) -> 1582.1 | H16: =MAX(H4:H15) -> 730 | I16: =SUM(I4:I15) -> 173628.27 | K16: =MAX(K4:K15) -> 170 | L16: =SUM(L4:L15) -> 10587.37 | O16: =SUM(O4:O15) -> 29634.802 | P16: =SUM(P4:P15) -> 9737.9512 | Q16: =SUM(Q4:Q15) -> 39372.753
A19: Demand-Shave Design Basis | B19: Value | C19: Unit | D19: Basis | E19: Status | F19: Interpretation | H19: Scenario | I19: Target Shave kW | J19: Annual Base Demand Savings | K19: Annual TOU Demand Savings | L19: Annual Total Demand Savings | M19: Comment
A20: Proposal target | B20: 100 | C20: kW | D20: Fixed target applied to Meter 2 account | E20: Recommended base | F20: Fixed demand-shave target for proposal modeling. | H20: Conservative | I20: 50 | J20: =SUM(MIN(I20,H4)*J4,MIN(I20,H5)*J5,MIN(I20,H6)*J6,MIN(I20,H7)*J7,MIN(I20,H8)*J8,MIN(I20,H9)*J9,MIN(I20,H10)*J10,MIN(I20,H11)*J11,MIN(I20,H12)*J12,MIN(I20,H13)*J13,MIN(I20,H14)*J14,MIN(I20,H15)*J15) -> 14817.401 | K20: =SUM(MIN(I20,K4)*M4,MIN(I20,K5)*M5,MIN(I20,K6)*M6,MIN(I20,K7)*M7,MIN(I20,K8)*M8,MIN(I20,K9)*M9,MIN(I20,K10)*M10,MIN(I20,K11)*M11,MIN(I20,K12)*M12,MIN(I20,K13)*M13,MIN(I20,K14)*M14,MIN(I20,K15)*M15) -> 6504.7506 | L20: =J20+K20 -> 21322.152 | M20: Low-risk screening case
A21: Battery-side screening power | B21: 215.04 | C21: kW | D21: 2 × 215.04 kWh × 0.5C | E21: Derived from product specs | F21: Upper battery-side power basis only. | H21: Recommended Base | I21: 100 | J21: =SUM(MIN(I21,H4)*J4,MIN(I21,H5)*J5,MIN(I21,H6)*J6,MIN(I21,H7)*J7,MIN(I21,H8)*J8,MIN(I21,H9)*J9,MIN(I21,H10)*J10,MIN(I21,H11)*J11,MIN(I21,H12)*J12,MIN(I21,H13)*J13,MIN(I21,H14)*J14,MIN(I21,H15)*J15) -> 29634.802 | K21: =SUM(MIN(I21,K4)*M4,MIN(I21,K5)*M5,MIN(I21,K6)*M6,MIN(I21,K7)*M7,MIN(I21,K8)*M8,MIN(I21,K9)*M9,MIN(I21,K10)*M10,MIN(I21,K11)*M11,MIN(I21,K12)*M12,MIN(I21,K13)*M13,MIN(I21,K14)*M14,MIN(I21,K15)*M15) -> 9737.9512 | L21: =J21+K21 -> 39372.753 | M21: Use in proposal
A22: Delivered ESS energy | B22: 367.7184 | C22: kWh/day-cycle | D22: 430.08 × 90% × 95% | E22: Derived from assumptions | F22: Energy available for dispatch | H22: 3-hour energy-backed | I22: 122.5728 | J22: =SUM(MIN(I22,H4)*J4,MIN(I22,H5)*J5,MIN(I22,H6)*J6,MIN(I22,H7)*J7,MIN(I22,H8)*J8,MIN(I22,H9)*J9,MIN(I22,H10)*J10,MIN(I22,H11)*J11,MIN(I22,H12)*J12,MIN(I22,H13)*J13,MIN(I22,H14)*J14,MIN(I22,H15)*J15) -> 36324.207 | K22: =SUM(MIN(I22,K4)*M4,MIN(I22,K5)*M5,MIN(I22,K6)*M6,MIN(I22,K7)*M7,MIN(I22,K8)*M8,MIN(I22,K9)*M9,MIN(I22,K10)*M10,MIN(I22,K11)*M11,MIN(I22,K12)*M12,MIN(I22,K13)*M13,MIN(I22,K14)*M14,MIN(I22,K15)*M15) -> 10142.531 | L22: =J22+K22 -> 46466.738 | M22: Derived from delivered ESS energy / 3 h
A23: 1-hour energy-backed shave | B23: =MIN(B21,B22/1) -> 215.04 | C23: kW | D23: min(power, delivered kWh / 1h) | E23: Derived | F23: Power-limited. | H23: 2-hour energy-backed | I23: 183.8592 | J23: =SUM(MIN(I23,H4)*J4,MIN(I23,H5)*J5,MIN(I23,H6)*J6,MIN(I23,H7)*J7,MIN(I23,H8)*J8,MIN(I23,H9)*J9,MIN(I23,H10)*J10,MIN(I23,H11)*J11,MIN(I23,H12)*J12,MIN(I23,H13)*J13,MIN(I23,H14)*J14,MIN(I23,H15)*J15) -> 54486.31 | K23: =SUM(MIN(I23,K4)*M4,MIN(I23,K5)*M5,MIN(I23,K6)*M6,MIN(I23,K7)*M7,MIN(I23,K8)*M8,MIN(I23,K9)*M9,MIN(I23,K10)*M10,MIN(I23,K11)*M11,MIN(I23,K12)*M12,MIN(I23,K13)*M13,MIN(I23,K14)*M14,MIN(I23,K15)*M15) -> 10587.37 | L23: =J23+K23 -> 65073.68 | M23: Derived from delivered ESS energy / 2 h
A24: 2-hour energy-backed shave | B24: =MIN(B21,B22/2) -> 183.8592 | C24: kW | D24: min(power, delivered kWh / 2h) | E24: Derived | F24: 183.86 kW. | H24: Battery-side power upper bound | I24: 215.04 | J24: =SUM(MIN(I24,H4)*J4,MIN(I24,H5)*J5,MIN(I24,H6)*J6,MIN(I24,H7)*J7,MIN(I24,H8)*J8,MIN(I24,H9)*J9,MIN(I24,H10)*J10,MIN(I24,H11)*J11,MIN(I24,H12)*J12,MIN(I24,H13)*J13,MIN(I24,H14)*J14,MIN(I24,H15)*J15) -> 63726.679 | K24: =SUM(MIN(I24,K4)*M4,MIN(I24,K5)*M5,MIN(I24,K6)*M6,MIN(I24,K7)*M7,MIN(I24,K8)*M8,MIN(I24,K9)*M9,MIN(I24,K10)*M10,MIN(I24,K11)*M11,MIN(I24,K12)*M12,MIN(I24,K13)*M13,MIN(I24,K14)*M14,MIN(I24,K15)*M15) -> 10587.37 | L24: =J24+K24 -> 74314.049 | M24: Theoretical screening upper bound; not verified AC PCS output
A25: 3-hour energy-backed shave | B25: =MIN(B21,B22/3) -> 122.5728 | C25: kW | D25: min(power, delivered kWh / 3h) | E25: Derived | F25: 122.57 kW.
H27: Account / Configuration | I27: ESS Power Allocation | J27: Annual Base Savings | K27: Annual TOU Savings | L27: Annual Total | M27: Interpretation
H28: Meter 2 only — modeling basis | I28: 100 | J28: =SUM(MIN(I28,H4)*J4,MIN(I28,H5)*J5,MIN(I28,H6)*J6,MIN(I28,H7)*J7,MIN(I28,H8)*J8,MIN(I28,H9)*J9,MIN(I28,H10)*J10,MIN(I28,H11)*J11,MIN(I28,H12)*J12,MIN(I28,H13)*J13,MIN(I28,H14)*J14,MIN(I28,H15)*J15) -> 29634.802 | K28: =SUM(MIN(I28,K4)*M4,MIN(I28,K5)*M5,MIN(I28,K6)*M6,MIN(I28,K7)*M7,MIN(I28,K8)*M8,MIN(I28,K9)*M9,MIN(I28,K10)*M10,MIN(I28,K11)*M11,MIN(I28,K12)*M12,MIN(I28,K13)*M13,MIN(I28,K14)*M14,MIN(I28,K15)*M15) -> 9737.9512 | L28: =J28+K28 -> 39372.753 | M28: Economically dominant account; proposal basis
H29: Meter 2 only — 100 kW target | I29: 100 | J29: =SUM(MIN(I29,B4)*D4,MIN(I29,B5)*D5,MIN(I29,B6)*D6,MIN(I29,B7)*D7,MIN(I29,B8)*D8,MIN(I29,B9)*D9,MIN(I29,B10)*D10,MIN(I29,B11)*D11,MIN(I29,B12)*D12,MIN(I29,B13)*D13,MIN(I29,B14)*D14,MIN(I29,B15)*D15) -> 7829.43 | K29: =SUM(MIN(I29,E4)*G4,MIN(I29,E5)*G5,MIN(I29,E6)*G6,MIN(I29,E7)*G7,MIN(I29,E8)*G8,MIN(I29,E9)*G9,MIN(I29,E10)*G10,MIN(I29,E11)*G11,MIN(I29,E12)*G12,MIN(I29,E13)*G13,MIN(I29,E14)*G14,MIN(I29,E15)*G15) -> 1582.1 | L29: =J29+K29 -> 9411.53 | M29: Power exceeds account monthly demand; theoretical bill-derived ceiling is much lower than Meter 2.
H30: One 107.52-kW battery-side unit per account | I30: 107.52 | J30: =SUM(MIN(I30,H4)*J4,MIN(I30,H5)*J5,MIN(I30,H6)*J6,MIN(I30,H7)*J7,MIN(I30,H8)*J8,MIN(I30,H9)*J9,MIN(I30,H10)*J10,MIN(I30,H11)*J11,MIN(I30,H12)*J12,MIN(I30,H13)*J13,MIN(I30,H14)*J14,MIN(I30,H15)*J15,MIN(I30,B4)*D4,MIN(I30,B5)*D5,MIN(I30,B6)*D6,MIN(I30,B7)*D7,MIN(I30,B8)*D8,MIN(I30,B9)*D9,MIN(I30,B10)*D10,MIN(I30,B11)*D11,MIN(I30,B12)*D12,MIN(I30,B13)*D13,MIN(I30,B14)*D14,MIN(I30,B15)*D15) -> 39692.769 | K30: =SUM(MIN(I30,K4)*M4,MIN(I30,K5)*M5,MIN(I30,K6)*M6,MIN(I30,K7)*M7,MIN(I30,K8)*M8,MIN(I30,K9)*M9,MIN(I30,K10)*M10,MIN(I30,K11)*M11,MIN(I30,K12)*M12,MIN(I30,K13)*M13,MIN(I30,K14)*M14,MIN(I30,K15)*M15,MIN(I30,E4)*G4,MIN(I30,E5)*G5,MIN(I30,E6)*G6,MIN(I30,E7)*G7,MIN(I30,E8)*G8,MIN(I30,E9)*G9,MIN(I30,E10)*G10,MIN(I30,E11)*G11,MIN(I30,E12)*G12,MIN(I30,E13)*G13,MIN(I30,E14)*G14,MIN(I30,E15)*G15) -> 11474.563 | L30: =J30+K30 -> 51167.333 | M30: Illustrative only; requires separate/compatible interconnection behind each meter.
